Workbook
Name UO: #REF!
Name Z_3FBB35F5_DD50_484F_B77F_6029FD8823ED_.wvu.PrintArea: 'Effectif par niveau'!$A$22:$G$40
Name Z_3FBB35F5_DD50_484F_B77F_6029FD8823ED_.wvu.PrintTitles: 'Personnel Région 3 DRH'!$2:$2
Name Z_3FBB35F5_DD50_484F_B77F_6029FD8823ED_.wvu.PrintTitles: 'Personnel Région_1 DRH'!$2:$2
Name Z_3FBB35F5_DD50_484F_B77F_6029FD8823ED_.wvu.PrintTitles: 'Personnel Région_2 DRH'!$2:$2

Sheet Couleurs
A1: Signification des couleurs
C2: Non disponible
C4: Non applicable

Sheet Table des matières
A1: TABLE DES MATIERES
A3: Indicateurs PNDS et ODD | B3: pp 4-5
A4: Synthèse de quelques indicateurs | B4: pp 6-11
A5: Quelques indicateurs économiques | B5: p 12
A6: 1. INFORMATIONS GENERALES
A7: Quelques résultats d'enquête et des CNS | B7: p 14
A8: Indicateurs clés de planification familiale issus de l’enquête PMABF | B8: pp 15-16
A9: Population du Burkina Faso par groupe d'âge | B9: pp 17 - 18
A10: populations cibles par district | B10: pp 19 - 22
A11: Population selon la distance par district | B11: pp 23 - 24
A12: Complétude des rapports des formations sanitaires | B12: pp 25 - 36
A13: 2. ADMINISTRATION ET GESTION
A14: Bilan physique et financier des plans d'ations | B14: pp 38 - 44
A15: Disponibilité des MEG dans les formations sanitaires | B15: pp 45 - 46
A16: Disponibilité des MEG traceurs dans les DRD par régions | B16: pp 47 - 49
A17: Ruptures de stock des 25 medicaments traceurs dans les DMEG témoins/région | B17: p 50
A18: Quleques résultats de la gratuité des soins | B18: pp 51 - 52
A19: 3. RESSOURCES ET INFRASTRUCTURES
A20: Ressources humaines | B20: pp 54 - 67
A21: Infrastructures | B21: pp 68 - 75
A22: Situation des OBC par district | B22: pp 76 - 77
A23: Lits et occupation dans les formations sanitaires | B23: pp 78 - 83
A24: rayon moyen d'action théorique (RMAT) | B24: pp 84 - 85
A25: Ratio habitant/CSPS | B25: pp 86 - 87
A26: 4. ACTIVITES DANS LES FORMATIONS SANITAIRES
A27: Couvertures vaccinales par antigène | B27: pp 89 - 102
A28: Vaccination contre la covid-19 | B28: pp 103 - 104
A29: Activités de santé maternelle et infantile | B29: pp 105 - 162
A30: Prévention de la transmission mère enfant du VIH | B30: pp 163 - 177
A31: Surveillance nutritionnelle et prise en charge de la nutrition | B31: pp 178 - 198
A32: Fréquentation des formations sanitaires, références/contre-références | B32: pp 199 - 271
A33: Paludisme | B33: pp 272 - 297
A34: Infections sexuellement transmissibles (IST) ,dépistage VIH/SIDA et hépatites | B34: pp 298 - 303
A35: File active du VIH et AELB | B35: pp 304 - 308
A36: Tuberculose | B36: pp 309 - 324
A37: MTN | B37: pp 325 - 335
A38: Surveillance épidémiologique | B38: pp 336 - 353
... A47: ANSSEAT | B47: pp 405
A48: 5. ACTIVITES DE SANTE COMMUNAUTAIRE
A49: Situation des ASBC récrutés par district | B49: pp 407 - 408
A50: Complétude des formulaires ASBC par district | B50: pp 409
A51: Nombre de séance d'IEC/CCC réalisé par les ASBC | B51: pp 410 - 421
A52: Distribution des méthodes contraceptives par les ASBC | B52: pp 422 - 424
A53: Accompagnement de la grossesse, l’accouchement et le post partum | B53: pp 425 - 427
A54: Recherche de perdus de vue à la vaccination | B54: pp 428 - 429
A55: Réalisation des activités de GASPA par district | B55: pp 430 - 433
A56: Dépistage et prise en charge de la malnutrition aiguë par les ASBC | B56: pp 434 - 435
A57: Diagnostic et prise en charge du paludisme par les ASBC | B57: pp 436 - 441
A58: Prise en charge de la diarrhée et de la toux par les ASBC | B58: pp 442 - 445
A59: TPI communautaire | B59: pp 446 - 447
A60: Decès en communauté notifiés par les ASBC | B60: pp 448 - 449

Sheet indicateursPNDS_ODD
A1: Tableau 0.01: indicateurs PNDS et ODD
A2: Indicateurs | B2: 2021 | C2: 2022 | D2: 2023 | E2: 2024 | F2: 2025 | G2: Sources de données | H2: Structure
A3: Ratio de mortalité maternelle pour 100 000 naissances vivantes | G3: Rapport EDS 2021 | H3: DGESS
A4: Taux de mortalité néonatale (‰) | G4: Rapport EDS 2021 | H4: DGESS
A5: Taux de mortalité infantile (‰) | G5: Rapport EDS 2021 | H5: DGESS
A6: Proportion des recommandations du CSD mises en œuvre dans les délais (%) | G6: Rapport CSD | H6: DPPSE
A7: Taux de satisfaction des usagers des services de santé (%) | G7: Rpport HHFA 2020 | H7: DSSE
A8: Proportion des structures ayant une performance globale satisfaisante (%) | G8: Rapport d'évaluation | H8: DDII
A9: Taux de complétude des saisies des rapports d’activités des formations sanitaires privés et publiques de soins | F9: =Complétude!K108 | G9: Annuaire statistique | H9: DSSE
A10: Taux de promptitude des saisies des rapports d’activités des formations sanitaires privés et publiques de soins | F10: =Complétude!M108 | G10: Annuaire statistique | H10: DSSE
A11: Densité des professionnels de santé pour 10 000 habitants | G11: Rpport HHFA 2020 | H11: DSSE
A12: Ratio population/médecin | F12: ='Evolution Effectif personnel'!F13 -> 0 | G12: Annuaire Statistique | H12: DRH
A13: Ratio population /Sage- femme-Maïeuticien | F13: ='Evolution Effectif personnel'!F17 -> 0 | G13: Annuaire Statistique | H13: DRH
A14: Proportion des CMA disposant d’au moins 2 médecins formés en Chirurgie essentielle | G14: Rapports d'activités | H14: DDSS
A15: Dépenses de santé des ménages en % des dépenses courantes de santé | F15: =IF(IndicateursEconomiques!#REF!="","",IndicateursEconomiques!#REF!) -> #REF! | G15: Comptes de santé | H15: DSSE
A16: Nombre de nouveaux contacts par habitant et par an des enfants de moins de 5 ans | F16: ='Nb_nouveau contact'!E107 | G16: Annuaire statistique MS | H16: DSSE
A17: Prévalence contraceptive (chez les femmes en union) (%) | F17: 32 | G17: PMA2020, EDS 2021 | H17: DSSE
A18: Taux de mortalité maternelle intra hospitalière pour 100 000 parturientes | F18: ='Taux de décès maternel'!F107 | G18: Annuaire statistique MS | H18: DSF
A19: Incidence du paludisme confirmé (pour 1000 hbts) | F19: ='Incidence paludisme confirmé'!F107 | G19: Annuaire statistique MS | H19: DSSE
A20: Taux de transmission résiduelle du VIH de la mère à l'enfant (%) | F20: 2.9229407 | G20: Enquête de séroprévalence | H20: PSLSS
A21: Prévalence de la malnutrition aiguë sévère chez les enfants de moins de 5 ans (%) | F21: 0.1 | G21: Rapport ENN | H21: DN
A22: Taux de notification de nouveaux cas de tuberculose toute forme et rechute (pour 100 000 habitants) | F22: ='Notification TB_Dépist TBVIH'!J108 | G22: Annuaire statistique MS | H22: PNT
A23: Part du budget alloué au MS | F23: 11.79 | H23: DGF santé
A24: Part du budget alloué au Secteur Santé | F24: 11.96 | H24: DGF santé
A25: Taux d'exécution des ressources financières (%) | F25: ='Bilan PA _2'!I159 | G25: Bilan des PA | H25: DPPSE
A26: Score moyen de la disponibilité des éléments de la capacité opérationnelle pour les SONUB (%) | G26: Rapport enquête HHFA | H26: DSSE
A27: Proportion de la population vivant à moins de 5 km d’une formation sanitaire (%) | F27: ='Pop_distance '!G108 | G27: Annuaire statistique | H27: DSSE
A28: Pourcentage des DMEG n'ayant pas connu de rupture des 25 molécules traceurs (%) | F28: =Rupture_DMEG!E86 | G28: Annuaire statistique | H28: DGAP
A29: Pourcentage des hôpitaux publics où la pharmacie hospitalière est fonctionnelle (%) | G29: Rapport d'activités DPH | H29: DPH
A30: Proportion des CM/CMA n’ayant pas connu de rupture des examens traceurs (%) | G30: Rapport d'activités | H30: DLBM
A31: Taux de satisfaction des demandes (utilisateurs) en PSL (%) | F31: =+CNTS5!D13 -> 67.593366 | G31: Annuaire statistique CNTS | H31: CNTS
A32: Pourcentage des femmes ayant reçu au moins 3 doses de traitement préventif intermittent pendant les consultations prénatales (%) | F32: ='Couverture CPN'!J107 | G32: Annuaire statistique MS | H32: SP-Palu
A33: Nombre de districts exclus du traitement de la filariose lymphatique | F33: 67 | G33: Annuaire statistique MS | H33: DPSP
A34: Pourcentage de femmes enceintes dépistées positives pour le VIH qui reçoivent un traitement ARV adapté | F34: ='synthèse indicateurs'!F98 -> 0 | G34: Annuaire statistique MS | H34: DSF
A35: Taux de succès aux traitements antituberculeux | F35: ='Traitement TB'!J108 | G35: Annuaire statistique MS | H35: PNT
A36: Pourcentage des femmes de 30 à 49 ans qui ont été soumises à un dépistage du cancer du col de l’utérus par les méthodes appropriées (inspection visuelle après application d’acide acétique/vinaigre et au Lugol (IVA/IVL), frottis (test de Pap), test VPH (virus du papillome humain) (%) | G36: Rapport enquête STEPS | H36: DPCM
A37: Proportion des formations sanitaires mettant en œuvre l’approche WHO-PEN | F37: 21.9 | G37: Rapport d’activités | H37: DSSE
A38: Létalité du paludisme grave chez les enfants de moins de 5 ans | F38: =Palu_létalité!G107 | G38: Annuaire statistique MS | H38: DSSE
A39: Taux de couverture en CPN4 et plus (%) | F39: ='Couverture CPN'!I107 | G39: Annuaire statistique MS | H39: DSSE
A40: Taux de couverture en RR2 (%) | F40: ='Couverture vaccinale2'!J107 | G40: Annuaire statistique MS | H40: DSSE
A41: Taux d’accouchements (%) | F41: =Accouchement!H107 | G41: Annuaire statistique MS | H41: DSSE
A42: Taux d’utilisation des méthodes contraceptives (%) | F42: ='UtilisatricePF '!J108 | G42: Annuaire statistique MS | H42: DSSE
A43: Proportion d’enfants pris en charge selon l'approche PCIME (%) | F43: =#REF! -> #REF! | G43: Annuaire statistique MS | H43: DSSE
A44: Pourcentage des faibles poids à la naissance (poids <2,5kg) | F44: =Naissances!H107 | G44: Annuaire statistique MS | H44: DSSE
A45: Taux de guérison de la MAS en interne (%) | F45: ='Nutrition 2'!I108 | G45: Annuaire statistique MS | H45: DN
A46: Proportion de la population consommant au moins 5 portions de fruits et légumes/jour | G46: Enquête STEPS | H46: DPCM
A47: Proportion de la population de 40 à 69 ans ayant un risque supérieur ou égal à 30% de développer une maladie cardiovasculaire pendant les 10 prochaines années ou ayant une maladie cardiovasculaire existante (%) | G47: Enquête STEPS | H47: DPCM
A48: Taux de couverture en Penta 3 | F48: ='Couverture vaccinale1'!K107 | G48: Annuaire statistique | H48: DSSE
A49: Demande contraceptive satisfaite par des méthodes modernes (%) | G49: PMA | H49: DSF
A50: Proportion d’enfants de 6-23 mois ayant une alimentation minimum acceptable (%) | F50: 26.2 | G50: Rapport ENN | H50: DN
A51: Pourcentage de formations sanitaires disposant d’une source d’eau potable | G51: Rapport HeRAMS | H51: DGOS
A52: Taux de létalité liée à une maladie d'urgence en santé publique (Covid-19) | F52: =+'MPE(suite2'!K87 | G52: TLOH | H52: DPSP
A53: Proportion des pathologies sous surveillance dont l’incidence est en dessous du seuil d’alerte | G53: Rapport de situation | H53: DPSP
A54: Proportion des hôpitaux disposant de plan blanc (%) | F54: 100 | G54: Rapport d'activité | H54: DFSP

Sheet synthèse indicateurs
A1: Tableau 0.02: Synthèse de quelques indicateurs
A2: Indicateurs | B2: 2021 | C2: 2022 | D2: 2023 | E2: 2024 | F2: 2025
A3: Démographie
A4: Population totale | B4: 21500559 | C4: 22184452 | D4: 22882385 | F4: =Population!F111 -> 0
A5: Population de moins de 5 ans | B5: 3933981 | C5: 4017780 | D5: 4090130 | F5: =Population!C111 -> 0
A6: Infrastructures Publiques
A7: Effectif des CHU | B7: 6 | C7: 6 | D7: 6 | F7: =Infrast_publique!C86 -> 0
A8: Effectif des CHR | B8: 9 | C8: 9 | D8: 9 | F8: =Infrast_publique!D86 -> 0
A9: Effectif des CMA | B9: 46 | C9: 46 | D9: 46 | F9: =Infrast_publique!E86 -> 0
A10: Effectif des CM | B10: 83 | C10: 99 | D10: 116 | F10: =Infrast_publique!F86 -> 0
A11: Effectif des CSPS | B11: 2126 | C11: 2207 | D11: 2233 | F11: =Infrast_publique!G86 -> 0
A12: Effectif des dispensaires isolés | B12: 87 | C12: 51 | D12: 49 | F12: =Infrast_publique!H86 -> 0
A13: Effectif maternités isolées | B13: 8 | C13: 4 | D13: 4 | F13: =Infrast_publique!I86 -> 0
A14: Autres FS publiques (infirmeries, etc) | B14: 201 | C14: 234 | D14: 213 | F14: =Infrast_publique!J86 -> 0
A15: Ratio habitant par CSPS | B15: 10113.151 | C15: 9396.2101 | D15: 9526.3884 | F15: =+Ratio_hbt_Csps!E86 -> #DIV/0!
A16: Rayon d’action moyen théorique en km (sans le privé) | B16: 6.1424756 | C16: 6.0678759 | D16: 6.0158663 | F16: =+RMAT!E86 -> #DIV/0!
A17: Pourcentage des formations sanitaires (CSPS) remplissant les normes minimales en personnel | B17: 89.228598 | C17: 89.669234 | D17: 72.458576 | F17: =+Norme_personnel!E86
A18: Poucentage de la population à plus de 5 km d'une FS | B18: 39.6 | C18: 37.99649 | D18: 36.56589 | F18: =+'Pop_distance '!H108+'Pop_distance '!I108 -> #VALUE!
A19: Infrastructures Privées
A20: Effectif des établissements sanitaires privés de soins hospitaliers* | B20: 208 | C20: 243 | D20: 318 | F20: =SUM(Infrastructure_privées1!C87:H87) -> 0
A21: Effectif des établissements sanitaires privés de soins non hospitaliers** | B21: 530 | C21: 617 | D21: 784 | F21: =Infrastructure_privées2!H87-SUM(Infrastructure_privées1!C87:H87) -> 0
A22: Effectif des officines | B22: 240 | C22: 311 | D22: 313 | F22: =Infrastructure_privées2!I87 -> 0
A23: Effectif des dépots pharmaceutiques privés | B23: 668 | C23: 812 | D23: 830 | F23: =Infrastructure_privées2!J87 -> 0
A24: Rayon d’action moyen théorique en km (y compris le privé) | B24: 5.491138 | C24: 5.3518673 | D24: 5.227606 | F24: =RMAT!G86 -> #DIV/0!
A25: Ressources financières
A26: Total budget ministère de la santé (millions F CFA) | B26: 266080.49 | C26: 301755.92 | D26: 266747.7 | F26: 336392.77
A27: Pourcentage du budget du Ministère de la santé / budget de l'Etat (norme : ≥ 12,7%) | B27: 13.52 | C27: 13.89 | D27: 11.53 | F27: =+indicateursPNDS_ODD!F23 -> 11.79
A28: Part du budget alloué au Secteur Santé (norme : ≥ 15%) | B28: 13.93 | C28: 14.46 | D28: 11.87 | F28: =+indicateursPNDS_ODD!F24 -> 11.96
A29: Taux d'exécution budgetaire du Ministère de la santé (%) | B29: 99.04 | C29: 93.73 | D29: 98.6
A30: Taux d’absorption des ressources financières allouées (%) | B30: 98.71 | C30: 93.26 | D30: 99.36 | F30: =+'Bilan PA _2'!I159
A31: Ressources humaines
A32: Effectif de Médecins | B32: 2226 | C32: 2319 | D32: 2318 | F32: ='Evolution Effectif personnel'!F3 -> 2518
A33: Effectif de Chirurgiens dentistes | B33: 45 | C33: 57 | D33: 55 | F33: ='Effectif par niveau'!H5 -> 40
A34: Effectif de Pharmaciens | B34: 329 | C34: 337 | D34: 317 | F34: ='Effectif par niveau'!H6 -> 379
A35: Effectif d'attaché de santé | B35: 2953 | C35: 3193 | D35: 3292 | F35: ='Effectif par niveau'!H7 -> 3080
A36: Effectif d' Infirmiers diplômés d'Etat (IDE) | B36: 7661 | C36: 7827 | D36: 7592 | F36: ='Effectif par niveau'!H10 -> 4037
A37: Effectif d'Infirmiers brevetés (IB) | B37: 1604 | C37: 1483 | D37: 1325 | F37: ='Effectif par niveau'!H12 -> 690
A38: Effectif de SF/ME | B38: 4847 | C38: 5086 | D38: 4970 | F38: ='Effectif par niveau'!H11 -> 3041
A39: Effectif d'Agents itinérants de santé (AIS) | B39: 2935 | C39: 2887 | D39: 2313 | F39: ='Effectif par niveau'!H19 -> 1021
A40: Effectif des ASBC | B40: 17648 | C40: 24958 | D40: 16785 | F40: ='Situation ASBC'!G87 -> 0
A41: Ratio population/médecin | B41: 9658.8315 | C41: 9271.4787 | D41: 9871.607 | F41: ='Evolution Effectif personnel'!F13 -> 0
A42: Ratio habitants/infirmier | B42: 2321 | C42: 2309.4048 | D42: 2566.1529 | F42: ='Evolution Effectif personnel'!F16 -> 0
A43: Ratio population/IDE | B43: 2806.4951 | C43: 2746.9732 | D43: 3014.0128 | F43: ='Evolution Effectif personnel'!F15 -> 0
A44: Ratio population/SFE-ME | B44: 4435.8488 | C44: 4227.4005 | D44: 4604.1016 | F44: ='Evolution Effectif personnel'!F17 -> 0
A45: Exhaustivité des rapports
A46: Complétude globale des rapports d’activités des formations sanitaires (%) | B46: 89.444208 | C46: 91.025824 | D46: 91.765907 | F46: =ComplétudeCorrige!K108 -> 0
A47: Complétude des rapports d’activités des formations sanitaires publiques (%) | B47: 94.921757 | C47: 98.109611 | D47: 98.374821 | F47: =ComplétudeCorrige!E108 -> 0
A48: Complétude des rapports d’activités des formations sanitaires privées de soins (%) | B48: 69.769965 | C48: 68.64139 | D48: 72.618836 | F48: =ComplétudeCorrige!H108
A49: Médicaments
A50: Pourcentage de DMEG n'ayant pas connu de rupture de médicaments traceurs | B50: 13.447972 | C50: 7.3846154 | D50: 11.343805 | F50: =Rupture_DMEG!E86
A51: Soins curatif et hospitalisation
A52: Nombre de nouveaux contacts par habitant par an dans la population generale | B52: 1.2 | C52: 1.1534923 | D52: 1.1200216 | F52: ='Nb_nouveau contact'!D107
A53: Nombre de nouveaux contacts par habitant par an des enfants de moins de 5 ans | B53: 2.5716174 | C53: 2.2687907 | D53: 2.1513915 | F53: ='Nb_nouveau contact'!E107
A54: Proportion d’enfants pris en charge selon l'approche PCIME (%) | B54: 76.093976 | C54: 80.260984 | D54: 77.11682 | F54: =#REF! -> #REF!
A55: Taux de mortalité intra hospitalière (CHU/CHR, HD) en pour 1000 | B55: 64.509816 | C55: 64.761834 | D55: 64.596181 | F55: ='Sortie Hospi'!J107
A56: Taux (%) d’occupation des lits dans les hôpitaux publics (CHU/CHR, HD) | B56: 56.501158 | C56: 85.269194 | D56: 62.165889 | F56: ='Occupation lit'!G108
A57: Sejour moyen (en jour) | B57: 3.37 | C57: 3.58083 | D57: 3.5957849 | F57: ='Occupation lit'!H108
A58: Coéfficient de rotation des lits (%) | B58: 61.1 | C58: 86.916317 | D58: 63.103189 | F58: ='Occupation lit'!I108
A59: Taux de contre référence reçue (%) par les FS du premier échelon | B59: 14.8 | C59: 17.750425 | D59: 19.015984 | F59: ='Réf_Evac_cont ref_1er échelon'!E86
A60: Surveillance épidemiologique
A61: Complétude du TLOH des FS publiques (%) | B61: 96.3 | C61: 94.045677 | D61: 87.736464 | F61: ='Complétude TLOH_Publique '!F86 -> 77.702703
A62: Complétude du TLOH des FS privées (%) | B62: 65.8 | C62: 60.227418 | D62: 71.012896 | F62: ='Complétude TLOH_Privée'!F86 -> 100
A63: Cas de méningite | B63: 1640 | C63: 2071 | D63: 1971 | F63: =MPE!C87 -> 1
A64: Létalité de la méningite | B64: 5.9 | C64: 3.911154 | D64: 3.805175 | F64: =MPE!E87 -> 0
A65: Cas de rougeole | B65: 3247 | C65: 3735 | D65: 2428 | F65: =MPE!F87 -> 5
A66: Létalité de la rougeole | B66: 0.2 | C66: 0.26773762 | D66: 0.16474465 | F66: =MPE!H87 -> 0
A67: Cas de Covid 19 | B67: 5366 | C67: 8431 | D67: 343 | F67: ='MPE(suite2'!I87 -> 0
A68: Létalité de la Covid 19 | B68: 4.4 | C68: 0.61677144 | D68: 1.1661808 | F68: ='MPE(suite2'!K87
A69: Cas de choléra | B69: 3 | C69: 4 | D69: 0 | F69: ='MPE(suite2'!C87 -> 0
A70: Létalité du choléra | B70: 0 | C70: 0 | D70: 0 | F70: 0
A71: Cas de dengue | B71: 8343 | C71: 13660 | D71: 160751 | F71: ='MPE(suite2'!F87 -> 161
A72: Létalité de la dengue | B72: 0.2 | C72: 0.1 | D72: 0.450386 | F72: ='MPE(suite2'!H87 -> 0
A73: Taux de PFA non polio pour 100 000 enfants de moins de quinze ans. | B73: 13.7 | C73: 12 | D73: 10.5 | E73: 11.6 | F73: 11.05 | G73: ok
A74: Taux d'adéquation des selles | B74: 90 | C74: 95 | D74: 95 | E74: 94 | F74: 96.1 | G74: ok
A75: Santé réproductive
A76: Prévalence contraceptive (Méthodes modernes) (%) | B76: 31.2
A77: Taux d'utilisation des méthodes contraceptives (%) | B77: 27.483064 | C77: 23.492166 | D77: 23.160586 | F77: ='UtilisatricePF '!J108
A78: Besoins non satisfaits en PF totaux (%) | B78: 20.9
A79: Nombre total de couple année protection | B79: 1785373 | C79: 1766085.3 | D79: 1914380.1 | F79: ='Couple années par structure2'!J107 -> 0
A80: Santé de la mère et de l’enfant
A81: Taux de couverture en CPN1 (%) | B81: 92.4 | C81: 86.755267 | D81: 83.213616 | F81: ='Couverture CPN'!G107
A82: Pourcentage des femmes enceintes vues au 1er trimestre | B82: 43.8 | C82: 44.406374 | D82: 44.462591 | F82: ='Couverture CPN'!H107
A83: Taux de couverture en CPN4 (%) | B83: 54.2 | C83: 54.093461 | D83: 52.28928 | F83: ='Couverture CPN'!I107
A84: Pourcentage des femmes enceintes ayant bénéficié du TPI3 | B84: 65 | C84: 68.64483 | D84: 70.374577 | F84: ='Couverture CPN'!J107
A85: Proportion de grossesses référées (%) | B85: 3.3 | C85: 3.0077119 | D85: 2.9443334 | F85: ='Grossesses référées'!E107
A86: Taux d'accouchement dans les FS (%) | B86: 87.4 | C86: 95.524758 | D86: 91.757643 | F86: =Accouchement!H107
A87: Proportion (%) des accouchements réalisés avec partogramme | B87: 87.2 | C87: 88.347807 | D87: 89.426639 | F87: =Ac_Partogramme_Mortnés!E107 -> 0
A88: Proportion de faible poids de naissance | B88: 10.5 | C88: 9.1232101 | D88: 8.4742244 | F88: =Naissances!H107
A89: Proportion (%) d'enfants mis au sein à la première heure | B89: 97.6 | C89: 95.449761 | D89: 95.902283 | F89: =Naissances!J107
A90: Proportion de décès néonatal parmis les naissances vivantes dans les FS | B90: 0.72141273 | C90: 0.82111686 | D90: 0.83490557 | F90: =Deces_neonatal!F107
A91: Taux de décès pour 100 000 parturientes | B91: 154.6 | C91: 130.01481 | D91: 131.75489 | F91: ='Taux de décès maternel'!F107
A92: Taux de césariennes parmi les naissances attendues (%) | B92: 5.3 | C92: 4.0128274 | D92: 4.1890881 | F92: =Taux_césarienne!D107
A93: Couverture en consultation postnatale 6e semaine (%) | B93: 36.2 | C93: 35.613478 | D93: 35.840029 | F93: =Cons_post_nat!G108
A94: PTME
A95: Taux de dépistage du VIH (%) | B95: 90.834026 | C95: 90.225811 | D95: 91.676007 | F95: =PTME_VIH!D107 -> 0
A96: Taux de séropositivité (%) | B96: 0.30660889 | C96: 0.24781821 | D96: 0.21917619 | F96: =PTME_VIH!F107 -> 0
A97: Taux de positivité à la PCR des nourrissons nés de mère séropositive | B97: 2.0979021 | C97: 3.4161491 | D97: 1.8700787 | F97: ='PTME_VIH-Enfant'!H107 -> 0
A98: Pourcentage d’enfants nés de mères infectées par le VIH ayant reçu les ARV complets pour la prévention dans les formations sanitaires | B98: 95.12894 | C98: 95.25641 | D98: 98.265354 | F98: ='PTME_VIH-Enfant'!E107 -> 0
A99: Nutrition
A100: Prévalence de la malnutrition aigue (%) chez les enfants de moins de 5 ans (%) | B100: 9.7 | C100: 8.8 | D100: 9.2
...

Sheet IndicateursEconomiques
A1: Tableau 0.03: Quelques indicateurs économiques
A2: INTITULE | B2: 2021 | C2: 2022 | D2: 2023 | E2: 2024
A3: Indicateurs macroéconomiques
A4: Budget État (millions de FCFA) | B4: 2572988 | C4: 2172097 | D4: 2314412
A5: PIB (millions de FCFA) | B5: 9664699 | C5: 11779465 | D5: 12328298
A6: PIB par habitant (unités de devises locales constantes) | B6: 449581.57 | C6: 494000 | D6: 486700
A7: Croissance PIB (%) | B7: 6.9063417 | C7: 2.7 | D7: 3
A8: Inflation, prix à la consommation (% annuel) | B8: 3.6535329 | C8: 14.3 | D8: 12.8
A9: Dépenses de santé du reste du monde (millions de FCFA) | B9: 129300.93 | C9: 162196.1 | D9: 209900.94
A10: Dépenses de santé de l’État (millions de FCFA) | B10: 298419.63 | C10: 301.75592 | D10: 314903.14
A11: Dépense des salaires payés par l’État (millions de FCFA) | B11: 175 701, 832 | C11: 192404.42 | D11: 199941.61
A12: Dépenses assurance maladie (millions de FCFA) | B12: 10895.24 | C12: 14938.1 | D12: 15788.11
A13: Dépenses de santé du reste du monde en % des dépenses courantes de santé | B13: 18.5 | C13: 20.353827 | D13: 21
A14: Dépenses de santé de l’État en % du budget de l’État | B14: 11.6 | C14: 11 | D14: 13.6
A15: Dépense des salaires payés par l’État en % les dépenses de santé de l’État | B15: 56.3 | C15: 60.01 | D15: 63.5
A16: Dépenses assurance maladie en % dépense totale de santé | B16: 1.5 | C16: 1.7 | D16: 1.5
A17: Dépenses assurance maladie en % dépense de santé des ménages | B17: 4.5 | C17: 5.4 | D17: 3.6
A18: Indicateurs de base des comptes de santé
A19: Dépenses courantes de santé | B19: 697963 | C19: 796882.57 | D19: 1001898
A20: Dépense en Investissement | B20: 27980 | C20: 55974.558 | D20: 35823
A21: Dépense connexe aux Investissement | B21: 2597 | C21: 3987.9865 | D21: 6584
A22: Dépenses Totale en santé (millions de FCFA) | B22: 728541 | C22: 856845.12 | D22: 1044304
A23: Dépenses des ménages (en millions de FCFA) | B23: 243127 | C23: 277819.22 | D23: 440863
A24: Dépenses publiques en santé (en millions de FCFA) | B24: 298420 | C24: 319898.86 | D24: 314903
A25: Dépenses publiques de santé en % des dépenses totales de santé (%) | B25: 0.41 | C25: 37.334502 | D25: 30.2
A26: Dépenses de santé par habitant (FCFA) | B26: 33885 | C26: 38623.677 | D26: 43785
A27: Dépenses de santé en % du PIB | B27: 0.075 | C27: 7.2740582 | D27: 8.5
A28: Dépenses de santé des ménages en % des dépenses courantes de santé | B28: 33.4 | C28: 32.423505 | D28: 44
A29: Dépenses de soins préventifs | B29: 162734 | C29: 174636.65 | D29: 201977
A30: Dépenses de soins curatifs | B30: 326765 | C30: 386856.09 | D30: 503822
... A38: Dep. de vaccination en % des dep. courantes de santé | B38: 0.98 | C38: 1.1782429 | D38: 1.86
A39: Source: Comptes de santé

Sheet Partie 1
A1: 1. INFORMATIONS GENERALES
A2: Quelques résultats d'enquête et des CNS | B2: p 14
A3: Indicateurs clés de planification familiale issus de l’enquête PMABF | B3: pp 15-16
A4: Population du Burkina Faso par groupe d'âge | B4: pp 17 - 18
A5: populations cibles par district | B5: pp 19 - 22
A6: Population selon la distance par district | B6: pp 23 - 24
A7: Complétude des rapports des formations sanitaires | B7: pp 25 - 36

Sheet SARA_QoC_RDQA_CS_HHFA
A1: Tableau 1.01: quelques résultats de l'audit de la qualité des données de routine (RDQA*)
A2: Indicateurs | C2: 2017 | D2: 2018 | E2: 2021 | F2: 2023
A3: Indice de concordance des données du système de routine sur le paludisme (%) | C3: 72.1 | D3: 80.5 | E3: 76.7 | F3: 77.6
A4: Indice de concordance des données du système de routine sur la vaccination(%) | C4: 82.9 | D4: 87 | E4: 92.3 | F4: 92.8
A5: Indice de concordance des données du système de routine sur la CPN (%) | C5: 85.9 | D5: 93.5 | E5: 94.3
A6: Indice de concordance des données du système de routine sur le VIH (%) | C6: 99.7 | D6: 96.6 | E6: 98.9 | F6: 99.4
A7: Indice de concordance des données du système de routine sur la tuberculose (%) | C7: 98.2 | D7: 99.2 | E7: 99.5 | F7: 97.8
A8: *Routine data quality assessment
A9: ** En 2017, les registres de vaccination ont été considérés comme sources de vérification et non les registres de coches
A11: Tableau 1.02: quelques résultats de l'enquête SARA/HHFA*
A12: Indicateurs | E12: 2018 | F12: 2020
A13: Score moyen de la disponibilité des éléments traceurs de la prévention des infections (%) | E13: 73 | F13: 72.2
A14: Score moyen de la disponibilité des éléments traceurs d’aménagement et de confort (%) | E14: 74 | F14: 66.4
A15: Score moyen de la disponibilité des éléments traceurs des équipements essentiels (%) | E15: 84 | F15: 77.66
A16: Score moyen de la disponibilité des éléments traceurs pour le diagnostic (%) | E16: 50 | F16: 54.78
A17: Score moyen de la disponibilité des médicaments essentiels pour la prise en charge d’un certain nombre de pathologies (%) | E17: 29 | F17: 76.3
A18: * service availability and readiness assessment(2018) et HHFA pour 2020
A20: Tableau 1.03: quelques résultats de l'enquête qualité des prestations de soins du paludisme, de la tuberculose et de l’infection à vih (QoC*)
A21: Indicateurs | C21: 2017 | D21: 2020
A22: Indice de la qualité des soins en matière de paludisme (%) | C22: 78.04 | D22: 66.35
A23: Indice de la qualité des soins en matière de tuberculose (%) | C23: 65.4 | D23: 44.77
A24: Indice de la qualité des soins en matière de PTME (%) | C24: 30.9 | D24: 33.88
A25: Indice de la qualité des soins en matière de VIH (%) | C25: 48.3 | D25: 60.87
A26: Source: SARA/HHFA
A27: * Quality of care

Sheet PMABF
A1: Tableau 1.04: Quelques indicateurs clés de planification familiale issus de l’enquête PMABF au Burkina Faso désagrégés par milieu de résidence
B2: Vague 8 | E2: Vague 9
B3: dec 2020 - mars 2021 | E3: 44228
A4: Indicateurs sur la santé reproductive et la contraception | B4: Urbain | C4: Rural | D4: Total | E4: Urbain | F4: Rural | G4: Total
A5: Âge médian au 1er rapport sexuel (chez les 25-49 ans)
A6: Âge médian à la 1ère union (chez les 25-49 ans)
A7: Âge médian à la 1ère naissance (chez les 25-49 ans)
A8: Âge médian à la 1ère utilisation de la contraception (chez les 25-49 ans)
A9: Nombre moyen d'enfants à la première utilisation de la contraception (15-49 ans)
A10: A reçu des informations sur la planification familiale d’un prestataire au cours des 12 derniers mois (%) (15-49 ans)
A11: Exposition aux messages médiatiques sur la PF au cours des mois ayant précédé l’enquête (%) (15-49 ans)
A13: Indicateurs sur l’accès, l’équité, la qualité et le choix des méthodes (Pour les utilisatrices actuelles des méthodes modernes)
B14: Urbain | C14: Rural | D14: Total | E14: Urbain | F14: Rural | G14: Total
A15: A choisi la méthode elle-même ou avec l’aide du partenaire
A16: A obtenu la méthode souhaitée
A17: On lui a parlé d'autres méthodes
A18: A été conseillée sur les effets secondaires
A19: A payé pour les services de PF
A20: Retournerait voir le prestataire et le recommanderait à une amie ou un membre de la famille
A21: A reçu une méthode d’un SPS dans le secteur public
A23: Événements de la vie avant l'âge de 18 ans (% de toutes femmes âgées de 18 à 24 ans) | B23: Urbain | C23: Rural | D23: Total | E23: Urbain | F23: Rural | G23: Total
A25: Mariées
A26: Ayant utilisé une méthode contraceptive
A27: Premier rapport sexuel
A28: Ayant accouché
A30: Indicateurs de planification familiale (parmi les femmes en union) | B30: Urbain | C30: Rural | D30: Total | E30: Urbain | F30: Rural | G30: Total
A31: Taux de prévalence contraceptive – Toutes méthodes (%)
A32: Taux de prévalence contraceptive – Méthodes modernes (%)
A33: Taux de prévalence contraceptive – De longue durée ou permanent (%)
A34: Besoins non satisfaits totaux (%)
A35: Besoins non satisfaits – Pour limiter les naissances (%)
A36: Besoins non satisfaits – Pour espacer les naissances (%)
A37: Demande contraceptive totale (%)
A38: Demande contraceptive satisfaite par des méthodes modernes (%)
A40: Distribution des méthodes modernes actuelles | B40: Urbain | C40: Rural | D40: Total | E40: Urbain | F40: Rural | G40: Total
A41: (parmi les utilisatrices en union)
A42: Stérilisation féminine
A43: Implants
A44: DIU
A45: Injectables-intramusculaire (DMPA-IM)
A46: Pilule
A47: Contraception d'urgence
A48: Préservatif masculin
A49: Préservatif féminin
A50: Mousse / Gelée spermicide
A51: Collier du cycle
A52: Injectables-sous cutané (DMPA-SC)
A54: Indicateurs de fécondité (%) | B54: Urbain | C54: Rural | D54: Total | E54: Urbain | F54: Rural | G54: Total
A55: Pourcentage de dernières naissances non souhaitées
A56: Désirait un autre enfant mais plus tard
A57: Ne désirait plus d’enfant
A59: Source:Source: Institut Supérieur des Sciences de la Population (ISSP) and The Bill & Melinda Gates Institute for Population and Reproductive Health at The Johns Hopkins Bloomberg School of Public Health. Performance Monitoring for Action (PMA) Familiy Planning and Nutrition Surveys, PMA/Burkina Faso 2020. Ouagadougou, Burkina Faso and Baltimore, Maryland, USA.

Sheet Population
A1: Tableau 1.05: répartition de la population du Burkina Faso par district et par groupe d'âge en 2025
A2: Régions/ districts | C2: Moins de 5 ans | D2: 5-14 ans | E2: 15 ans et plus | F2: Total
A3: Bankui
B4: CHR Dédougou
B5: DS Boromo
B6: DS Dedougou
B7: DS Solenzo
A8: Djoro
B9: CHR Gaoua
B10: DS Batié
B11: DS Dano
B12: DS Diébougou
B13: DS Gaoua
B14: DS Kampti
A15: Goulmou
B16: CHR Fada N'Gourma
B17: DS Fada
B18: DS Pama
A19: Guiriko
B20: CHU Sanou Souro
B21: DS Dafra
B22: DS Dande
B23: DS Do
B24: DS Hounde
B25: DS Karangasso Vigue
B26: DS Léna
B27: DS N'Dorola
B28: DS Orodara
A29: Kadiogo
B30: CHU Bogodogo
B31: CHU Pédiatrique CDG
B32: CHU Tengandogo
B33: CHU Yalgado
B34: Hôpital Paul VI
B35: Hôpital Saint Camille
B36: Hôpital SCHIPHRA
B37: DS Baskuy
B38: DS Bogodogo
B39: DS Boulmiougou
B40: DS Nongr-Massom
B41: DS Sig-Noghin
A42: Koulsé
B43: CHR Kaya
B44: DS Barsalogho
B45: DS Boulsa
B46: DS Boussouma
B47: DS Kaya
B48: DS Kongoussi
B49: DS Tougouri
A50: Liptako
B51: CHR Dori
B52: DS Dori
B53: DS Gorom-Gorom
B54: DS Sebba
A55: Nakambé
B56: CHR Tenkodogo
B57: DS Bittou
B58: DS Garango
B59: DS Koupéla
B60: DS Ouargaye
B61: DS Pouytenga
B62: DS Tenkodogo
B63: DS Zabré
A64: Nando
B65: CHR Koudougou
B66: DS Koudougou
B67: DS Léo
B68: DS Nanoro
B69: DS Réo
B70: DS Sabou
B71: DS Sapouy
B72: DS Tenado
A73: Nazinon
B74: CHR Manga
B75: DS Kombissiri
B76: DS Manga
B77: DS Po
B78: DS Sapone
A79: Oubri
B80: CHR Ziniaré
B81: DS Boussé
B82: DS Ziniaré
B83: DS Zorgho
A84: Sirba
B85: DS Bogande
B86: DS Gayeri
B87: DS Manni
A88: Soum
B89: DS Djibo
A90: Sourou
B91: DS Nouna
B92: DS Toma
B93: DS Tougan
A94: Tannounyan
B95: CHR Banfora
B96: DS Banfora
B97: DS Mangodara
B98: DS Sindou
A99: Tapoa
B100: DS Diapaga
...

Sheet Pop_cible
A1: Tableau 1.06: Effectifs des populations cibles par district en 2025
A2: Régions/ districts | C2: Femmes en Age de procréer | D2: Grossesses attendues | E2: Accouchements attendus | F2: Naissances vivantes attendues | G2: 0 à 11 mois | H2: 6 à 11 Mois | I2: 12 à 59 Mois | J2: Cas attendus de MAM | K2: Cas attendus de MAS | L2: 12 à 23 Mois | M2: Fille de 9ans
A3: Bankui
B4: CHR Dédougou
B5: DS Boromo
B6: DS Dedougou
B7: DS Solenzo
A8: Djoro
B9: CHR Gaoua
B10: DS Batié
B11: DS Dano
B12: DS Diébougou
B13: DS Gaoua
B14: DS Kampti
A15: Goulmou
B16: CHR Fada N'Gourma
B17: DS Fada
B18: DS Pama
A19: Guiriko
B20: CHU Sanou Souro
B21: DS Dafra
B22: DS Dande
B23: DS Do
B24: DS Hounde
B25: DS Karangasso Vigue
B26: DS Léna
B27: DS N'Dorola
B28: DS Orodara
A29: Kadiogo
B30: CHU Bogodogo
B31: CHU Pédiatrique CDG
B32: CHU Tengandogo
B33: CHU Yalgado
B34: Hôpital Paul VI
B35: Hôpital Saint Camille
B36: Hôpital SCHIPHRA
B37: DS Baskuy
B38: DS Bogodogo
B39: DS Boulmiougou
B40: DS Nongr-Massom
B41: DS Sig-Noghin
A42: Koulsé
B43: CHR Kaya
B44: DS Barsalogho
B45: DS Boulsa
B46: DS Boussouma
B47: DS Kaya
B48: DS Kongoussi
B49: DS Tougouri
A50: Liptako
B51: CHR Dori
B52: DS Dori
B53: DS Gorom-Gorom
B54: DS Sebba
A55: Nakambé
B56: CHR Tenkodogo
B57: DS Bittou
B58: DS Garango
B59: DS Koupéla
B60: DS Ouargaye
B61: DS Pouytenga
B62: DS Tenkodogo
B63: DS Zabré
A64: Nando
B65: CHR Koudougou
B66: DS Koudougou
B67: DS Léo
B68: DS Nanoro
B69: DS Réo
B70: DS Sabou
B71: DS Sapouy
B72: DS Tenado
A73: Nazinon
B74: CHR Manga
B75: DS Kombissiri
B76: DS Manga
B77: DS Po
B78: DS Sapone
A79: Oubri
B80: CHR Ziniaré
B81: DS Boussé
B82: DS Ziniaré
B83: DS Zorgho
A84: Sirba
B85: DS Bogande
B86: DS Gayeri
B87: DS Manni
A88: Soum
B89: DS Djibo
A90: Sourou
B91: DS Nouna
B92: DS Toma
B93: DS Tougan
A94: Tannounyan
B95: CHR Banfora
B96: DS Banfora
B97: DS Mangodara
B98: DS Sindou
A99: Tapoa
B100: DS Diapaga
...

Sheet Pop_distance 
A1: Tableau 1.07: Répartition de la population selon la distance à la formation sanitaire de référence en 2025
C2: Population totale | D2: Effectif | G2: Proportion (%)
A3: Régions/Districts | D3: 0 à 4 km | E3: 5 à 9 km | F3: 10 km et + | G3: 0 à 4 km | H3: 5 à 9 km | I3: 10 km et + | J3: Vérification
A4: Bankui | C4: =+Population!F3 -> 0 | D4: =SUM(D5:D8) -> 830062 | E4: =SUM(E5:E8) -> 220009 | F4: =SUM(F5:F8) -> 152657 | G4: =IFERROR(D4/$C4*100,"") | H4: =IFERROR(E4/$C4*100,"") | I4: =IFERROR(F4/$C4*100,"") | J4: =IF(C4="","",C4=SUM(D4+E4+F4)) -> FALSE
B5: CHR Dédougou | C5: =+Population!F4 -> 0 | G5: =IFERROR(D5/$C5*100,"") | H5: =IFERROR(E5/$C5*100,"") | I5: =IFERROR(F5/$C5*100,"") | J5: =IF(C5="","",C5=SUM(D5+E5+F5)) -> TRUE
B6: DS Boromo | C6: =+Population!F5 -> 0 | D6: 277565 | E6: 44103 | F6: 27043 | G6: =IFERROR(D6/$C6*100,"") | H6: =IFERROR(E6/$C6*100,"") | I6: =IFERROR(F6/$C6*100,"") | J6: =IF(C6="","",C6=SUM(D6+E6+F6)) -> FALSE
B7: DS Dedougou | C7: =+Population!F6 -> 0 | D7: 282952 | E7: 111627 | F7: 59156 | G7: =IFERROR(D7/$C7*100,"") | H7: =IFERROR(E7/$C7*100,"") | I7: =IFERROR(F7/$C7*100,"") | J7: =IF(C7="","",C7=SUM(D7+E7+F7)) -> FALSE
B8: DS Solenzo | C8: =+Population!F7 -> 0 | D8: 269545 | E8: 64279 | F8: 66458 | G8: =IFERROR(D8/$C8*100,"") | H8: =IFERROR(E8/$C8*100,"") | I8: =IFERROR(F8/$C8*100,"") | J8: =IF(C8="","",C8=SUM(D8+E8+F8)) -> FALSE
A9: Djoro | C9: =+Population!F8 -> 0 | D9: =SUM(D10:D15) -> 455152 | E9: =SUM(E10:E15) -> 358814 | F9: =SUM(F10:F15) -> 214904 | G9: =IFERROR(D9/$C9*100,"") | H9: =IFERROR(E9/$C9*100,"") | I9: =IFERROR(F9/$C9*100,"") | J9: =IF(C9="","",C9=SUM(D9+E9+F9)) -> FALSE
B10: CHR Gaoua | C10: =+Population!F9 -> 0 | G10: =IFERROR(D10/$C10*100,"") | H10: =IFERROR(E10/$C10*100,"") | I10: =IFERROR(F10/$C10*100,"") | J10: =IF(C10="","",C10=SUM(D10+E10+F10)) -> TRUE
B11: DS Batié | C11: =+Population!F10 -> 0 | D11: 33087 | E11: 45937 | F11: 37247 | G11: =IFERROR(D11/$C11*100,"") | H11: =IFERROR(E11/$C11*100,"") | I11: =IFERROR(F11/$C11*100,"") | J11: =IF(C11="","",C11=SUM(D11+E11+F11)) -> FALSE
B12: DS Dano | C12: =+Population!F11 -> 0 | D12: 178091 | E12: 109836 | F12: 23353 | G12: =IFERROR(D12/$C12*100,"") | H12: =IFERROR(E12/$C12*100,"") | I12: =IFERROR(F12/$C12*100,"") | J12: =IF(C12="","",C12=SUM(D12+E12+F12)) -> FALSE
B13: DS Diébougou | C13: =+Population!F12 -> 0 | D13: 72678 | E13: 76534 | F13: 33978 | G13: =IFERROR(D13/$C13*100,"") | H13: =IFERROR(E13/$C13*100,"") | I13: =IFERROR(F13/$C13*100,"") | J13: =IF(C13="","",C13=SUM(D13+E13+F13)) -> FALSE
B14: DS Gaoua | C14: =+Population!F13 -> 0 | D14: 115171 | E14: 81651 | F14: 83313 | G14: =IFERROR(D14/$C14*100,"") | H14: =IFERROR(E14/$C14*100,"") | I14: =IFERROR(F14/$C14*100,"") | J14: =IF(C14="","",C14=SUM(D14+E14+F14)) -> FALSE
B15: DS Kampti | C15: =+Population!F14 -> 0 | D15: 56125 | E15: 44856 | F15: 37013 | G15: =IFERROR(D15/$C15*100,"") | H15: =IFERROR(E15/$C15*100,"") | I15: =IFERROR(F15/$C15*100,"") | J15: =IF(C15="","",C15=SUM(D15+E15+F15)) -> FALSE
A16: Goulmou | C16: =+Population!F15 -> 0 | D16: =SUM(D17:D19) -> 313778 | E16: =SUM(E17:E19) -> 150119 | F16: =SUM(F17:F19) -> 191787 | G16: =IFERROR(D16/$C16*100,"") | H16: =IFERROR(E16/$C16*100,"") | I16: =IFERROR(F16/$C16*100,"") | J16: =IF(C16="","",C16=SUM(D16+E16+F16)) -> FALSE
B17: CHR Fada N'Gourma | G17: =IFERROR(D17/$C17*100,"") | H17: =IFERROR(E17/$C17*100,"") | I17: =IFERROR(F17/$C17*100,"") | J17: =IF(C17="","",C17=SUM(D17+E17+F17))
B18: DS Fada | C18: =+Population!F17 -> 0 | D18: 244281 | E18: 119176 | F18: 151355 | G18: =IFERROR(D18/$C18*100,"") | H18: =IFERROR(E18/$C18*100,"") | I18: =IFERROR(F18/$C18*100,"") | J18: =IF(C18="","",C18=SUM(D18+E18+F18)) -> FALSE
B19: DS Pama | C19: =+Population!F18 -> 0 | D19: 69497 | E19: 30943 | F19: 40432 | G19: =IFERROR(D19/$C19*100,"") | H19: =IFERROR(E19/$C19*100,"") | I19: =IFERROR(F19/$C19*100,"") | J19: =IF(C19="","",C19=SUM(D19+E19+F19)) -> FALSE
A20: Guiriko | C20: =+Population!F19 -> 0 | D20: =SUM(D21:D29) -> 2089110 | E20: =SUM(E21:E29) -> 288282 | F20: =SUM(F21:F29) -> 296986 | G20: =IFERROR(D20/$C20*100,"") | H20: =IFERROR(E20/$C20*100,"") | I20: =IFERROR(F20/$C20*100,"") | J20: =IF(C20="","",C20=SUM(D20+E20+F20)) -> FALSE
B21: CHU Sanou Souro | C21: =+Population!F20 -> 0 | G21: =IFERROR(D21/$C21*100,"") | H21: =IFERROR(E21/$C21*100,"") | I21: =IFERROR(F21/$C21*100,"") | J21: =IF(C21="","",C21=SUM(D21+E21+F21)) -> TRUE
B22: DS Dafra | C22: =+Population!F21 -> 0 | D22: 498264 | E22: 8725 | F22: 12752 | G22: =IFERROR(D22/$C22*100,"") | H22: =IFERROR(E22/$C22*100,"") | I22: =IFERROR(F22/$C22*100,"") | J22: =IF(C22="","",C22=SUM(D22+E22+F22)) -> FALSE
B23: DS Dande | C23: =+Population!F22 -> 0 | D23: 173216 | E23: 57112 | F23: 33802 | G23: =IFERROR(D23/$C23*100,"") | H23: =IFERROR(E23/$C23*100,"") | I23: =IFERROR(F23/$C23*100,"") | J23: =IF(C23="","",C23=SUM(D23+E23+F23)) -> FALSE
B24: DS Do | C24: =+Population!F23 -> 0 | D24: 686566 | E24: 48477 | F24: 62270 | G24: =IFERROR(D24/$C24*100,"") | H24: =IFERROR(E24/$C24*100,"") | I24: =IFERROR(F24/$C24*100,"") | J24: =IF(C24="","",C24=SUM(D24+E24+F24)) -> FALSE
B25: DS Hounde | C25: =+Population!F24 -> 0 | D25: 309732 | E25: 31939 | F25: 46872 | G25: =IFERROR(D25/$C25*100,"") | H25: =IFERROR(E25/$C25*100,"") | I25: =IFERROR(F25/$C25*100,"") | J25: =IF(C25="","",C25=SUM(D25+E25+F25)) -> FALSE
B26: DS Karangasso Vigue | C26: =+Population!F25 -> 0 | D26: 52074 | E26: 51079 | F26: 43288 | G26: =IFERROR(D26/$C26*100,"") | H26: =IFERROR(E26/$C26*100,"") | I26: =IFERROR(F26/$C26*100,"") | J26: =IF(C26="","",C26=SUM(D26+E26+F26)) -> FALSE
B27: DS Léna | C27: =+Population!F26 -> 0 | D27: 72144 | E27: 8547 | F27: 8343 | G27: =IFERROR(D27/$C27*100,"") | H27: =IFERROR(E27/$C27*100,"") | I27: =IFERROR(F27/$C27*100,"") | J27: =IF(C27="","",C27=SUM(D27+E27+F27)) -> FALSE
B28: DS N'Dorola | C28: =+Population!F27 -> 0 | D28: 102157 | E28: 40779 | F28: 34725 | G28: =IFERROR(D28/$C28*100,"") | H28: =IFERROR(E28/$C28*100,"") | I28: =IFERROR(F28/$C28*100,"") | J28: =IF(C28="","",C28=SUM(D28+E28+F28)) -> FALSE
B29: DS Orodara | C29: =+Population!F28 -> 0 | D29: 194957 | E29: 41624 | F29: 54934 | G29: =IFERROR(D29/$C29*100,"") | H29: =IFERROR(E29/$C29*100,"") | I29: =IFERROR(F29/$C29*100,"") | J29: =IF(C29="","",C29=SUM(D29+E29+F29)) -> FALSE
A30: Kadiogo | C30: =+Population!F29 -> 0 | D30: =SUM(D31:D42) -> 3600935 | E30: =SUM(E31:E42) -> 107431 | F30: =SUM(F31:F42) -> 14774 | G30: =IFERROR(D30/$C30*100,"") | H30: =IFERROR(E30/$C30*100,"") | I30: =IFERROR(F30/$C30*100,"") | J30: =IF(C30="","",C30=SUM(D30+E30+F30)) -> FALSE
B31: CHU Bogodogo | C31: =+Population!F30 -> 0 | G31: =IFERROR(D31/$C31*100,"") | H31: =IFERROR(E31/$C31*100,"") | I31: =IFERROR(F31/$C31*100,"") | J31: =IF(C31="","",C31=SUM(D31+E31+F31)) -> TRUE
B32: CHU Pédiatrique CDG | C32: =+Population!F31 -> 0 | G32: =IFERROR(D32/$C32*100,"") | H32: =IFERROR(E32/$C32*100,"") | I32: =IFERROR(F32/$C32*100,"") | J32: =IF(C32="","",C32=SUM(D32+E32+F32)) -> TRUE
B33: CHU Tengandogo | C33: =+Population!F32 -> 0 | G33: =IFERROR(D33/$C33*100,"") | H33: =IFERROR(E33/$C33*100,"") | I33: =IFERROR(F33/$C33*100,"") | J33: =IF(C33="","",C33=SUM(D33+E33+F33)) -> TRUE
B34: CHU Yalgado | C34: =+Population!F33 -> 0 | G34: =IFERROR(D34/$C34*100,"") | H34: =IFERROR(E34/$C34*100,"") | I34: =IFERROR(F34/$C34*100,"") | J34: =IF(C34="","",C34=SUM(D34+E34+F34)) -> TRUE
B35: Hôpital Paul VI | C35: =+Population!F34 -> 0 | G35: =IFERROR(D35/$C35*100,"") | H35: =IFERROR(E35/$C35*100,"") | I35: =IFERROR(F35/$C35*100,"") | J35: =IF(C35="","",C35=SUM(D35+E35+F35)) -> TRUE
B36: Hôpital Saint Camille | C36: =+Population!F35 -> 0 | G36: =IFERROR(D36/$C36*100,"") | H36: =IFERROR(E36/$C36*100,"") | I36: =IFERROR(F36/$C36*100,"") | J36: =IF(C36="","",C36=SUM(D36+E36+F36)) -> TRUE
B37: Hôpital SCHIPHRA | C37: =+Population!F36 -> 0 | G37: =IFERROR(D37/$C37*100,"") | H37: =IFERROR(E37/$C37*100,"") | I37: =IFERROR(F37/$C37*100,"") | J37: =IF(C37="","",C37=SUM(D37+E37+F37)) -> TRUE
B38: DS Baskuy | C38: =+Population!F37 -> 0 | D38: 184704 | E38: 0 | F38: 0 | G38: =IFERROR(D38/$C38*100,"") | H38: =IFERROR(E38/$C38*100,"") | I38: =IFERROR(F38/$C38*100,"") | J38: =IF(C38="","",C38=SUM(D38+E38+F38)) -> FALSE
B39: DS Bogodogo | C39: =+Population!F38 -> 0 | D39: 1129454 | E39: 29109 | F39: 5823 | G39: =IFERROR(D39/$C39*100,"") | H39: =IFERROR(E39/$C39*100,"") | I39: =IFERROR(F39/$C39*100,"") | J39: =IF(C39="","",C39=SUM(D39+E39+F39)) -> FALSE
B40: DS Boulmiougou | C40: =+Population!F39 -> 0 | D40: 1194422 | E40: 72976 | F40: 8951 | G40: =IFERROR(D40/$C40*100,"") | H40: =IFERROR(E40/$C40*100,"") | I40: =IFERROR(F40/$C40*100,"") | J40: =IF(C40="","",C40=SUM(D40+E40+F40)) -> FALSE
B41: DS Nongr-Massom | C41: =+Population!F40 -> 0 | D41: 384822 | E41: 0 | F41: 0 | G41: =IFERROR(D41/$C41*100,"") | H41: =IFERROR(E41/$C41*100,"") | I41: =IFERROR(F41/$C41*100,"") | J41: =IF(C41="","",C41=SUM(D41+E41+F41)) -> FALSE
B42: DS Sig-Noghin | C42: =+Population!F41 -> 0 | D42: 707533 | E42: 5346 | F42: 0 | G42: =IFERROR(D42/$C42*100,"") | H42: =IFERROR(E42/$C42*100,"") | I42: =IFERROR(F42/$C42*100,"") | J42: =IF(C42="","",C42=SUM(D42+E42+F42)) -> FALSE
A43: Koulsé | C43: =+Population!F42 -> 0 | D43: =SUM(D44:D50) -> 1246183.9 | E43: =SUM(E44:E50) -> 586591.9 | F43: =SUM(F44:F50) -> 416093.22 | G43: =IFERROR(D43/$C43*100,"") | H43: =IFERROR(E43/$C43*100,"") | I43: =IFERROR(F43/$C43*100,"") | J43: =IF(C43="","",C43=SUM(D43+E43+F43)) -> FALSE
B44: CHR Kaya | C44: =+Population!F43 -> 0 | G44: =IFERROR(D44/$C44*100,"") | H44: =IFERROR(E44/$C44*100,"") | I44: =IFERROR(F44/$C44*100,"") | J44: =IF(C44="","",C44=SUM(D44+E44+F44)) -> TRUE
B45: DS Barsalogho | C45: =+Population!F44 -> 0 | D45: 77118.883 | E45: 66990.898 | F45: 83759.218 | G45: =IFERROR(D45/$C45*100,"") | H45: =IFERROR(E45/$C45*100,"") | I45: =IFERROR(F45/$C45*100,"") | J45: =IF(C45="","",C45=SUM(D45+E45+F45)) -> FALSE
B46: DS Boulsa | C46: =+Population!F45 -> 0 | D46: 165869 | E46: 68858 | F46: 39781 | G46: =IFERROR(D46/$C46*100,"") | H46: =IFERROR(E46/$C46*100,"") | I46: =IFERROR(F46/$C46*100,"") | J46: =IF(C46="","",C46=SUM(D46+E46+F46)) -> FALSE
B47: DS Boussouma | C47: =+Population!F46 -> 0 | D47: 137229 | E47: 71468 | F47: 46130 | G47: =IFERROR(D47/$C47*100,"") | H47: =IFERROR(E47/$C47*100,"") | I47: =IFERROR(F47/$C47*100,"") | J47: =IF(C47="","",C47=SUM(D47+E47+F47)) -> FALSE
B48: DS Kaya | C48: =+Population!F47 -> 0 | D48: 316341 | E48: 163613 | F48: 86946 | G48: =IFERROR(D48/$C48*100,"") | H48: =IFERROR(E48/$C48*100,"") | I48: =IFERROR(F48/$C48*100,"") | J48: =IF(C48="","",C48=SUM(D48+E48+F48)) -> FALSE
B49: DS Kongoussi | C49: =+Population!F48 -> 0 | D49: 359738 | E49: 163610 | F49: 59626 | G49: =IFERROR(D49/$C49*100,"") | H49: =IFERROR(E49/$C49*100,"") | I49: =IFERROR(F49/$C49*100,"") | J49: =IF(C49="","",C49=SUM(D49+E49+F49)) -> FALSE
B50: DS Tougouri | C50: =+Population!F49 -> 0 | D50: 189888 | E50: 52052 | F50: 99851 | G50: =IFERROR(D50/$C50*100,"") | H50: =IFERROR(E50/$C50*100,"") | I50: =IFERROR(F50/$C50*100,"") | J50: =IF(C50="","",C50=SUM(D50+E50+F50)) -> FALSE
A51: Liptako | C51: =+Population!F50 -> 0 | D51: =SUM(D52:D55) -> 341083.28 | E51: =SUM(E52:E55) -> 135815.45 | F51: =SUM(F52:F55) -> 357674.27 | G51: =IFERROR(D51/$C51*100,"") | H51: =IFERROR(E51/$C51*100,"") | I51: =IFERROR(F51/$C51*100,"") | J51: =IF(C51="","",C51=SUM(D51+E51+F51)) -> FALSE
B52: CHR Dori | C52: =+Population!F51 -> 0 | G52: =IFERROR(D52/$C52*100,"") | H52: =IFERROR(E52/$C52*100,"") | I52: =IFERROR(F52/$C52*100,"") | J52: =IF(C52="","",C52=SUM(D52+E52+F52)) -> TRUE
B53: DS Dori | C53: =+Population!F52 -> 0 | D53: 201706 | E53: 85587 | F53: 192959 | G53: =IFERROR(D53/$C53*100,"") | H53: =IFERROR(E53/$C53*100,"") | I53: =IFERROR(F53/$C53*100,"") | J53: =IF(C53="","",C53=SUM(D53+E53+F53)) -> FALSE
B54: DS Gorom-Gorom | C54: =+Population!F53 -> 0 | D54: 56524.457 | E54: 14270.821 | F54: 94043.722 | G54: =IFERROR(D54/$C54*100,"") | H54: =IFERROR(E54/$C54*100,"") | I54: =IFERROR(F54/$C54*100,"") | J54: =IF(C54="","",C54=SUM(D54+E54+F54)) -> FALSE
B55: DS Sebba | C55: =+Population!F54 -> 0 | D55: 82852.819 | E55: 35957.632 | F55: 70671.549 | G55: =IFERROR(D55/$C55*100,"") | H55: =IFERROR(E55/$C55*100,"") | I55: =IFERROR(F55/$C55*100,"") | J55: =IF(C55="","",C55=SUM(D55+E55+F55)) -> FALSE
A56: Nakambé | C56: =+Population!F55 -> 0 | D56: =SUM(D57:D64) -> 1141904 | E56: =SUM(E57:E64) -> 432733 | F56: =SUM(F57:F64) -> 279069 | G56: =IFERROR(D56/$C56*100,"") | H56: =IFERROR(E56/$C56*100,"") | I56: =IFERROR(F56/$C56*100,"") | J56: =IF(C56="","",C56=SUM(D56+E56+F56)) -> FALSE
B57: CHR Tenkodogo | C57: =+Population!F56 -> 0 | G57: =IFERROR(D57/$C57*100,"") | H57: =IFERROR(E57/$C57*100,"") | I57: =IFERROR(F57/$C57*100,"") | J57: =IF(C57="","",C57=SUM(D57+E57+F57)) -> TRUE
B58: DS Bittou | C58: =+Population!F57 -> 0 | D58: 89784 | E58: 41908 | F58: 29548 | G58: =IFERROR(D58/$C58*100,"") | H58: =IFERROR(E58/$C58*100,"") | I58: =IFERROR(F58/$C58*100,"") | J58: =IF(C58="","",C58=SUM(D58+E58+F58)) -> FALSE
B59: DS Garango | C59: =+Population!F58 -> 0 | D59: 198490 | E59: 33417 | F59: 8417 | G59: =IFERROR(D59/$C59*100,"") | H59: =IFERROR(E59/$C59*100,"") | I59: =IFERROR(F59/$C59*100,"") | J59: =IF(C59="","",C59=SUM(D59+E59+F59)) -> FALSE
B60: DS Koupéla | C60: =+Population!F59 -> 0 | D60: 175954 | E60: 82725 | F60: 39724 | G60: =IFERROR(D60/$C60*100,"") | H60: =IFERROR(E60/$C60*100,"") | I60: =IFERROR(F60/$C60*100,"") | J60: =IF(C60="","",C60=SUM(D60+E60+F60)) -> FALSE
B61: DS Ouargaye | C61: =+Population!F60 -> 0 | D61: 223310 | E61: 84513 | F61: 117819 | G61: =IFERROR(D61/$C61*100,"") | H61: =IFERROR(E61/$C61*100,"") | I61: =IFERROR(F61/$C61*100,"") | J61: =IF(C61="","",C61=SUM(D61+E61+F61)) -> FALSE
B62: DS Pouytenga | C62: =+Population!F61 -> 0 | D62: 184240 | E62: 73356 | F62: 11733 | G62: =IFERROR(D62/$C62*100,"") | H62: =IFERROR(E62/$C62*100,"") | I62: =IFERROR(F62/$C62*100,"") | J62: =IF(C62="","",C62=SUM(D62+E62+F62)) -> FALSE
B63: DS Tenkodogo | C63: =+Population!F62 -> 0 | D63: 159035 | E63: 70889 | F63: 26786 | G63: =IFERROR(D63/$C63*100,"") | H63: =IFERROR(E63/$C63*100,"") | I63: =IFERROR(F63/$C63*100,"") | J63: =IF(C63="","",C63=SUM(D63+E63+F63)) -> FALSE
B64: DS Zabré | C64: =+Population!F63 -> 0 | D64: 111091 | E64: 45925 | F64: 45042 | G64: =IFERROR(D64/$C64*100,"") | H64: =IFERROR(E64/$C64*100,"") | I64: =IFERROR(F64/$C64*100,"") | J64: =IF(C64="","",C64=SUM(D64+E64+F64)) -> FALSE
A65: Nando | C65: =+Population!F64 -> 0 | D65: =SUM(D66:D73) -> 1261865 | E65: =SUM(E66:E73) -> 354844 | F65: =SUM(F66:F73) -> 331218 | G65: =IFERROR(D65/$C65*100,"") | H65: =IFERROR(E65/$C65*100,"") | I65: =IFERROR(F65/$C65*100,"") | J65: =IF(C65="","",C65=SUM(D65+E65+F65)) -> FALSE
B66: CHR Koudougou | C66: =+Population!F65 -> 0 | G66: =IFERROR(D66/$C66*100,"") | H66: =IFERROR(E66/$C66*100,"") | I66: =IFERROR(F66/$C66*100,"") | J66: =IF(C66="","",C66=SUM(D66+E66+F66)) -> TRUE
B67: DS Koudougou | C67: =+Population!F66 -> 0 | D67: 364423 | E67: 111527 | F67: 0 | G67: =IFERROR(D67/$C67*100,"") | H67: =IFERROR(E67/$C67*100,"") | I67: =IFERROR(F67/$C67*100,"") | J67: =IF(C67="","",C67=SUM(D67+E67+F67)) -> FALSE
B68: DS Léo | C68: =+Population!F67 -> 0 | D68: 168777 | E68: 70435 | F68: 167879 | G68: =IFERROR(D68/$C68*100,"") | H68: =IFERROR(E68/$C68*100,"") | I68: =IFERROR(F68/$C68*100,"") | J68: =IF(C68="","",C68=SUM(D68+E68+F68)) -> FALSE
B69: DS Nanoro | C69: =+Population!F68 -> 0 | D69: 156108 | E69: 38629 | F69: 4276 | G69: =IFERROR(D69/$C69*100,"") | H69: =IFERROR(E69/$C69*100,"") | I69: =IFERROR(F69/$C69*100,"") | J69: =IF(C69="","",C69=SUM(D69+E69+F69)) -> FALSE
B70: DS Réo | C70: =+Population!F69 -> 0 | D70: 155493 | E70: 51889 | F70: 22773 | G70: =IFERROR(D70/$C70*100,"") | H70: =IFERROR(E70/$C70*100,"") | I70: =IFERROR(F70/$C70*100,"") | J70: =IF(C70="","",C70=SUM(D70+E70+F70)) -> FALSE
B71: DS Sabou | C71: =+Population!F70 -> 0 | D71: 108341 | E71: 19497 | F71: 1930 | G71: =IFERROR(D71/$C71*100,"") | H71: =IFERROR(E71/$C71*100,"") | I71: =IFERROR(F71/$C71*100,"") | J71: =IF(C71="","",C71=SUM(D71+E71+F71)) -> FALSE
B72: DS Sapouy | C72: =+Population!F71 -> 0 | D72: 163064 | E72: 26144 | F72: 93212 | G72: =IFERROR(D72/$C72*100,"") | H72: =IFERROR(E72/$C72*100,"") | I72: =IFERROR(F72/$C72*100,"") | J72: =IF(C72="","",C72=SUM(D72+E72+F72)) -> FALSE
B73: DS Tenado | C73: =+Population!F72 -> 0 | D73: 145659 | E73: 36723 | F73: 41148 | G73: =IFERROR(D73/$C73*100,"") | H73: =IFERROR(E73/$C73*100,"") | I73: =IFERROR(F73/$C73*100,"") | J73: =IF(C73="","",C73=SUM(D73+E73+F73)) -> FALSE
A74: Nazinon | C74: =+Population!F73 -> 0 | D74: =SUM(D75:D79) -> 478764 | E74: =SUM(E75:E79) -> 172687 | F74: =SUM(F75:F79) -> 249879 | G74: =IFERROR(D74/$C74*100,"") | H74: =IFERROR(E74/$C74*100,"") | I74: =IFERROR(F74/$C74*100,"") | J74: =IF(C74="","",C74=SUM(D74+E74+F74)) -> FALSE
B75: CHR Manga | C75: =+Population!F74 -> 0 | G75: =IFERROR(D75/$C75*100,"") | H75: =IFERROR(E75/$C75*100,"") | I75: =IFERROR(F75/$C75*100,"") | J75: =IF(C75="","",C75=SUM(D75+E75+F75)) -> TRUE
B76: DS Kombissiri | C76: =+Population!F75 -> 0 | D76: 113937 | E76: 56593 | F76: 36295 | G76: =IFERROR(D76/$C76*100,"") | H76: =IFERROR(E76/$C76*100,"") | I76: =IFERROR(F76/$C76*100,"") | J76: =IF(C76="","",C76=SUM(D76+E76+F76)) -> FALSE
B77: DS Manga | C77: =+Population!F76 -> 0 | D77: 193287 | E77: 67391 | F77: 98151 | G77: =IFERROR(D77/$C77*100,"") | H77: =IFERROR(E77/$C77*100,"") | I77: =IFERROR(F77/$C77*100,"") | J77: =IF(C77="","",C77=SUM(D77+E77+F77)) -> FALSE
B78: DS Po | C78: =+Population!F77 -> 0 | D78: 118903 | E78: 41644 | F78: 63823 | G78: =IFERROR(D78/$C78*100,"") | H78: =IFERROR(E78/$C78*100,"") | I78: =IFERROR(F78/$C78*100,"") | J78: =IF(C78="","",C78=SUM(D78+E78+F78)) -> FALSE
B79: DS Sapone | C79: =+Population!F78 -> 0 | D79: 52637 | E79: 7059 | F79: 51610 | G79: =IFERROR(D79/$C79*100,"") | H79: =IFERROR(E79/$C79*100,"") | I79: =IFERROR(F79/$C79*100,"") | J79: =IF(C79="","",C79=SUM(D79+E79+F79)) -> FALSE
A80: Oubri | C80: =+Population!F79 -> 0 | D80: =SUM(D81:D84) -> 746987 | E80: =SUM(E81:E84) -> 254908 | F80: =SUM(F81:F84) -> 147402 | G80: =IFERROR(D80/$C80*100,"") | H80: =IFERROR(E80/$C80*100,"") | I80: =IFERROR(F80/$C80*100,"") | J80: =IF(C80="","",C80=SUM(D80+E80+F80)) -> FALSE
B81: CHR Ziniaré | C81: =+Population!F80 -> 0 | G81: =IFERROR(D81/$C81*100,"") | H81: =IFERROR(E81/$C81*100,"") | I81: =IFERROR(F81/$C81*100,"") | J81: =IF(C81="","",C81=SUM(D81+E81+F81)) -> TRUE
B82: DS Boussé | C82: =+Population!F81 -> 0 | D82: 142709 | E82: 44609 | F82: 22427 | G82: =IFERROR(D82/$C82*100,"") | H82: =IFERROR(E82/$C82*100,"") | I82: =IFERROR(F82/$C82*100,"") | J82: =IF(C82="","",C82=SUM(D82+E82+F82)) -> FALSE
B83: DS Ziniaré | C83: =+Population!F82 -> 0 | D83: 262400 | E83: 65235 | F83: 36809 | G83: =IFERROR(D83/$C83*100,"") | H83: =IFERROR(E83/$C83*100,"") | I83: =IFERROR(F83/$C83*100,"") | J83: =IF(C83="","",C83=SUM(D83+E83+F83)) -> FALSE
B84: DS Zorgho | C84: =+Population!F83 -> 0 | D84: 341878 | E84: 145064 | F84: 88166 | G84: =IFERROR(D84/$C84*100,"") | H84: =IFERROR(E84/$C84*100,"") | I84: =IFERROR(F84/$C84*100,"") | J84: =IF(C84="","",C84=SUM(D84+E84+F84)) -> FALSE
A85: Sirba | C85: =+Population!F84 -> 0 | D85: =SUM(D86:D88) -> 299205 | E85: =SUM(E86:E88) -> 278216 | F85: =SUM(F86:F88) -> 365618 | G85: =IFERROR(D85/$C85*100,"") | H85: =IFERROR(E85/$C85*100,"") | I85: =IFERROR(F85/$C85*100,"") | J85: =IF(C85="","",C85=SUM(D85+E85+F85)) -> FALSE
B86: DS Bogande | C86: =+Population!F85 -> 0 | D86: 154822 | E86: 156893 | F86: 194690 | G86: =IFERROR(D86/$C86*100,"") | H86: =IFERROR(E86/$C86*100,"") | I86: =IFERROR(F86/$C86*100,"") | J86: =IF(C86="","",C86=SUM(D86+E86+F86)) -> FALSE
B87: DS Gayeri | C87: =+Population!F86 -> 0 | D87: 38332 | E87: 25808 | F87: 58323 | G87: =IFERROR(D87/$C87*100,"") | H87: =IFERROR(E87/$C87*100,"") | I87: =IFERROR(F87/$C87*100,"") | J87: =IF(C87="","",C87=SUM(D87+E87+F87)) -> FALSE
B88: DS Manni | C88: =+Population!F87 -> 0 | D88: 106051 | E88: 95515 | F88: 112605 | G88: =IFERROR(D88/$C88*100,"") | H88: =IFERROR(E88/$C88*100,"") | I88: =IFERROR(F88/$C88*100,"") | J88: =IF(C88="","",C88=SUM(D88+E88+F88)) -> FALSE
A89: Soum | C89: =+Population!F88 -> 0 | D89: =D90 -> 183061 | E89: =E90 -> 68063 | F89: =F90 -> 148557 | G89: =IFERROR(D89/$C89*100,"") | H89: =IFERROR(E89/$C89*100,"") | I89: =IFERROR(F89/$C89*100,"") | J89: =IF(C89="","",C89=SUM(D89+E89+F89)) -> FALSE
B90: DS Djibo | C90: =+Population!F89 -> 0 | D90: 183061 | E90: 68063 | F90: 148557 | G90: =IFERROR(D90/$C90*100,"") | H90: =IFERROR(E90/$C90*100,"") | I90: =IFERROR(F90/$C90*100,"") | J90: =IF(C90="","",C90=SUM(D90+E90+F90)) -> FALSE
A91: Sourou | C91: =+Population!F90 -> 0 | D91: =SUM(D92:D94) -> 605852 | E91: =SUM(E92:E94) -> 224194 | F91: =SUM(F92:F94) -> 170963 | G91: =IFERROR(D91/$C91*100,"") | H91: =IFERROR(E91/$C91*100,"") | I91: =IFERROR(F91/$C91*100,"") | J91: =IF(C91="","",C91=SUM(D91+E91+F91)) -> FALSE
B92: DS Nouna | C92: =+Population!F91 -> 0 | D92: 208166 | E92: 99969 | F92: 103396 | G92: =IFERROR(D92/$C92*100,"") | H92: =IFERROR(E92/$C92*100,"") | I92: =IFERROR(F92/$C92*100,"") | J92: =IF(C92="","",C92=SUM(D92+E92+F92)) -> FALSE
B93: DS Toma | C93: =+Population!F92 -> 0 | D93: 179744 | E93: 48453 | F93: 32302 | G93: =IFERROR(D93/$C93*100,"") | H93: =IFERROR(E93/$C93*100,"") | I93: =IFERROR(F93/$C93*100,"") | J93: =IF(C93="","",C93=SUM(D93+E93+F93)) -> FALSE
B94: DS Tougan | C94: =+Population!F93 -> 0 | D94: 217942 | E94: 75772 | F94: 35265 | G94: =IFERROR(D94/$C94*100,"") | H94: =IFERROR(E94/$C94*100,"") | I94: =IFERROR(F94/$C94*100,"") | J94: =IF(C94="","",C94=SUM(D94+E94+F94)) -> FALSE
A95: Tannounyan | C95: =+Population!F94 -> 0 | D95: =SUM(D96:D99) -> 493882 | E95: =SUM(E96:E99) -> 175170 | F95: =SUM(F96:F99) -> 301506 | G95: =IFERROR(D95/$C95*100,"") | H95: =IFERROR(E95/$C95*100,"") | I95: =IFERROR(F95/$C95*100,"") | J95: =IF(C95="","",C95=SUM(D95+E95+F95)) -> FALSE
B96: CHR Banfora | C96: =+Population!F95 -> 0 | G96: =IFERROR(D96/$C96*100,"") | H96: =IFERROR(E96/$C96*100,"") | I96: =IFERROR(F96/$C96*100,"") | J96: =IF(C96="","",C96=SUM(D96+E96+F96)) -> TRUE
B97: DS Banfora | C97: =+Population!F96 -> 0 | D97: 258277 | E97: 70755 | F97: 125368 | G97: =IFERROR(D97/$C97*100,"") | H97: =IFERROR(E97/$C97*100,"") | I97: =IFERROR(F97/$C97*100,"") | J97: =IF(C97="","",C97=SUM(D97+E97+F97)) -> FALSE
B98: DS Mangodara | C98: =+Population!F97 -> 0 | D98: 85181 | E98: 56057 | F98: 163068 | G98: =IFERROR(D98/$C98*100,"") | H98: =IFERROR(E98/$C98*100,"") | I98: =IFERROR(F98/$C98*100,"") | J98: =IF(C98="","",C98=SUM(D98+E98+F98)) -> FALSE
B99: DS Sindou | C99: =+Population!F98 -> 0 | D99: 150424 | E99: 48358 | F99: 13070 | G99: =IFERROR(D99/$C99*100,"") | H99: =IFERROR(E99/$C99*100,"") | I99: =IFERROR(F99/$C99*100,"") | J99: =IF(C99="","",C99=SUM(D99+E99+F99)) -> FALSE
A100: Tapoa | C100: =+Population!F99 -> 0 | D100: =SUM(D101) -> 279876 | E100: =SUM(E101) -> 199131 | F100: =SUM(F101) -> 265800 | G100: =IFERROR(D100/$C100*100,"") | H100: =IFERROR(E100/$C100*100,"") | I100: =IFERROR(F100/$C100*100,"") | J100: =IF(C100="","",C100=SUM(D100+E100+F100)) -> FALSE
...

Sheet Complétude
A1: Tableau 1.08: Complétude des rapports mensuels des formations sanitaires en 2025
A2: Régions / districts | C2: Formations sanitaires publiques | F2: Formations sanitaires privées | I2: Formations sanitaires publiques et privées
C3: Nombre de rapports attendus | D3: Nombre de rapports saisis | E3: Complétude (%) des rapports dans la base | F3: Nombre de rapports attendus | G3: Nombre de rapports saisis | H3: Complétude (%) des rapports dans la base | I3: Nombre de rapports attendus | J3: Nombre de rapports saisis | K3: Complétude (%) des rapports dans la base | L3: Nombre de rapports saisis à temps | M3: Promptitude (%) des rapports dans la base
A4: Bankui | E4: =IF(C4=0,"",D4/C4*100) | H4: =IF(F4=0,"",G4/F4*100) | I4: =SUM(C4)+SUM(F4) -> 0 | J4: =D4+G4 -> 0 | K4: =IF(I4=0,"",J4/I4*100) | M4: =IF(I4=0,"",L4/I4*100)
B5: CHR Dédougou | E5: =IF(C5=0,"",D5/C5*100) | H5: =IF(F5=0,"",G5/F5*100) | I5: =SUM(C5)+SUM(F5) -> 0 | J5: =D5+G5 -> 0 | K5: =IF(I5=0,"",J5/I5*100) | M5: =IF(I5=0,"",L5/I5*100)
B6: DS Boromo | E6: =IF(C6=0,"",D6/C6*100) | H6: =IF(F6=0,"",G6/F6*100) | I6: =SUM(C6)+SUM(F6) -> 0 | J6: =D6+G6 -> 0 | K6: =IF(I6=0,"",J6/I6*100) | M6: =IF(I6=0,"",L6/I6*100)
B7: DS Dedougou | E7: =IF(C7=0,"",D7/C7*100) | H7: =IF(F7=0,"",G7/F7*100) | I7: =SUM(C7)+SUM(F7) -> 0 | J7: =D7+G7 -> 0 | K7: =IF(I7=0,"",J7/I7*100) | M7: =IF(I7=0,"",L7/I7*100)
B8: DS Solenzo | E8: =IF(C8=0,"",D8/C8*100) | H8: =IF(F8=0,"",G8/F8*100) | I8: =SUM(C8)+SUM(F8) -> 0 | J8: =D8+G8 -> 0 | K8: =IF(I8=0,"",J8/I8*100) | M8: =IF(I8=0,"",L8/I8*100)
A9: Djoro | E9: =IF(C9=0,"",D9/C9*100) | H9: =IF(F9=0,"",G9/F9*100) | I9: =SUM(C9)+SUM(F9) -> 0 | J9: =D9+G9 -> 0 | K9: =IF(I9=0,"",J9/I9*100) | M9: =IF(I9=0,"",L9/I9*100)
B10: CHR Gaoua | E10: =IF(C10=0,"",D10/C10*100) | H10: =IF(F10=0,"",G10/F10*100) | I10: =SUM(C10)+SUM(F10) -> 0 | J10: =D10+G10 -> 0 | K10: =IF(I10=0,"",J10/I10*100) | M10: =IF(I10=0,"",L10/I10*100)
B11: DS Batié | E11: =IF(C11=0,"",D11/C11*100) | H11: =IF(F11=0,"",G11/F11*100) | I11: =SUM(C11)+SUM(F11) -> 0 | J11: =D11+G11 -> 0 | K11: =IF(I11=0,"",J11/I11*100) | M11: =IF(I11=0,"",L11/I11*100)
B12: DS Dano | E12: =IF(C12=0,"",D12/C12*100) | H12: =IF(F12=0,"",G12/F12*100) | I12: =SUM(C12)+SUM(F12) -> 0 | J12: =D12+G12 -> 0 | K12: =IF(I12=0,"",J12/I12*100) | M12: =IF(I12=0,"",L12/I12*100)
B13: DS Diébougou | E13: =IF(C13=0,"",D13/C13*100) | H13: =IF(F13=0,"",G13/F13*100) | I13: =SUM(C13)+SUM(F13) -> 0 | J13: =D13+G13 -> 0 | K13: =IF(I13=0,"",J13/I13*100) | M13: =IF(I13=0,"",L13/I13*100)
B14: DS Gaoua | E14: =IF(C14=0,"",D14/C14*100) | H14: =IF(F14=0,"",G14/F14*100) | I14: =SUM(C14)+SUM(F14) -> 0 | J14: =D14+G14 -> 0 | K14: =IF(I14=0,"",J14/I14*100) | M14: =IF(I14=0,"",L14/I14*100)
B15: DS Kampti | E15: =IF(C15=0,"",D15/C15*100) | H15: =IF(F15=0,"",G15/F15*100) | I15: =SUM(C15)+SUM(F15) -> 0 | J15: =D15+G15 -> 0 | K15: =IF(I15=0,"",J15/I15*100) | M15: =IF(I15=0,"",L15/I15*100)
A16: Goulmou | E16: =IF(C16=0,"",D16/C16*100) | H16: =IF(F16=0,"",G16/F16*100) | I16: =SUM(C16)+SUM(F16) -> 0 | J16: =D16+G16 -> 0 | K16: =IF(I16=0,"",J16/I16*100) | M16: =IF(I16=0,"",L16/I16*100)
B17: CHR Fada N'Gourma | E17: =IF(C17=0,"",D17/C17*100) | H17: =IF(F17=0,"",G17/F17*100) | I17: =SUM(C17)+SUM(F17) -> 0 | J17: =D17+G17 -> 0 | K17: =IF(I17=0,"",J17/I17*100) | M17: =IF(I17=0,"",L17/I17*100)
B18: DS Fada | E18: =IF(C18=0,"",D18/C18*100) | H18: =IF(F18=0,"",G18/F18*100) | I18: =SUM(C18)+SUM(F18) -> 0 | J18: =D18+G18 -> 0 | K18: =IF(I18=0,"",J18/I18*100) | M18: =IF(I18=0,"",L18/I18*100)
B19: DS Pama | E19: =IF(C19=0,"",D19/C19*100) | H19: =IF(F19=0,"",G19/F19*100) | I19: =SUM(C19)+SUM(F19) -> 0 | J19: =D19+G19 -> 0 | K19: =IF(I19=0,"",J19/I19*100) | M19: =IF(I19=0,"",L19/I19*100)
A20: Guiriko | E20: =IF(C20=0,"",D20/C20*100) | H20: =IF(F20=0,"",G20/F20*100) | I20: =SUM(C20)+SUM(F20) -> 0 | J20: =D20+G20 -> 0 | K20: =IF(I20=0,"",J20/I20*100) | M20: =IF(I20=0,"",L20/I20*100)
B21: CHU Sanou Souro | E21: =IF(C21=0,"",D21/C21*100) | H21: =IF(F21=0,"",G21/F21*100) | I21: =SUM(C21)+SUM(F21) -> 0 | J21: =D21+G21 -> 0 | K21: =IF(I21=0,"",J21/I21*100) | M21: =IF(I21=0,"",L21/I21*100)
B22: DS Dafra | E22: =IF(C22=0,"",D22/C22*100) | H22: =IF(F22=0,"",G22/F22*100) | I22: =SUM(C22)+SUM(F22) -> 0 | J22: =D22+G22 -> 0 | K22: =IF(I22=0,"",J22/I22*100) | M22: =IF(I22=0,"",L22/I22*100)
B23: DS Dande | E23: =IF(C23=0,"",D23/C23*100) | H23: =IF(F23=0,"",G23/F23*100) | I23: =SUM(C23)+SUM(F23) -> 0 | J23: =D23+G23 -> 0 | K23: =IF(I23=0,"",J23/I23*100) | M23: =IF(I23=0,"",L23/I23*100)
B24: DS Do | E24: =IF(C24=0,"",D24/C24*100) | H24: =IF(F24=0,"",G24/F24*100) | I24: =SUM(C24)+SUM(F24) -> 0 | J24: =D24+G24 -> 0 | K24: =IF(I24=0,"",J24/I24*100) | M24: =IF(I24=0,"",L24/I24*100)
B25: DS Hounde | E25: =IF(C25=0,"",D25/C25*100) | H25: =IF(F25=0,"",G25/F25*100) | I25: =SUM(C25)+SUM(F25) -> 0 | J25: =D25+G25 -> 0 | K25: =IF(I25=0,"",J25/I25*100) | M25: =IF(I25=0,"",L25/I25*100)
B26: DS Karangasso Vigue | E26: =IF(C26=0,"",D26/C26*100) | H26: =IF(F26=0,"",G26/F26*100) | I26: =SUM(C26)+SUM(F26) -> 0 | J26: =D26+G26 -> 0 | K26: =IF(I26=0,"",J26/I26*100) | M26: =IF(I26=0,"",L26/I26*100)
B27: DS Léna | E27: =IF(C27=0,"",D27/C27*100) | H27: =IF(F27=0,"",G27/F27*100) | I27: =SUM(C27)+SUM(F27) -> 0 | J27: =D27+G27 -> 0 | K27: =IF(I27=0,"",J27/I27*100) | M27: =IF(I27=0,"",L27/I27*100)
B28: DS N'Dorola | E28: =IF(C28=0,"",D28/C28*100) | H28: =IF(F28=0,"",G28/F28*100) | I28: =SUM(C28)+SUM(F28) -> 0 | J28: =D28+G28 -> 0 | K28: =IF(I28=0,"",J28/I28*100) | M28: =IF(I28=0,"",L28/I28*100)
B29: DS Orodara | E29: =IF(C29=0,"",D29/C29*100) | H29: =IF(F29=0,"",G29/F29*100) | I29: =SUM(C29)+SUM(F29) -> 0 | J29: =D29+G29 -> 0 | K29: =IF(I29=0,"",J29/I29*100) | M29: =IF(I29=0,"",L29/I29*100)
A30: Kadiogo | E30: =IF(C30=0,"",D30/C30*100) | H30: =IF(F30=0,"",G30/F30*100) | I30: =SUM(C30)+SUM(F30) -> 0 | J30: =D30+G30 -> 0 | K30: =IF(I30=0,"",J30/I30*100) | M30: =IF(I30=0,"",L30/I30*100)
B31: CHU Bogodogo | E31: =IF(C31=0,"",D31/C31*100) | H31: =IF(F31=0,"",G31/F31*100) | I31: =SUM(C31)+SUM(F31) -> 0 | J31: =D31+G31 -> 0 | K31: =IF(I31=0,"",J31/I31*100) | M31: =IF(I31=0,"",L31/I31*100)
B32: CHU Pédiatrique CDG | E32: =IF(C32=0,"",D32/C32*100) | H32: =IF(F32=0,"",G32/F32*100) | I32: =SUM(C32)+SUM(F32) -> 0 | J32: =D32+G32 -> 0 | K32: =IF(I32=0,"",J32/I32*100) | M32: =IF(I32=0,"",L32/I32*100)
B33: CHU Tengandogo | E33: =IF(C33=0,"",D33/C33*100) | H33: =IF(F33=0,"",G33/F33*100) | I33: =SUM(C33)+SUM(F33) -> 0 | J33: =D33+G33 -> 0 | K33: =IF(I33=0,"",J33/I33*100) | M33: =IF(I33=0,"",L33/I33*100)
B34: CHU Yalgado | E34: =IF(C34=0,"",D34/C34*100) | H34: =IF(F34=0,"",G34/F34*100) | I34: =SUM(C34)+SUM(F34) -> 0 | J34: =D34+G34 -> 0 | K34: =IF(I34=0,"",J34/I34*100) | M34: =IF(I34=0,"",L34/I34*100)
B35: Hôpital Paul VI | E35: =IF(C35=0,"",D35/C35*100) | H35: =IF(F35=0,"",G35/F35*100) | I35: =SUM(C35)+SUM(F35) -> 0 | J35: =D35+G35 -> 0 | K35: =IF(I35=0,"",J35/I35*100) | M35: =IF(I35=0,"",L35/I35*100)
B36: Hôpital Saint Camille | E36: =IF(C36=0,"",D36/C36*100) | H36: =IF(F36=0,"",G36/F36*100) | I36: =SUM(C36)+SUM(F36) -> 0 | J36: =D36+G36 -> 0 | K36: =IF(I36=0,"",J36/I36*100) | M36: =IF(I36=0,"",L36/I36*100)
B37: Hôpital SCHIPHRA | E37: =IF(C37=0,"",D37/C37*100) | H37: =IF(F37=0,"",G37/F37*100) | I37: =SUM(C37)+SUM(F37) -> 0 | J37: =D37+G37 -> 0 | K37: =IF(I37=0,"",J37/I37*100) | M37: =IF(I37=0,"",L37/I37*100)
B38: DS Baskuy | E38: =IF(C38=0,"",D38/C38*100) | H38: =IF(F38=0,"",G38/F38*100) | I38: =SUM(C38)+SUM(F38) -> 0 | J38: =D38+G38 -> 0 | K38: =IF(I38=0,"",J38/I38*100) | M38: =IF(I38=0,"",L38/I38*100)
B39: DS Bogodogo | E39: =IF(C39=0,"",D39/C39*100) | H39: =IF(F39=0,"",G39/F39*100) | I39: =SUM(C39)+SUM(F39) -> 0 | J39: =D39+G39 -> 0 | K39: =IF(I39=0,"",J39/I39*100) | M39: =IF(I39=0,"",L39/I39*100)
B40: DS Boulmiougou | E40: =IF(C40=0,"",D40/C40*100) | H40: =IF(F40=0,"",G40/F40*100) | I40: =SUM(C40)+SUM(F40) -> 0 | J40: =D40+G40 -> 0 | K40: =IF(I40=0,"",J40/I40*100) | M40: =IF(I40=0,"",L40/I40*100)
B41: DS Nongr-Massom | E41: =IF(C41=0,"",D41/C41*100) | H41: =IF(F41=0,"",G41/F41*100) | I41: =SUM(C41)+SUM(F41) -> 0 | J41: =D41+G41 -> 0 | K41: =IF(I41=0,"",J41/I41*100) | M41: =IF(I41=0,"",L41/I41*100)
B42: DS Sig-Noghin | E42: =IF(C42=0,"",D42/C42*100) | H42: =IF(F42=0,"",G42/F42*100) | I42: =SUM(C42)+SUM(F42) -> 0 | J42: =D42+G42 -> 0 | K42: =IF(I42=0,"",J42/I42*100) | M42: =IF(I42=0,"",L42/I42*100)
A43: Koulsé | E43: =IF(C43=0,"",D43/C43*100) | H43: =IF(F43=0,"",G43/F43*100) | I43: =SUM(C43)+SUM(F43) -> 0 | J43: =D43+G43 -> 0 | K43: =IF(I43=0,"",J43/I43*100) | M43: =IF(I43=0,"",L43/I43*100)
B44: CHR Kaya | E44: =IF(C44=0,"",D44/C44*100) | H44: =IF(F44=0,"",G44/F44*100) | I44: =SUM(C44)+SUM(F44) -> 0 | J44: =D44+G44 -> 0 | K44: =IF(I44=0,"",J44/I44*100) | M44: =IF(I44=0,"",L44/I44*100)
B45: DS Barsalogho | E45: =IF(C45=0,"",D45/C45*100) | H45: =IF(F45=0,"",G45/F45*100) | I45: =SUM(C45)+SUM(F45) -> 0 | J45: =D45+G45 -> 0 | K45: =IF(I45=0,"",J45/I45*100) | M45: =IF(I45=0,"",L45/I45*100)
B46: DS Boulsa | E46: =IF(C46=0,"",D46/C46*100) | H46: =IF(F46=0,"",G46/F46*100) | I46: =SUM(C46)+SUM(F46) -> 0 | J46: =D46+G46 -> 0 | K46: =IF(I46=0,"",J46/I46*100) | M46: =IF(I46=0,"",L46/I46*100)
B47: DS Boussouma | E47: =IF(C47=0,"",D47/C47*100) | H47: =IF(F47=0,"",G47/F47*100) | I47: =SUM(C47)+SUM(F47) -> 0 | J47: =D47+G47 -> 0 | K47: =IF(I47=0,"",J47/I47*100) | M47: =IF(I47=0,"",L47/I47*100)
B48: DS Kaya | E48: =IF(C48=0,"",D48/C48*100) | H48: =IF(F48=0,"",G48/F48*100) | I48: =SUM(C48)+SUM(F48) -> 0 | J48: =D48+G48 -> 0 | K48: =IF(I48=0,"",J48/I48*100) | M48: =IF(I48=0,"",L48/I48*100)
B49: DS Kongoussi | E49: =IF(C49=0,"",D49/C49*100) | H49: =IF(F49=0,"",G49/F49*100) | I49: =SUM(C49)+SUM(F49) -> 0 | J49: =D49+G49 -> 0 | K49: =IF(I49=0,"",J49/I49*100) | M49: =IF(I49=0,"",L49/I49*100)
B50: DS Tougouri | E50: =IF(C50=0,"",D50/C50*100) | H50: =IF(F50=0,"",G50/F50*100) | I50: =SUM(C50)+SUM(F50) -> 0 | J50: =D50+G50 -> 0 | K50: =IF(I50=0,"",J50/I50*100) | M50: =IF(I50=0,"",L50/I50*100)
A51: Liptako | E51: =IF(C51=0,"",D51/C51*100) | H51: =IF(F51=0,"",G51/F51*100) | I51: =SUM(C51)+SUM(F51) -> 0 | J51: =D51+G51 -> 0 | K51: =IF(I51=0,"",J51/I51*100) | M51: =IF(I51=0,"",L51/I51*100)
B52: CHR Dori | E52: =IF(C52=0,"",D52/C52*100) | H52: =IF(F52=0,"",G52/F52*100) | I52: =SUM(C52)+SUM(F52) -> 0 | J52: =D52+G52 -> 0 | K52: =IF(I52=0,"",J52/I52*100) | M52: =IF(I52=0,"",L52/I52*100)
B53: DS Dori | E53: =IF(C53=0,"",D53/C53*100) | H53: =IF(F53=0,"",G53/F53*100) | I53: =SUM(C53)+SUM(F53) -> 0 | J53: =D53+G53 -> 0 | K53: =IF(I53=0,"",J53/I53*100) | M53: =IF(I53=0,"",L53/I53*100)
B54: DS Gorom-Gorom | E54: =IF(C54=0,"",D54/C54*100) | H54: =IF(F54=0,"",G54/F54*100) | I54: =SUM(C54)+SUM(F54) -> 0 | J54: =D54+G54 -> 0 | K54: =IF(I54=0,"",J54/I54*100) | M54: =IF(I54=0,"",L54/I54*100)
B55: DS Sebba | E55: =IF(C55=0,"",D55/C55*100) | H55: =IF(F55=0,"",G55/F55*100) | I55: =SUM(C55)+SUM(F55) -> 0 | J55: =D55+G55 -> 0 | K55: =IF(I55=0,"",J55/I55*100) | M55: =IF(I55=0,"",L55/I55*100)
A56: Nakambé | E56: =IF(C56=0,"",D56/C56*100) | H56: =IF(F56=0,"",G56/F56*100) | I56: =SUM(C56)+SUM(F56) -> 0 | J56: =D56+G56 -> 0 | K56: =IF(I56=0,"",J56/I56*100) | M56: =IF(I56=0,"",L56/I56*100)
B57: CHR Tenkodogo | E57: =IF(C57=0,"",D57/C57*100) | H57: =IF(F57=0,"",G57/F57*100) | I57: =SUM(C57)+SUM(F57) -> 0 | J57: =D57+G57 -> 0 | K57: =IF(I57=0,"",J57/I57*100) | M57: =IF(I57=0,"",L57/I57*100)
B58: DS Bittou | E58: =IF(C58=0,"",D58/C58*100) | H58: =IF(F58=0,"",G58/F58*100) | I58: =SUM(C58)+SUM(F58) -> 0 | J58: =D58+G58 -> 0 | K58: =IF(I58=0,"",J58/I58*100) | M58: =IF(I58=0,"",L58/I58*100)
B59: DS Garango | E59: =IF(C59=0,"",D59/C59*100) | H59: =IF(F59=0,"",G59/F59*100) | I59: =SUM(C59)+SUM(F59) -> 0 | J59: =D59+G59 -> 0 | K59: =IF(I59=0,"",J59/I59*100) | M59: =IF(I59=0,"",L59/I59*100)
B60: DS Koupéla | E60: =IF(C60=0,"",D60/C60*100) | H60: =IF(F60=0,"",G60/F60*100) | I60: =SUM(C60)+SUM(F60) -> 0 | J60: =D60+G60 -> 0 | K60: =IF(I60=0,"",J60/I60*100) | M60: =IF(I60=0,"",L60/I60*100)
B61: DS Ouargaye | E61: =IF(C61=0,"",D61/C61*100) | H61: =IF(F61=0,"",G61/F61*100) | I61: =SUM(C61)+SUM(F61) -> 0 | J61: =D61+G61 -> 0 | K61: =IF(I61=0,"",J61/I61*100) | M61: =IF(I61=0,"",L61/I61*100)
B62: DS Pouytenga | E62: =IF(C62=0,"",D62/C62*100) | H62: =IF(F62=0,"",G62/F62*100) | I62: =SUM(C62)+SUM(F62) -> 0 | J62: =D62+G62 -> 0 | K62: =IF(I62=0,"",J62/I62*100) | M62: =IF(I62=0,"",L62/I62*100)
B63: DS Tenkodogo | E63: =IF(C63=0,"",D63/C63*100) | H63: =IF(F63=0,"",G63/F63*100) | I63: =SUM(C63)+SUM(F63) -> 0 | J63: =D63+G63 -> 0 | K63: =IF(I63=0,"",J63/I63*100) | M63: =IF(I63=0,"",L63/I63*100)
B64: DS Zabré | E64: =IF(C64=0,"",D64/C64*100) | H64: =IF(F64=0,"",G64/F64*100) | I64: =SUM(C64)+SUM(F64) -> 0 | J64: =D64+G64 -> 0 | K64: =IF(I64=0,"",J64/I64*100) | M64: =IF(I64=0,"",L64/I64*100)
A65: Nando | E65: =IF(C65=0,"",D65/C65*100) | H65: =IF(F65=0,"",G65/F65*100) | I65: =SUM(C65)+SUM(F65) -> 0 | J65: =D65+G65 -> 0 | K65: =IF(I65=0,"",J65/I65*100) | M65: =IF(I65=0,"",L65/I65*100)
B66: CHR Koudougou | E66: =IF(C66=0,"",D66/C66*100) | H66: =IF(F66=0,"",G66/F66*100) | I66: =SUM(C66)+SUM(F66) -> 0 | J66: =D66+G66 -> 0 | K66: =IF(I66=0,"",J66/I66*100) | M66: =IF(I66=0,"",L66/I66*100)
B67: DS Koudougou | E67: =IF(C67=0,"",D67/C67*100) | H67: =IF(F67=0,"",G67/F67*100) | I67: =SUM(C67)+SUM(F67) -> 0 | J67: =D67+G67 -> 0 | K67: =IF(I67=0,"",J67/I67*100) | M67: =IF(I67=0,"",L67/I67*100)
B68: DS Léo | E68: =IF(C68=0,"",D68/C68*100) | H68: =IF(F68=0,"",G68/F68*100) | I68: =SUM(C68)+SUM(F68) -> 0 | J68: =D68+G68 -> 0 | K68: =IF(I68=0,"",J68/I68*100) | M68: =IF(I68=0,"",L68/I68*100)
B69: DS Nanoro | E69: =IF(C69=0,"",D69/C69*100) | H69: =IF(F69=0,"",G69/F69*100) | I69: =SUM(C69)+SUM(F69) -> 0 | J69: =D69+G69 -> 0 | K69: =IF(I69=0,"",J69/I69*100) | M69: =IF(I69=0,"",L69/I69*100)
B70: DS Réo | E70: =IF(C70=0,"",D70/C70*100) | H70: =IF(F70=0,"",G70/F70*100) | I70: =SUM(C70)+SUM(F70) -> 0 | J70: =D70+G70 -> 0 | K70: =IF(I70=0,"",J70/I70*100) | M70: =IF(I70=0,"",L70/I70*100)
B71: DS Sabou | E71: =IF(C71=0,"",D71/C71*100) | H71: =IF(F71=0,"",G71/F71*100) | I71: =SUM(C71)+SUM(F71) -> 0 | J71: =D71+G71 -> 0 | K71: =IF(I71=0,"",J71/I71*100) | M71: =IF(I71=0,"",L71/I71*100)
B72: DS Sapouy | E72: =IF(C72=0,"",D72/C72*100) | H72: =IF(F72=0,"",G72/F72*100) | I72: =SUM(C72)+SUM(F72) -> 0 | J72: =D72+G72 -> 0 | K72: =IF(I72=0,"",J72/I72*100) | M72: =IF(I72=0,"",L72/I72*100)
B73: DS Tenado | E73: =IF(C73=0,"",D73/C73*100) | H73: =IF(F73=0,"",G73/F73*100) | I73: =SUM(C73)+SUM(F73) -> 0 | J73: =D73+G73 -> 0 | K73: =IF(I73=0,"",J73/I73*100) | M73: =IF(I73=0,"",L73/I73*100)
A74: Nazinon | E74: =IF(C74=0,"",D74/C74*100) | H74: =IF(F74=0,"",G74/F74*100) | I74: =SUM(C74)+SUM(F74) -> 0 | J74: =D74+G74 -> 0 | K74: =IF(I74=0,"",J74/I74*100) | M74: =IF(I74=0,"",L74/I74*100)
B75: CHR Manga | E75: =IF(C75=0,"",D75/C75*100) | H75: =IF(F75=0,"",G75/F75*100) | I75: =SUM(C75)+SUM(F75) -> 0 | J75: =D75+G75 -> 0 | K75: =IF(I75=0,"",J75/I75*100) | M75: =IF(I75=0,"",L75/I75*100)
B76: DS Kombissiri | E76: =IF(C76=0,"",D76/C76*100) | H76: =IF(F76=0,"",G76/F76*100) | I76: =SUM(C76)+SUM(F76) -> 0 | J76: =D76+G76 -> 0 | K76: =IF(I76=0,"",J76/I76*100) | M76: =IF(I76=0,"",L76/I76*100)
B77: DS Manga | E77: =IF(C77=0,"",D77/C77*100) | H77: =IF(F77=0,"",G77/F77*100) | I77: =SUM(C77)+SUM(F77) -> 0 | J77: =D77+G77 -> 0 | K77: =IF(I77=0,"",J77/I77*100) | M77: =IF(I77=0,"",L77/I77*100)
B78: DS Po | E78: =IF(C78=0,"",D78/C78*100) | H78: =IF(F78=0,"",G78/F78*100) | I78: =SUM(C78)+SUM(F78) -> 0 | J78: =D78+G78 -> 0 | K78: =IF(I78=0,"",J78/I78*100) | M78: =IF(I78=0,"",L78/I78*100)
B79: DS Sapone | E79: =IF(C79=0,"",D79/C79*100) | H79: =IF(F79=0,"",G79/F79*100) | I79: =SUM(C79)+SUM(F79) -> 0 | J79: =D79+G79 -> 0 | K79: =IF(I79=0,"",J79/I79*100) | M79: =IF(I79=0,"",L79/I79*100)
A80: Oubri | E80: =IF(C80=0,"",D80/C80*100) | H80: =IF(F80=0,"",G80/F80*100) | I80: =SUM(C80)+SUM(F80) -> 0 | J80: =D80+G80 -> 0 | K80: =IF(I80=0,"",J80/I80*100) | M80: =IF(I80=0,"",L80/I80*100)
B81: CHR Ziniaré | E81: =IF(C81=0,"",D81/C81*100) | H81: =IF(F81=0,"",G81/F81*100) | I81: =SUM(C81)+SUM(F81) -> 0 | J81: =D81+G81 -> 0 | K81: =IF(I81=0,"",J81/I81*100) | M81: =IF(I81=0,"",L81/I81*100)
B82: DS Boussé | E82: =IF(C82=0,"",D82/C82*100) | H82: =IF(F82=0,"",G82/F82*100) | I82: =SUM(C82)+SUM(F82) -> 0 | J82: =D82+G82 -> 0 | K82: =IF(I82=0,"",J82/I82*100) | M82: =IF(I82=0,"",L82/I82*100)
B83: DS Ziniaré | E83: =IF(C83=0,"",D83/C83*100) | H83: =IF(F83=0,"",G83/F83*100) | I83: =SUM(C83)+SUM(F83) -> 0 | J83: =D83+G83 -> 0 | K83: =IF(I83=0,"",J83/I83*100) | M83: =IF(I83=0,"",L83/I83*100)
B84: DS Zorgho | E84: =IF(C84=0,"",D84/C84*100) | H84: =IF(F84=0,"",G84/F84*100) | I84: =SUM(C84)+SUM(F84) -> 0 | J84: =D84+G84 -> 0 | K84: =IF(I84=0,"",J84/I84*100) | M84: =IF(I84=0,"",L84/I84*100)
A85: Sirba | E85: =IF(C85=0,"",D85/C85*100) | H85: =IF(F85=0,"",G85/F85*100) | I85: =SUM(C85)+SUM(F85) -> 0 | J85: =D85+G85 -> 0 | K85: =IF(I85=0,"",J85/I85*100) | M85: =IF(I85=0,"",L85/I85*100)
B86: DS Bogande | E86: =IF(C86=0,"",D86/C86*100) | H86: =IF(F86=0,"",G86/F86*100) | I86: =SUM(C86)+SUM(F86) -> 0 | J86: =D86+G86 -> 0 | K86: =IF(I86=0,"",J86/I86*100) | M86: =IF(I86=0,"",L86/I86*100)
B87: DS Gayeri | E87: =IF(C87=0,"",D87/C87*100) | H87: =IF(F87=0,"",G87/F87*100) | I87: =SUM(C87)+SUM(F87) -> 0 | J87: =D87+G87 -> 0 | K87: =IF(I87=0,"",J87/I87*100) | M87: =IF(I87=0,"",L87/I87*100)
B88: DS Manni | E88: =IF(C88=0,"",D88/C88*100) | H88: =IF(F88=0,"",G88/F88*100) | I88: =SUM(C88)+SUM(F88) -> 0 | J88: =D88+G88 -> 0 | K88: =IF(I88=0,"",J88/I88*100) | M88: =IF(I88=0,"",L88/I88*100)
A89: Soum | E89: =IF(C89=0,"",D89/C89*100) | H89: =IF(F89=0,"",G89/F89*100) | I89: =SUM(C89)+SUM(F89) -> 0 | J89: =D89+G89 -> 0 | K89: =IF(I89=0,"",J89/I89*100) | M89: =IF(I89=0,"",L89/I89*100)
B90: DS Djibo | E90: =IF(C90=0,"",D90/C90*100) | H90: =IF(F90=0,"",G90/F90*100) | I90: =SUM(C90)+SUM(F90) -> 0 | J90: =D90+G90 -> 0 | K90: =IF(I90=0,"",J90/I90*100) | M90: =IF(I90=0,"",L90/I90*100)
A91: Sourou | E91: =IF(C91=0,"",D91/C91*100) | H91: =IF(F91=0,"",G91/F91*100) | I91: =SUM(C91)+SUM(F91) -> 0 | J91: =D91+G91 -> 0 | K91: =IF(I91=0,"",J91/I91*100) | M91: =IF(I91=0,"",L91/I91*100)
B92: DS Nouna | E92: =IF(C92=0,"",D92/C92*100) | H92: =IF(F92=0,"",G92/F92*100) | I92: =SUM(C92)+SUM(F92) -> 0 | J92: =D92+G92 -> 0 | K92: =IF(I92=0,"",J92/I92*100) | M92: =IF(I92=0,"",L92/I92*100)
B93: DS Toma | E93: =IF(C93=0,"",D93/C93*100) | H93: =IF(F93=0,"",G93/F93*100) | I93: =SUM(C93)+SUM(F93) -> 0 | J93: =D93+G93 -> 0 | K93: =IF(I93=0,"",J93/I93*100) | M93: =IF(I93=0,"",L93/I93*100)
B94: DS Tougan | E94: =IF(C94=0,"",D94/C94*100) | H94: =IF(F94=0,"",G94/F94*100) | I94: =SUM(C94)+SUM(F94) -> 0 | J94: =D94+G94 -> 0 | K94: =IF(I94=0,"",J94/I94*100) | M94: =IF(I94=0,"",L94/I94*100)
A95: Tannounyan | E95: =IF(C95=0,"",D95/C95*100) | H95: =IF(F95=0,"",G95/F95*100) | I95: =SUM(C95)+SUM(F95) -> 0 | J95: =D95+G95 -> 0 | K95: =IF(I95=0,"",J95/I95*100) | M95: =IF(I95=0,"",L95/I95*100)
B96: CHR Banfora | E96: =IF(C96=0,"",D96/C96*100) | H96: =IF(F96=0,"",G96/F96*100) | I96: =SUM(C96)+SUM(F96) -> 0 | J96: =D96+G96 -> 0 | K96: =IF(I96=0,"",J96/I96*100) | M96: =IF(I96=0,"",L96/I96*100)
B97: DS Banfora | E97: =IF(C97=0,"",D97/C97*100) | H97: =IF(F97=0,"",G97/F97*100) | I97: =SUM(C97)+SUM(F97) -> 0 | J97: =D97+G97 -> 0 | K97: =IF(I97=0,"",J97/I97*100) | M97: =IF(I97=0,"",L97/I97*100)
B98: DS Mangodara | E98: =IF(C98=0,"",D98/C98*100) | H98: =IF(F98=0,"",G98/F98*100) | I98: =SUM(C98)+SUM(F98) -> 0 | J98: =D98+G98 -> 0 | K98: =IF(I98=0,"",J98/I98*100) | M98: =IF(I98=0,"",L98/I98*100)
B99: DS Sindou | E99: =IF(C99=0,"",D99/C99*100) | H99: =IF(F99=0,"",G99/F99*100) | I99: =SUM(C99)+SUM(F99) -> 0 | J99: =D99+G99 -> 0 | K99: =IF(I99=0,"",J99/I99*100) | M99: =IF(I99=0,"",L99/I99*100)
A100: Tapoa | E100: =IF(C100=0,"",D100/C100*100) | H100: =IF(F100=0,"",G100/F100*100) | I100: =SUM(C100)+SUM(F100) -> 0 | J100: =D100+G100 -> 0 | K100: =IF(I100=0,"",J100/I100*100) | M100: =IF(I100=0,"",L100/I100*100)
...

Sheet Sécurité précaire_Publique
A1: Tableau 1.09: Rapports non transmis pour raison d'insécurité par mois des FS publiques en 2025
A2: Régions/Districts | C2: Janv | D2: Févr | E2: Mars | F2: Avr | G2: Mai | H2: Juin | I2: Juil | J2: Août | K2: Sept | L2: Oct | M2: Nov | N2: Déc | O2: Total RMA
A3: Bankui | C3: =SUM(C4:C7) -> 23 | D3: =SUM(D4:D7) -> 23 | E3: =SUM(E4:E7) -> 23 | F3: =SUM(F4:F7) -> 23 | G3: =SUM(G4:G7) -> 22 | H3: =SUM(H4:H7) -> 21 | I3: =SUM(I4:I7) -> 19 | J3: =SUM(J4:J7) -> 18 | ... N3: =SUM(N4:N7) -> 16 | O3: =SUM(C3:N3) -> 236
B4: CHR Dédougou | C4: 0 | D4: 0 | E4: 0 | F4: 0 | G4: 0 | H4: 0 | I4: 0 | J4: 0 | K4: 0 | L4: 0 | M4: 0 | N4: 0 | O4: =SUM(C4:N4) -> 0
B5: DS Boromo | C5: 0 | D5: 0 | E5: 0 | F5: 0 | G5: 0 | H5: 0 | I5: 0 | J5: 0 | K5: 0 | L5: 0 | M5: 0 | N5: 0 | O5: =SUM(C5:N5) -> 0
B6: DS Dedougou | C6: 6 | D6: 6 | E6: 6 | F6: 6 | G6: 6 | H6: 6 | I6: 6 | J6: 6 | K6: 6 | L6: 5 | M6: 5 | N6: 5 | O6: =SUM(C6:N6) -> 69
B7: DS Solenzo | C7: 17 | D7: 17 | E7: 17 | F7: 17 | G7: 16 | H7: 15 | I7: 13 | J7: 12 | K7: 11 | L7: 11 | M7: 10 | N7: 11 | O7: =SUM(C7:N7) -> 167
A8: Djoro | C8: =SUM(C9:C14) -> 1 | D8: =SUM(D9:D14) -> 1 | E8: =SUM(E9:E14) -> 1 | F8: =SUM(F9:F14) -> 1 | G8: =SUM(G9:G14) -> 1 | H8: =SUM(H9:H14) -> 1 | I8: =SUM(I9:I14) -> 1 | J8: =SUM(J9:J14) -> 1 | ... N8: =SUM(N9:N14) -> 1 | O8: =SUM(C8:N8) -> 12
B9: CHR Gaoua | C9: 0 | D9: 0 | E9: 0 | F9: 0 | G9: 0 | H9: 0 | I9: 0 | J9: 0 | K9: 0 | L9: 0 | M9: 0 | N9: 0 | O9: =SUM(C9:N9) -> 0
B10: DS Batié | C10: 0 | D10: 0 | E10: 0 | F10: 0 | G10: 0 | H10: 0 | I10: 0 | J10: 0 | K10: 0 | L10: 0 | M10: 0 | N10: 0 | O10: =SUM(C10:N10) -> 0
B11: DS Dano | C11: 0 | D11: 0 | E11: 0 | F11: 0 | G11: 0 | H11: 0 | I11: 0 | J11: 0 | K11: 0 | L11: 0 | M11: 0 | N11: 0 | O11: =SUM(C11:N11) -> 0
B12: DS Diébougou | C12: 0 | D12: 0 | E12: 0 | F12: 0 | G12: 0 | H12: 0 | I12: 0 | J12: 0 | K12: 0 | L12: 0 | M12: 0 | N12: 0 | O12: =SUM(C12:N12) -> 0
B13: DS Gaoua | C13: 0 | D13: 0 | E13: 0 | F13: 0 | G13: 0 | H13: 0 | I13: 0 | J13: 0 | K13: 0 | L13: 0 | M13: 0 | N13: 0 | O13: =SUM(C13:N13) -> 0
B14: DS Kampti | C14: 1 | D14: 1 | E14: 1 | F14: 1 | G14: 1 | H14: 1 | I14: 1 | J14: 1 | K14: 1 | L14: 1 | M14: 1 | N14: 1 | O14: =SUM(C14:N14) -> 12
A15: Goulmou | C15: =SUM(C16:C18) -> 26 | D15: =SUM(D16:D18) -> 29 | E15: =SUM(E16:E18) -> 30 | F15: =SUM(F16:F18) -> 29 | G15: =SUM(G16:G18) -> 31 | H15: =SUM(H16:H18) -> 31 | I15: =SUM(I16:I18) -> 33 | J15: =SUM(J16:J18) -> 39 | ... N15: =SUM(N16:N18) -> 42 | O15: =SUM(C15:N15) -> 415
B16: CHR Fada N'Gourma | C16: 0 | D16: 0 | E16: 0 | F16: 0 | G16: 0 | H16: 0 | I16: 0 | J16: 0 | K16: 0 | L16: 0 | M16: 0 | N16: 0 | O16: =SUM(C16:N16) -> 0
B17: DS Fada | C17: 17 | D17: 20 | E17: 21 | F17: 20 | G17: 22 | H17: 22 | I17: 24 | J17: 30 | K17: 32 | L17: 33 | M17: 33 | N17: 33 | O17: =SUM(C17:N17) -> 307
B18: DS Pama | C18: 9 | D18: 9 | E18: 9 | F18: 9 | G18: 9 | H18: 9 | I18: 9 | J18: 9 | K18: 9 | L18: 9 | M18: 9 | N18: 9 | O18: =SUM(C18:N18) -> 108
A19: Guiriko | C19: =SUM(C20:C28) -> 9 | D19: =SUM(D20:D28) -> 9 | E19: =SUM(E20:E28) -> 9 | F19: =SUM(F20:F28) -> 9 | G19: =SUM(G20:G28) -> 9 | H19: =SUM(H20:H28) -> 9 | I19: =SUM(I20:I28) -> 7 | J19: =SUM(J20:J28) -> 7 | ... N19: =SUM(N20:N28) -> 7 | O19: =SUM(C19:N19) -> 96
B20: CHU Sanou Souro | C20: 0 | D20: 0 | E20: 0 | F20: 0 | G20: 0 | H20: 0 | I20: 0 | J20: 0 | K20: 0 | L20: 0 | M20: 0 | N20: 0 | O20: =SUM(C20:N20) -> 0
B21: DS Dafra | C21: 0 | D21: 0 | E21: 0 | F21: 0 | G21: 0 | H21: 0 | I21: 0 | J21: 0 | K21: 0 | L21: 0 | M21: 0 | N21: 0 | O21: =SUM(C21:N21) -> 0
B22: DS Dande | C22: 2 | D22: 2 | E22: 2 | F22: 2 | G22: 2 | H22: 2 | I22: 1 | J22: 1 | K22: 1 | L22: 1 | M22: 1 | N22: 1 | O22: =SUM(C22:N22) -> 18
B23: DS Do | C23: 0 | D23: 0 | E23: 0 | F23: 0 | G23: 0 | H23: 0 | I23: 0 | J23: 0 | K23: 0 | L23: 0 | M23: 0 | N23: 0 | O23: =SUM(C23:N23) -> 0
B24: DS Hounde | C24: 1 | D24: 1 | E24: 1 | F24: 1 | G24: 1 | H24: 1 | I24: 1 | J24: 1 | K24: 1 | L24: 1 | M24: 1 | N24: 1 | O24: =SUM(C24:N24) -> 12
B25: DS Karangasso Vigue | C25: 0 | D25: 0 | E25: 0 | F25: 0 | G25: 0 | H25: 0 | I25: 0 | J25: 0 | K25: 0 | L25: 0 | M25: 0 | N25: 0 | O25: =SUM(C25:N25) -> 0
B26: DS Léna | C26: 0 | D26: 0 | E26: 0 | F26: 0 | G26: 0 | H26: 0 | I26: 0 | J26: 0 | K26: 0 | L26: 0 | M26: 0 | N26: 0 | O26: =SUM(C26:N26) -> 0
B27: DS N'Dorola | C27: 3 | D27: 3 | E27: 3 | F27: 3 | G27: 3 | H27: 3 | I27: 3 | J27: 3 | K27: 3 | L27: 3 | M27: 3 | N27: 3 | O27: =SUM(C27:N27) -> 36
B28: DS Orodara | C28: 3 | D28: 3 | E28: 3 | F28: 3 | G28: 3 | H28: 3 | I28: 2 | J28: 2 | K28: 2 | L28: 2 | M28: 2 | N28: 2 | O28: =SUM(C28:N28) -> 30
A29: Kadiogo | C29: =SUM(C30:C41) -> 0 | D29: =SUM(D30:D41) -> 0 | E29: =SUM(E30:E41) -> 0 | F29: =SUM(F30:F41) -> 0 | G29: =SUM(G30:G41) -> 0 | H29: =SUM(H30:H41) -> 0 | I29: =SUM(I30:I41) -> 0 | J29: =SUM(J30:J41) -> 0 | ... N29: =SUM(N30:N41) -> 0 | O29: =SUM(C29:N29) -> 0
B30: CHU Bogodogo | C30: 0 | D30: 0 | E30: 0 | F30: 0 | G30: 0 | H30: 0 | I30: 0 | J30: 0 | K30: 0 | L30: 0 | M30: 0 | N30: 0 | O30: =SUM(C30:N30) -> 0
B31: CHU Pédiatrique CDG | C31: 0 | D31: 0 | E31: 0 | F31: 0 | G31: 0 | H31: 0 | I31: 0 | J31: 0 | K31: 0 | L31: 0 | M31: 0 | N31: 0 | O31: =SUM(C31:N31) -> 0
B32: CHU Tengandogo | C32: 0 | D32: 0 | E32: 0 | F32: 0 | G32: 0 | H32: 0 | I32: 0 | J32: 0 | K32: 0 | L32: 0 | M32: 0 | N32: 0 | O32: =SUM(C32:N32) -> 0
B33: CHU Yalgado | C33: 0 | D33: 0 | E33: 0 | F33: 0 | G33: 0 | H33: 0 | I33: 0 | J33: 0 | K33: 0 | L33: 0 | M33: 0 | N33: 0 | O33: =SUM(C33:N33) -> 0
B34: Hôpital Paul VI | O34: =SUM(C34:N34) -> 0
B35: Hôpital Saint Camille | O35: =SUM(C35:N35) -> 0
B36: Hôpital SCHIPHRA | O36: =SUM(C36:N36) -> 0
B37: DS Baskuy | C37: 0 | D37: 0 | E37: 0 | F37: 0 | G37: 0 | H37: 0 | I37: 0 | J37: 0 | K37: 0 | L37: 0 | M37: 0 | N37: 0 | O37: =SUM(C37:N37) -> 0
B38: DS Bogodogo | C38: 0 | D38: 0 | E38: 0 | F38: 0 | G38: 0 | H38: 0 | I38: 0 | J38: 0 | K38: 0 | L38: 0 | M38: 0 | N38: 0 | O38: =SUM(C38:N38) -> 0
B39: DS Boulmiougou | C39: 0 | D39: 0 | E39: 0 | F39: 0 | G39: 0 | H39: 0 | I39: 0 | J39: 0 | K39: 0 | L39: 0 | M39: 0 | N39: 0 | O39: =SUM(C39:N39) -> 0
B40: DS Nongr-Massom | C40: 0 | D40: 0 | E40: 0 | F40: 0 | G40: 0 | H40: 0 | I40: 0 | J40: 0 | K40: 0 | L40: 0 | M40: 0 | N40: 0 | O40: =SUM(C40:N40) -> 0
B41: DS Sig-Noghin | C41: 0 | D41: 0 | E41: 0 | F41: 0 | G41: 0 | H41: 0 | I41: 0 | J41: 0 | K41: 0 | L41: 0 | M41: 0 | N41: 0 | O41: =SUM(C41:N41) -> 0
A42: Koulsé | C42: =SUM(C43:C49) -> 77 | D42: =SUM(D43:D49) -> 77 | E42: =SUM(E43:E49) -> 76 | F42: =SUM(F43:F49) -> 78 | G42: =SUM(G43:G49) -> 78 | H42: =SUM(H43:H49) -> 80 | I42: =SUM(I43:I49) -> 81 | J42: =SUM(J43:J49) -> 81 | ... N42: =SUM(N43:N49) -> 80 | O42: =SUM(C42:N42) -> 950
B43: CHR Kaya | C43: 0 | D43: 0 | E43: 0 | F43: 0 | G43: 0 | H43: 0 | I43: 0 | J43: 0 | K43: 0 | L43: 0 | M43: 0 | N43: 0 | O43: =SUM(C43:N43) -> 0
B44: DS Barsalogho | C44: 12 | D44: 12 | E44: 10 | F44: 10 | G44: 10 | H44: 10 | I44: 10 | J44: 10 | K44: 10 | L44: 10 | M44: 10 | N44: 10 | O44: =SUM(C44:N44) -> 124
B45: DS Boulsa | C45: 8 | D45: 8 | E45: 8 | F45: 8 | G45: 8 | H45: 8 | I45: 8 | J45: 8 | K45: 8 | L45: 8 | M45: 8 | N45: 8 | O45: =SUM(C45:N45) -> 96
B46: DS Boussouma | C46: 0 | D46: 0 | E46: 0 | F46: 0 | G46: 0 | H46: 1 | I46: 1 | J46: 1 | K46: 1 | L46: 1 | M46: 0 | N46: 0 | O46: =SUM(C46:N46) -> 5
B47: DS Kaya | C47: 11 | D47: 11 | E47: 12 | F47: 12 | G47: 12 | H47: 12 | I47: 13 | J47: 13 | K47: 13 | L47: 13 | M47: 13 | N47: 13 | O47: =SUM(C47:N47) -> 148
B48: DS Kongoussi | C48: 28 | D48: 28 | E48: 28 | F48: 28 | G48: 28 | H48: 28 | I48: 28 | J48: 28 | K48: 28 | L48: 28 | M48: 28 | N48: 28 | O48: =SUM(C48:N48) -> 336
B49: DS Tougouri | C49: 18 | D49: 18 | E49: 18 | F49: 20 | G49: 20 | H49: 21 | I49: 21 | J49: 21 | K49: 21 | L49: 21 | M49: 21 | N49: 21 | O49: =SUM(C49:N49) -> 241
A50: Liptako | C50: =SUM(C51:C54) -> 51 | D50: =SUM(D51:D54) -> 52 | E50: =SUM(E51:E54) -> 52 | F50: =SUM(F51:F54) -> 53 | G50: =SUM(G51:G54) -> 55 | H50: =SUM(H51:H54) -> 53 | I50: =SUM(I51:I54) -> 54 | J50: =SUM(J51:J54) -> 54 | ... N50: =SUM(N51:N54) -> 61 | O50: =SUM(C50:N50) -> 656
B51: CHR Dori | C51: 0 | D51: 0 | E51: 0 | F51: 0 | G51: 0 | H51: 0 | I51: 0 | J51: 0 | K51: 0 | L51: 0 | M51: 0 | N51: 0 | O51: =SUM(C51:N51) -> 0
B52: DS Dori | C52: 20 | D52: 21 | E52: 21 | F52: 22 | G52: 24 | H52: 22 | I52: 24 | J52: 24 | K52: 24 | L52: 26 | M52: 24 | N52: 24 | O52: =SUM(C52:N52) -> 276
B53: DS Gorom-Gorom | C53: 17 | D53: 17 | E53: 17 | F53: 17 | G53: 17 | H53: 17 | I53: 16 | J53: 16 | K53: 16 | L53: 16 | M53: 16 | N53: 18 | O53: =SUM(C53:N53) -> 200
B54: DS Sebba | C54: 14 | D54: 14 | E54: 14 | F54: 14 | G54: 14 | H54: 14 | I54: 14 | J54: 14 | K54: 15 | L54: 15 | M54: 19 | N54: 19 | O54: =SUM(C54:N54) -> 180
A55: Nakambé | C55: =SUM(C56:C63) -> 18 | D55: =SUM(D56:D63) -> 20 | E55: =SUM(E56:E63) -> 21 | F55: =SUM(F56:F63) -> 24 | G55: =SUM(G56:G63) -> 27 | H55: =SUM(H56:H63) -> 28 | I55: =SUM(I56:I63) -> 26 | J55: =SUM(J56:J63) -> 27 | ... N55: =SUM(N56:N63) -> 26 | O55: =SUM(C55:N55) -> 297
B56: CHR Tenkodogo | C56: 0 | D56: 0 | E56: 0 | F56: 0 | G56: 0 | H56: 0 | I56: 0 | J56: 0 | K56: 0 | L56: 0 | M56: 0 | N56: 0 | O56: =SUM(C56:N56) -> 0
B57: DS Bittou | C57: 3 | D57: 3 | E57: 3 | F57: 3 | G57: 3 | H57: 3 | I57: 3 | J57: 3 | K57: 3 | L57: 3 | M57: 3 | N57: 3 | O57: =SUM(C57:N57) -> 36
B58: DS Garango | C58: 0 | D58: 0 | E58: 0 | F58: 0 | G58: 0 | H58: 0 | I58: 0 | J58: 0 | K58: 0 | L58: 0 | M58: 0 | N58: 0 | O58: =SUM(C58:N58) -> 0
B59: DS Koupéla | C59: 0 | D59: 0 | E59: 0 | F59: 0 | G59: 0 | H59: 0 | I59: 0 | J59: 0 | K59: 0 | L59: 0 | M59: 0 | N59: 0 | O59: =SUM(C59:N59) -> 0
B60: DS Ouargaye | C60: 15 | D60: 17 | E60: 18 | F60: 21 | G60: 22 | H60: 22 | I60: 21 | J60: 22 | K60: 22 | L60: 22 | M60: 21 | N60: 21 | O60: =SUM(C60:N60) -> 244
B61: DS Pouytenga | C61: 0 | D61: 0 | E61: 0 | F61: 0 | G61: 0 | H61: 0 | I61: 0 | J61: 0 | K61: 0 | L61: 0 | M61: 0 | N61: 0 | O61: =SUM(C61:N61) -> 0
B62: DS Tenkodogo | C62: 0 | D62: 0 | E62: 0 | F62: 0 | G62: 2 | H62: 3 | I62: 2 | J62: 2 | K62: 2 | L62: 2 | M62: 2 | N62: 2 | O62: =SUM(C62:N62) -> 17
B63: DS Zabré | C63: 0 | D63: 0 | E63: 0 | F63: 0 | G63: 0 | H63: 0 | I63: 0 | J63: 0 | K63: 0 | L63: 0 | M63: 0 | N63: 0 | O63: =SUM(C63:N63) -> 0
A64: Nando | C64: =SUM(C65:C72) -> 0 | D64: =SUM(D65:D72) -> 0 | E64: =SUM(E65:E72) -> 0 | F64: =SUM(F65:F72) -> 0 | G64: =SUM(G65:G72) -> 0 | H64: =SUM(H65:H72) -> 0 | I64: =SUM(I65:I72) -> 0 | J64: =SUM(J65:J72) -> 0 | ... N64: =SUM(N65:N72) -> 0 | O64: =SUM(C64:N64) -> 0
B65: CHR Koudougou | C65: 0 | D65: 0 | E65: 0 | F65: 0 | G65: 0 | H65: 0 | I65: 0 | J65: 0 | K65: 0 | L65: 0 | M65: 0 | N65: 0 | O65: =SUM(C65:N65) -> 0
B66: DS Koudougou | C66: 0 | D66: 0 | E66: 0 | F66: 0 | G66: 0 | H66: 0 | I66: 0 | J66: 0 | K66: 0 | L66: 0 | M66: 0 | N66: 0 | O66: =SUM(C66:N66) -> 0
B67: DS Léo | C67: 0 | D67: 0 | E67: 0 | F67: 0 | G67: 0 | H67: 0 | I67: 0 | J67: 0 | K67: 0 | L67: 0 | M67: 0 | N67: 0 | O67: =SUM(C67:N67) -> 0
B68: DS Nanoro | C68: 0 | D68: 0 | E68: 0 | F68: 0 | G68: 0 | H68: 0 | I68: 0 | J68: 0 | K68: 0 | L68: 0 | M68: 0 | N68: 0 | O68: =SUM(C68:N68) -> 0
B69: DS Réo | C69: 0 | D69: 0 | E69: 0 | F69: 0 | G69: 0 | H69: 0 | I69: 0 | J69: 0 | K69: 0 | L69: 0 | M69: 0 | N69: 0 | O69: =SUM(C69:N69) -> 0
B70: DS Sabou | C70: 0 | D70: 0 | E70: 0 | F70: 0 | G70: 0 | H70: 0 | I70: 0 | J70: 0 | K70: 0 | L70: 0 | M70: 0 | N70: 0 | O70: =SUM(C70:N70) -> 0
B71: DS Sapouy | C71: 0 | D71: 0 | E71: 0 | F71: 0 | G71: 0 | H71: 0 | I71: 0 | J71: 0 | K71: 0 | L71: 0 | M71: 0 | N71: 0 | O71: =SUM(C71:N71) -> 0
B72: DS Tenado | C72: 0 | D72: 0 | E72: 0 | F72: 0 | G72: 0 | H72: 0 | I72: 0 | J72: 0 | K72: 0 | L72: 0 | M72: 0 | N72: 0 | O72: =SUM(C72:N72) -> 0
A73: Nazinon | C73: =SUM(C74:C78) -> 0 | D73: =SUM(D74:D78) -> 0 | E73: =SUM(E74:E78) -> 0 | F73: =SUM(F74:F78) -> 0 | G73: =SUM(G74:G78) -> 0 | H73: =SUM(H74:H78) -> 0 | I73: =SUM(I74:I78) -> 0 | J73: =SUM(J74:J78) -> 0 | ... N73: =SUM(N74:N78) -> 0 | O73: =SUM(C73:N73) -> 0
B74: CHR Manga | C74: 0 | D74: 0 | E74: 0 | F74: 0 | G74: 0 | H74: 0 | I74: 0 | J74: 0 | K74: 0 | L74: 0 | M74: 0 | N74: 0 | O74: =SUM(C74:N74) -> 0
B75: DS Kombissiri | C75: 0 | D75: 0 | E75: 0 | F75: 0 | G75: 0 | H75: 0 | I75: 0 | J75: 0 | K75: 0 | L75: 0 | M75: 0 | N75: 0 | O75: =SUM(C75:N75) -> 0
B76: DS Manga | C76: 0 | D76: 0 | E76: 0 | F76: 0 | G76: 0 | H76: 0 | I76: 0 | J76: 0 | K76: 0 | L76: 0 | M76: 0 | N76: 0 | O76: =SUM(C76:N76) -> 0
B77: DS Po | C77: 0 | D77: 0 | E77: 0 | F77: 0 | G77: 0 | H77: 0 | I77: 0 | J77: 0 | K77: 0 | L77: 0 | M77: 0 | N77: 0 | O77: =SUM(C77:N77) -> 0
B78: DS Sapone | C78: 0 | D78: 0 | E78: 0 | F78: 0 | G78: 0 | H78: 0 | I78: 0 | J78: 0 | K78: 0 | L78: 0 | M78: 0 | N78: 0 | O78: =SUM(C78:N78) -> 0
A79: Oubri | C79: =SUM(C80:C83) -> 0 | D79: =SUM(D80:D83) -> 0 | E79: =SUM(E80:E83) -> 0 | F79: =SUM(F80:F83) -> 0 | G79: =SUM(G80:G83) -> 0 | H79: =SUM(H80:H83) -> 0 | I79: =SUM(I80:I83) -> 0 | J79: =SUM(J80:J83) -> 0 | ... N79: =SUM(N80:N83) -> 0 | O79: =SUM(C79:N79) -> 0
B80: CHR Ziniaré | C80: 0 | D80: 0 | E80: 0 | F80: 0 | G80: 0 | H80: 0 | I80: 0 | J80: 0 | K80: 0 | L80: 0 | M80: 0 | N80: 0 | O80: =SUM(C80:N80) -> 0
B81: DS Boussé | C81: 0 | D81: 0 | E81: 0 | F81: 0 | G81: 0 | H81: 0 | I81: 0 | J81: 0 | K81: 0 | L81: 0 | M81: 0 | N81: 0 | O81: =SUM(C81:N81) -> 0
B82: DS Ziniaré | C82: 0 | D82: 0 | E82: 0 | F82: 0 | G82: 0 | H82: 0 | I82: 0 | J82: 0 | K82: 0 | L82: 0 | M82: 0 | N82: 0 | O82: =SUM(C82:N82) -> 0
B83: DS Zorgho | C83: 0 | D83: 0 | E83: 0 | F83: 0 | G83: 0 | H83: 0 | I83: 0 | J83: 0 | K83: 0 | L83: 0 | M83: 0 | N83: 0 | O83: =SUM(C83:N83) -> 0
A84: Sirba | C84: =SUM(C85:C87) -> 36 | D84: =SUM(D85:D87) -> 31 | E84: =SUM(E85:E87) -> 28 | F84: =SUM(F85:F87) -> 28 | G84: =SUM(G85:G87) -> 25 | H84: =SUM(H85:H87) -> 25 | I84: =SUM(I85:I87) -> 24 | J84: =SUM(J85:J87) -> 25 | ... N84: =SUM(N85:N87) -> 25 | O84: =SUM(C84:N84) -> 331
B85: DS Bogande | C85: 9 | D85: 9 | E85: 9 | F85: 9 | G85: 9 | H85: 9 | I85: 8 | J85: 8 | K85: 8 | L85: 8 | M85: 8 | N85: 8 | O85: =SUM(C85:N85) -> 102
B86: DS Gayeri | C86: 11 | D86: 6 | E86: 4 | F86: 5 | G86: 3 | H86: 3 | I86: 3 | J86: 4 | K86: 11 | L86: 11 | M86: 11 | N86: 11 | O86: =SUM(C86:N86) -> 83
B87: DS Manni | C87: 16 | D87: 16 | E87: 15 | F87: 14 | G87: 13 | H87: 13 | I87: 13 | J87: 13 | K87: 12 | L87: 9 | M87: 6 | N87: 6 | O87: =SUM(C87:N87) -> 146
A88: Soum | C88: =C89 -> 36 | D88: =D89 -> 36 | E88: =E89 -> 36 | F88: =F89 -> 36 | G88: =G89 -> 36 | H88: =H89 -> 36 | I88: =I89 -> 36 | J88: =J89 -> 36 | ... N88: =N89 -> 36 | O88: =SUM(C88:N88) -> 432
B89: DS Djibo | C89: 36 | D89: 36 | E89: 36 | F89: 36 | G89: 36 | H89: 36 | I89: 36 | J89: 36 | K89: 36 | L89: 36 | M89: 36 | N89: 36 | O89: =SUM(C89:N89) -> 432
A90: Sourou | C90: =SUM(C91:C93) -> 50 | D90: =SUM(D91:D93) -> 52 | E90: =SUM(E91:E93) -> 46 | F90: =SUM(F91:F93) -> 57 | G90: =SUM(G91:G93) -> 57 | H90: =SUM(H91:H93) -> 58 | I90: =SUM(I91:I93) -> 58 | J90: =SUM(J91:J93) -> 59 | ... N90: =SUM(N91:N93) -> 66 | O90: =SUM(C90:N90) -> 699
B91: DS Nouna | C91: 19 | D91: 19 | E91: 19 | F91: 19 | G91: 19 | H91: 19 | I91: 19 | J91: 20 | K91: 21 | L91: 21 | M91: 19 | N91: 19 | O91: =SUM(C91:N91) -> 233
B92: DS Toma | C92: 14 | D92: 14 | E92: 10 | F92: 10 | G92: 10 | H92: 11 | I92: 11 | J92: 11 | K92: 11 | L92: 11 | M92: 11 | N92: 11 | O92: =SUM(C92:N92) -> 135
B93: DS Tougan | C93: 17 | D93: 19 | E93: 17 | F93: 28 | G93: 28 | H93: 28 | I93: 28 | J93: 28 | K93: 30 | L93: 37 | M93: 35 | N93: 36 | O93: =SUM(C93:N93) -> 331
A94: Tannounyan | C94: =SUM(C95:C98) -> 1 | D94: =SUM(D95:D98) -> 1 | E94: =SUM(E95:E98) -> 0 | F94: =SUM(F95:F98) -> 0 | G94: =SUM(G95:G98) -> 0 | H94: =SUM(H95:H98) -> 0 | I94: =SUM(I95:I98) -> 0 | J94: =SUM(J95:J98) -> 0 | ... N94: =SUM(N95:N98) -> 0 | O94: =SUM(C94:N94) -> 2
B95: CHR Banfora | C95: 0 | D95: 0 | E95: 0 | F95: 0 | G95: 0 | H95: 0 | I95: 0 | J95: 0 | K95: 0 | L95: 0 | M95: 0 | N95: 0 | O95: =SUM(C95:N95) -> 0
B96: DS Banfora | C96: 0 | D96: 0 | E96: 0 | F96: 0 | G96: 0 | H96: 0 | I96: 0 | J96: 0 | K96: 0 | L96: 0 | M96: 0 | N96: 0 | O96: =SUM(C96:N96) -> 0
B97: DS Mangodara | C97: 1 | D97: 1 | E97: 0 | F97: 0 | G97: 0 | H97: 0 | I97: 0 | J97: 0 | K97: 0 | L97: 0 | M97: 0 | N97: 0 | O97: =SUM(C97:N97) -> 2
B98: DS Sindou | C98: 0 | D98: 0 | E98: 0 | F98: 0 | G98: 0 | H98: 0 | I98: 0 | J98: 0 | K98: 0 | L98: 0 | M98: 0 | N98: 0 | O98: =SUM(C98:N98) -> 0
A99: Tapoa | C99: =SUM(C100) -> 23 | D99: =SUM(D100) -> 12 | E99: =SUM(E100) -> 13 | F99: =SUM(F100) -> 12 | G99: =SUM(G100) -> 14 | H99: =SUM(H100) -> 13 | I99: =SUM(I100) -> 22 | J99: =SUM(J100) -> 40 | ... N99: =SUM(N100) -> 43 | O99: =SUM(C99:N99) -> 321
B100: DS Diapaga | C100: 23 | D100: 12 | E100: 13 | F100: 12 | G100: 14 | H100: 13 | I100: 22 | J100: 40 | K100: 43 | L100: 43 | M100: 43 | N100: 43 | O100: =SUM(C100:N100) -> 321
...

Sheet Sécurité précaire_Privee
A1: Tableau 1.10: Rapports non transmis pour raison d'insécurité par mois des FS privées en 2025
A2: Régions/Districts | C2: Janv | D2: Févr | E2: Mars | F2: Avr | G2: Mai | H2: Juin | I2: Juil | J2: Août | K2: Sept | L2: Oct | M2: Nov | N2: Déc | O2: Total RMA
A3: Bankui | C3: =SUM(C4:C7) -> 0 | D3: =SUM(D4:D7) -> 0 | E3: =SUM(E4:E7) -> 0 | F3: =SUM(F4:F7) -> 0 | G3: =SUM(G4:G7) -> 0 | H3: =SUM(H4:H7) -> 0 | I3: =SUM(I4:I7) -> 0 | J3: =SUM(J4:J7) -> 0 | ... N3: =SUM(N4:N7) -> 0 | O3: =SUM(C3:N3) -> 0
B4: CHR Dédougou | C4: 0 | D4: 0 | E4: 0 | F4: 0 | G4: 0 | H4: 0 | I4: 0 | J4: 0 | K4: 0 | L4: 0 | M4: 0 | N4: 0 | O4: =SUM(C4:N4) -> 0
B5: DS Boromo | C5: 0 | D5: 0 | E5: 0 | F5: 0 | G5: 0 | H5: 0 | I5: 0 | J5: 0 | K5: 0 | L5: 0 | M5: 0 | N5: 0 | O5: =SUM(C5:N5) -> 0
B6: DS Dedougou | C6: 0 | D6: 0 | E6: 0 | F6: 0 | G6: 0 | H6: 0 | I6: 0 | J6: 0 | K6: 0 | L6: 0 | M6: 0 | N6: 0 | O6: =SUM(C6:N6) -> 0
B7: DS Solenzo | C7: 0 | D7: 0 | E7: 0 | F7: 0 | G7: 0 | H7: 0 | I7: 0 | J7: 0 | K7: 0 | L7: 0 | M7: 0 | N7: 0 | O7: =SUM(C7:N7) -> 0
A8: Djoro | C8: 0 | D8: 0 | E8: 0 | F8: 0 | G8: 0 | H8: 0 | I8: 0 | J8: 0 | K8: 0 | L8: 0 | M8: 0 | N8: 0 | O8: =SUM(C8:N8) -> 0
B9: CHR Gaoua | C9: 0 | D9: 0 | E9: 0 | F9: 0 | G9: 0 | H9: 0 | I9: 0 | J9: 0 | K9: 0 | L9: 0 | M9: 0 | N9: 0 | O9: =SUM(C9:N9) -> 0
B10: DS Batié | C10: 0 | D10: 0 | E10: 0 | F10: 0 | G10: 0 | H10: 0 | I10: 0 | J10: 0 | K10: 0 | L10: 0 | M10: 0 | N10: 0 | O10: =SUM(C10:N10) -> 0
B11: DS Dano | C11: 0 | D11: 0 | E11: 0 | F11: 0 | G11: 0 | H11: 0 | I11: 0 | J11: 0 | K11: 0 | L11: 0 | M11: 0 | N11: 0 | O11: =SUM(C11:N11) -> 0
B12: DS Diébougou | C12: 0 | D12: 0 | E12: 0 | F12: 0 | G12: 0 | H12: 0 | I12: 0 | J12: 0 | K12: 0 | L12: 0 | M12: 0 | N12: 0 | O12: =SUM(C12:N12) -> 0
B13: DS Gaoua | C13: 0 | D13: 0 | E13: 0 | F13: 0 | G13: 0 | H13: 0 | I13: 0 | J13: 0 | K13: 0 | L13: 0 | M13: 0 | N13: 0 | O13: =SUM(C13:N13) -> 0
B14: DS Kampti | C14: 0 | D14: 0 | E14: 0 | F14: 0 | G14: 0 | H14: 0 | I14: 0 | J14: 0 | K14: 0 | L14: 0 | M14: 0 | N14: 0 | O14: =SUM(C14:N14) -> 0
A15: Goulmou | C15: =SUM(C16:C18) -> 2 | D15: =SUM(D16:D18) -> 2 | E15: =SUM(E16:E18) -> 2 | F15: =SUM(F16:F18) -> 2 | G15: =SUM(G16:G18) -> 2 | H15: =SUM(H16:H18) -> 2 | I15: =SUM(I16:I18) -> 2 | J15: =SUM(J16:J18) -> 2 | ... N15: =SUM(N16:N18) -> 2 | O15: =SUM(C15:N15) -> 24
B16: CHR Fada N'Gourma | C16: 0 | D16: 0 | E16: 0 | F16: 0 | G16: 0 | H16: 0 | I16: 0 | J16: 0 | K16: 0 | L16: 0 | M16: 0 | N16: 0 | O16: =SUM(C16:N16) -> 0
B17: DS Fada | C17: 1 | D17: 1 | E17: 1 | F17: 1 | G17: 1 | H17: 1 | I17: 1 | J17: 1 | K17: 1 | L17: 1 | M17: 1 | N17: 1 | O17: =SUM(C17:N17) -> 12
B18: DS Pama | C18: 1 | D18: 1 | E18: 1 | F18: 1 | G18: 1 | H18: 1 | I18: 1 | J18: 1 | K18: 1 | L18: 1 | M18: 1 | N18: 1 | O18: =SUM(C18:N18) -> 12
A19: Guiriko | C19: =SUM(C20:C28) -> 0 | D19: =SUM(D20:D28) -> 0 | E19: =SUM(E20:E28) -> 0 | F19: =SUM(F20:F28) -> 0 | G19: =SUM(G20:G28) -> 0 | H19: =SUM(H20:H28) -> 0 | I19: =SUM(I20:I28) -> 0 | J19: =SUM(J20:J28) -> 0 | ... N19: =SUM(N20:N28) -> 0 | O19: =SUM(C19:N19) -> 0
B20: CHU Sanou Souro | C20: 0 | D20: 0 | E20: 0 | F20: 0 | G20: 0 | H20: 0 | I20: 0 | J20: 0 | K20: 0 | L20: 0 | M20: 0 | N20: 0 | O20: =SUM(C20:N20) -> 0
B21: DS Dafra | C21: 0 | D21: 0 | E21: 0 | F21: 0 | G21: 0 | H21: 0 | I21: 0 | J21: 0 | K21: 0 | L21: 0 | M21: 0 | N21: 0 | O21: =SUM(C21:N21) -> 0
B22: DS Dande | C22: 0 | D22: 0 | E22: 0 | F22: 0 | G22: 0 | H22: 0 | I22: 0 | J22: 0 | K22: 0 | L22: 0 | M22: 0 | N22: 0 | O22: =SUM(C22:N22) -> 0
B23: DS Do | C23: 0 | D23: 0 | E23: 0 | F23: 0 | G23: 0 | H23: 0 | I23: 0 | J23: 0 | K23: 0 | L23: 0 | M23: 0 | N23: 0 | O23: =SUM(C23:N23) -> 0
B24: DS Hounde | C24: 0 | D24: 0 | E24: 0 | F24: 0 | G24: 0 | H24: 0 | I24: 0 | J24: 0 | K24: 0 | L24: 0 | M24: 0 | N24: 0 | O24: =SUM(C24:N24) -> 0
B25: DS Karangasso Vigue | C25: 0 | D25: 0 | E25: 0 | F25: 0 | G25: 0 | H25: 0 | I25: 0 | J25: 0 | K25: 0 | L25: 0 | M25: 0 | N25: 0 | O25: =SUM(C25:N25) -> 0
B26: DS Léna | C26: 0 | D26: 0 | E26: 0 | F26: 0 | G26: 0 | H26: 0 | I26: 0 | J26: 0 | K26: 0 | L26: 0 | M26: 0 | N26: 0 | O26: =SUM(C26:N26) -> 0
B27: DS N'Dorola | C27: 0 | D27: 0 | E27: 0 | F27: 0 | G27: 0 | H27: 0 | I27: 0 | J27: 0 | K27: 0 | L27: 0 | M27: 0 | N27: 0 | O27: =SUM(C27:N27) -> 0
B28: DS Orodara | C28: 0 | D28: 0 | E28: 0 | F28: 0 | G28: 0 | H28: 0 | I28: 0 | J28: 0 | K28: 0 | L28: 0 | M28: 0 | N28: 0 | O28: =SUM(C28:N28) -> 0
A29: Kadiogo | C29: =SUM(C30:C41) -> 0 | D29: =SUM(D30:D41) -> 0 | E29: =SUM(E30:E41) -> 0 | F29: =SUM(F30:F41) -> 0 | G29: =SUM(G30:G41) -> 0 | H29: =SUM(H30:H41) -> 0 | I29: =SUM(I30:I41) -> 0 | J29: =SUM(J30:J41) -> 0 | ... N29: =SUM(N30:N41) -> 0 | O29: =SUM(C29:N29) -> 0
B30: CHU Bogodogo | C30: 0 | D30: 0 | E30: 0 | F30: 0 | G30: 0 | H30: 0 | I30: 0 | J30: 0 | K30: 0 | L30: 0 | M30: 0 | N30: 0 | O30: =SUM(C30:N30) -> 0
B31: CHU Pédiatrique CDG | C31: 0 | D31: 0 | E31: 0 | F31: 0 | G31: 0 | H31: 0 | I31: 0 | J31: 0 | K31: 0 | L31: 0 | M31: 0 | N31: 0 | O31: =SUM(C31:N31) -> 0
B32: CHU Tengandogo | C32: 0 | D32: 0 | E32: 0 | F32: 0 | G32: 0 | H32: 0 | I32: 0 | J32: 0 | K32: 0 | L32: 0 | M32: 0 | N32: 0 | O32: =SUM(C32:N32) -> 0
B33: CHU Yalgado | C33: 0 | D33: 0 | E33: 0 | F33: 0 | G33: 0 | H33: 0 | I33: 0 | J33: 0 | K33: 0 | L33: 0 | M33: 0 | N33: 0 | O33: =SUM(C33:N33) -> 0
B34: Hôpital Paul VI | C34: 0 | D34: 0 | E34: 0 | F34: 0 | G34: 0 | H34: 0 | I34: 0 | J34: 0 | K34: 0 | L34: 0 | M34: 0 | N34: 0 | O34: =SUM(C34:N34) -> 0
B35: Hôpital Saint Camille | C35: 0 | D35: 0 | E35: 0 | F35: 0 | G35: 0 | H35: 0 | I35: 0 | J35: 0 | K35: 0 | L35: 0 | M35: 0 | N35: 0 | O35: =SUM(C35:N35) -> 0
B36: Hôpital SCHIPHRA | C36: 0 | D36: 0 | E36: 0 | F36: 0 | G36: 0 | H36: 0 | I36: 0 | J36: 0 | K36: 0 | L36: 0 | M36: 0 | N36: 0 | O36: =SUM(C36:N36) -> 0
B37: DS Baskuy | C37: 0 | D37: 0 | E37: 0 | F37: 0 | G37: 0 | H37: 0 | I37: 0 | J37: 0 | K37: 0 | L37: 0 | M37: 0 | N37: 0 | O37: =SUM(C37:N37) -> 0
B38: DS Bogodogo | C38: 0 | D38: 0 | E38: 0 | F38: 0 | G38: 0 | H38: 0 | I38: 0 | J38: 0 | K38: 0 | L38: 0 | M38: 0 | N38: 0 | O38: =SUM(C38:N38) -> 0
B39: DS Boulmiougou | C39: 0 | D39: 0 | E39: 0 | F39: 0 | G39: 0 | H39: 0 | I39: 0 | J39: 0 | K39: 0 | L39: 0 | M39: 0 | N39: 0 | O39: =SUM(C39:N39) -> 0
B40: DS Nongr-Massom | C40: 0 | D40: 0 | E40: 0 | F40: 0 | G40: 0 | H40: 0 | I40: 0 | J40: 0 | K40: 0 | L40: 0 | M40: 0 | N40: 0 | O40: =SUM(C40:N40) -> 0
B41: DS Sig-Noghin | C41: 0 | D41: 0 | E41: 0 | F41: 0 | G41: 0 | H41: 0 | I41: 0 | J41: 0 | K41: 0 | L41: 0 | M41: 0 | N41: 0 | O41: =SUM(C41:N41) -> 0
A42: Koulsé | C42: =SUM(C43:C49) -> 4 | D42: =SUM(D43:D49) -> 4 | E42: =SUM(E43:E49) -> 4 | F42: =SUM(F43:F49) -> 4 | G42: =SUM(G43:G49) -> 4 | H42: =SUM(H43:H49) -> 4 | I42: =SUM(I43:I49) -> 4 | J42: =SUM(J43:J49) -> 4 | ... N42: =SUM(N43:N49) -> 4 | O42: =SUM(C42:N42) -> 48
B43: CHR Kaya | C43: 0 | D43: 0 | E43: 0 | F43: 0 | G43: 0 | H43: 0 | I43: 0 | J43: 0 | K43: 0 | L43: 0 | M43: 0 | N43: 0 | O43: =SUM(C43:N43) -> 0
B44: DS Barsalogho | C44: 1 | D44: 1 | E44: 1 | F44: 1 | G44: 1 | H44: 1 | I44: 1 | J44: 1 | K44: 1 | L44: 1 | M44: 1 | N44: 1 | O44: =SUM(C44:N44) -> 12
B45: DS Boulsa | C45: 0 | D45: 0 | E45: 0 | F45: 0 | G45: 0 | H45: 0 | I45: 0 | J45: 0 | K45: 0 | L45: 0 | M45: 0 | N45: 0 | O45: =SUM(C45:N45) -> 0
B46: DS Boussouma | C46: 0 | D46: 0 | E46: 0 | F46: 0 | G46: 0 | H46: 0 | I46: 0 | J46: 0 | K46: 0 | L46: 0 | M46: 0 | N46: 0 | O46: =SUM(C46:N46) -> 0
B47: DS Kaya | C47: 0 | D47: 0 | E47: 0 | F47: 0 | G47: 0 | H47: 0 | I47: 0 | J47: 0 | K47: 0 | L47: 0 | M47: 0 | N47: 0 | O47: =SUM(C47:N47) -> 0
B48: DS Kongoussi | C48: 2 | D48: 2 | E48: 2 | F48: 2 | G48: 2 | H48: 2 | I48: 2 | J48: 2 | K48: 2 | L48: 2 | M48: 2 | N48: 2 | O48: =SUM(C48:N48) -> 24
B49: DS Tougouri | C49: 1 | D49: 1 | E49: 1 | F49: 1 | G49: 1 | H49: 1 | I49: 1 | J49: 1 | K49: 1 | L49: 1 | M49: 1 | N49: 1 | O49: =SUM(C49:N49) -> 12
A50: Liptako | C50: =SUM(C51:C54) -> 1 | D50: =SUM(D51:D54) -> 1 | E50: =SUM(E51:E54) -> 1 | F50: =SUM(F51:F54) -> 1 | G50: =SUM(G51:G54) -> 1 | H50: =SUM(H51:H54) -> 1 | I50: =SUM(I51:I54) -> 1 | J50: =SUM(J51:J54) -> 1 | ... N50: =SUM(N51:N54) -> 1 | O50: =SUM(C50:N50) -> 12
B51: CHR Dori | C51: 0 | D51: 0 | E51: 0 | F51: 0 | G51: 0 | H51: 0 | I51: 0 | J51: 0 | K51: 0 | L51: 0 | M51: 0 | N51: 0 | O51: =SUM(C51:N51) -> 0
B52: DS Dori | C52: 0 | D52: 0 | E52: 0 | F52: 0 | G52: 0 | H52: 0 | I52: 0 | J52: 0 | K52: 0 | L52: 0 | M52: 0 | N52: 0 | O52: =SUM(C52:N52) -> 0
B53: DS Gorom-Gorom | C53: 0 | D53: 0 | E53: 0 | F53: 0 | G53: 0 | H53: 0 | I53: 0 | J53: 0 | K53: 0 | L53: 0 | M53: 0 | N53: 0 | O53: =SUM(C53:N53) -> 0
B54: DS Sebba | C54: 1 | D54: 1 | E54: 1 | F54: 1 | G54: 1 | H54: 1 | I54: 1 | J54: 1 | K54: 1 | L54: 1 | M54: 1 | N54: 1 | O54: =SUM(C54:N54) -> 12
A55: Nakambé | C55: =SUM(C56:C63) -> 0 | D55: =SUM(D56:D63) -> 0 | E55: =SUM(E56:E63) -> 0 | F55: =SUM(F56:F63) -> 0 | G55: =SUM(G56:G63) -> 0 | H55: =SUM(H56:H63) -> 0 | I55: =SUM(I56:I63) -> 0 | J55: =SUM(J56:J63) -> 0 | ... N55: =SUM(N56:N63) -> 0 | O55: =SUM(C55:N55) -> 0
B56: CHR Tenkodogo | C56: 0 | D56: 0 | E56: 0 | F56: 0 | G56: 0 | H56: 0 | I56: 0 | J56: 0 | K56: 0 | L56: 0 | M56: 0 | N56: 0 | O56: =SUM(C56:N56) -> 0
B57: DS Bittou | C57: 0 | D57: 0 | E57: 0 | F57: 0 | G57: 0 | H57: 0 | I57: 0 | J57: 0 | K57: 0 | L57: 0 | M57: 0 | N57: 0 | O57: =SUM(C57:N57) -> 0
B58: DS Garango | C58: 0 | D58: 0 | E58: 0 | F58: 0 | G58: 0 | H58: 0 | I58: 0 | J58: 0 | K58: 0 | L58: 0 | M58: 0 | N58: 0 | O58: =SUM(C58:N58) -> 0
B59: DS Koupéla | C59: 0 | D59: 0 | E59: 0 | F59: 0 | G59: 0 | H59: 0 | I59: 0 | J59: 0 | K59: 0 | L59: 0 | M59: 0 | N59: 0 | O59: =SUM(C59:N59) -> 0
B60: DS Ouargaye | C60: 0 | D60: 0 | E60: 0 | F60: 0 | G60: 0 | H60: 0 | I60: 0 | J60: 0 | K60: 0 | L60: 0 | M60: 0 | N60: 0 | O60: =SUM(C60:N60) -> 0
B61: DS Pouytenga | C61: 0 | D61: 0 | E61: 0 | F61: 0 | G61: 0 | H61: 0 | I61: 0 | J61: 0 | K61: 0 | L61: 0 | M61: 0 | N61: 0 | O61: =SUM(C61:N61) -> 0
B62: DS Tenkodogo | C62: 0 | D62: 0 | E62: 0 | F62: 0 | G62: 0 | H62: 0 | I62: 0 | J62: 0 | K62: 0 | L62: 0 | M62: 0 | N62: 0 | O62: =SUM(C62:N62) -> 0
B63: DS Zabré | C63: 0 | D63: 0 | E63: 0 | F63: 0 | G63: 0 | H63: 0 | I63: 0 | J63: 0 | K63: 0 | L63: 0 | M63: 0 | N63: 0 | O63: =SUM(C63:N63) -> 0
A64: Nando | C64: =SUM(C65:C72) -> 0 | D64: =SUM(D65:D72) -> 0 | E64: =SUM(E65:E72) -> 0 | F64: =SUM(F65:F72) -> 0 | G64: =SUM(G65:G72) -> 0 | H64: =SUM(H65:H72) -> 0 | I64: =SUM(I65:I72) -> 0 | J64: =SUM(J65:J72) -> 0 | ... N64: =SUM(N65:N72) -> 0 | O64: =SUM(C64:N64) -> 0
B65: CHR Koudougou | C65: 0 | D65: 0 | E65: 0 | F65: 0 | G65: 0 | H65: 0 | I65: 0 | J65: 0 | K65: 0 | L65: 0 | M65: 0 | N65: 0 | O65: =SUM(C65:N65) -> 0
B66: DS Koudougou | C66: 0 | D66: 0 | E66: 0 | F66: 0 | G66: 0 | H66: 0 | I66: 0 | J66: 0 | K66: 0 | L66: 0 | M66: 0 | N66: 0 | O66: =SUM(C66:N66) -> 0
B67: DS Léo | C67: 0 | D67: 0 | E67: 0 | F67: 0 | G67: 0 | H67: 0 | I67: 0 | J67: 0 | K67: 0 | L67: 0 | M67: 0 | N67: 0 | O67: =SUM(C67:N67) -> 0
B68: DS Nanoro | C68: 0 | D68: 0 | E68: 0 | F68: 0 | G68: 0 | H68: 0 | I68: 0 | J68: 0 | K68: 0 | L68: 0 | M68: 0 | N68: 0 | O68: =SUM(C68:N68) -> 0
B69: DS Réo | C69: 0 | D69: 0 | E69: 0 | F69: 0 | G69: 0 | H69: 0 | I69: 0 | J69: 0 | K69: 0 | L69: 0 | M69: 0 | N69: 0 | O69: =SUM(C69:N69) -> 0
B70: DS Sabou | C70: 0 | D70: 0 | E70: 0 | F70: 0 | G70: 0 | H70: 0 | I70: 0 | J70: 0 | K70: 0 | L70: 0 | M70: 0 | N70: 0 | O70: =SUM(C70:N70) -> 0
B71: DS Sapouy | C71: 0 | D71: 0 | E71: 0 | F71: 0 | G71: 0 | H71: 0 | I71: 0 | J71: 0 | K71: 0 | L71: 0 | M71: 0 | N71: 0 | O71: =SUM(C71:N71) -> 0
B72: DS Tenado | C72: 0 | D72: 0 | E72: 0 | F72: 0 | G72: 0 | H72: 0 | I72: 0 | J72: 0 | K72: 0 | L72: 0 | M72: 0 | N72: 0 | O72: =SUM(C72:N72) -> 0
A73: Nazinon | C73: =SUM(C74:C78) -> 0 | D73: =SUM(D74:D78) -> 0 | E73: =SUM(E74:E78) -> 0 | F73: =SUM(F74:F78) -> 0 | G73: =SUM(G74:G78) -> 0 | H73: =SUM(H74:H78) -> 0 | I73: =SUM(I74:I78) -> 0 | J73: =SUM(J74:J78) -> 0 | ... N73: =SUM(N74:N78) -> 0 | O73: =SUM(C73:N73) -> 0
B74: CHR Manga | C74: 0 | D74: 0 | E74: 0 | F74: 0 | G74: 0 | H74: 0 | I74: 0 | J74: 0 | K74: 0 | L74: 0 | M74: 0 | N74: 0 | O74: =SUM(C74:N74) -> 0
B75: DS Kombissiri | C75: 0 | D75: 0 | E75: 0 | F75: 0 | G75: 0 | H75: 0 | I75: 0 | J75: 0 | K75: 0 | L75: 0 | M75: 0 | N75: 0 | O75: =SUM(C75:N75) -> 0
B76: DS Manga | C76: 0 | D76: 0 | E76: 0 | F76: 0 | G76: 0 | H76: 0 | I76: 0 | J76: 0 | K76: 0 | L76: 0 | M76: 0 | N76: 0 | O76: =SUM(C76:N76) -> 0
B77: DS Po | C77: 0 | D77: 0 | E77: 0 | F77: 0 | G77: 0 | H77: 0 | I77: 0 | J77: 0 | K77: 0 | L77: 0 | M77: 0 | N77: 0 | O77: =SUM(C77:N77) -> 0
B78: DS Sapone | C78: 0 | D78: 0 | E78: 0 | F78: 0 | G78: 0 | H78: 0 | I78: 0 | J78: 0 | K78: 0 | L78: 0 | M78: 0 | N78: 0 | O78: =SUM(C78:N78) -> 0
A79: Oubri | C79: =SUM(C80:C83) -> 0 | D79: =SUM(D80:D83) -> 0 | E79: =SUM(E80:E83) -> 0 | F79: =SUM(F80:F83) -> 0 | G79: =SUM(G80:G83) -> 0 | H79: =SUM(H80:H83) -> 0 | I79: =SUM(I80:I83) -> 0 | J79: =SUM(J80:J83) -> 0 | ... N79: =SUM(N80:N83) -> 0 | O79: =SUM(C79:N79) -> 0
B80: CHR Ziniaré | C80: 0 | D80: 0 | E80: 0 | F80: 0 | G80: 0 | H80: 0 | I80: 0 | J80: 0 | K80: 0 | L80: 0 | M80: 0 | N80: 0 | O80: =SUM(C80:N80) -> 0
B81: DS Boussé | C81: 0 | D81: 0 | E81: 0 | F81: 0 | G81: 0 | H81: 0 | I81: 0 | J81: 0 | K81: 0 | L81: 0 | M81: 0 | N81: 0 | O81: =SUM(C81:N81) -> 0
B82: DS Ziniaré | C82: 0 | D82: 0 | E82: 0 | F82: 0 | G82: 0 | H82: 0 | I82: 0 | J82: 0 | K82: 0 | L82: 0 | M82: 0 | N82: 0 | O82: =SUM(C82:N82) -> 0
B83: DS Zorgho | C83: 0 | D83: 0 | E83: 0 | F83: 0 | G83: 0 | H83: 0 | I83: 0 | J83: 0 | K83: 0 | L83: 0 | M83: 0 | N83: 0 | O83: =SUM(C83:N83) -> 0
A84: Sirba | C84: =SUM(C85:C87) -> 0 | D84: =SUM(D85:D87) -> 0 | E84: =SUM(E85:E87) -> 0 | F84: =SUM(F85:F87) -> 1 | G84: =SUM(G85:G87) -> 1 | H84: =SUM(H85:H87) -> 1 | I84: =SUM(I85:I87) -> 1 | J84: =SUM(J85:J87) -> 1 | ... N84: =SUM(N85:N87) -> 1 | O84: =SUM(C84:N84) -> 9
B85: DS Bogande | C85: 0 | D85: 0 | E85: 0 | F85: 1 | G85: 1 | H85: 1 | I85: 1 | J85: 1 | K85: 1 | L85: 1 | M85: 1 | N85: 1 | O85: =SUM(C85:N85) -> 9
B86: DS Gayeri | C86: 0 | D86: 0 | E86: 0 | F86: 0 | G86: 0 | H86: 0 | I86: 0 | J86: 0 | K86: 0 | L86: 0 | M86: 0 | N86: 0 | O86: =SUM(C86:N86) -> 0
B87: DS Manni | C87: 0 | D87: 0 | E87: 0 | F87: 0 | G87: 0 | H87: 0 | I87: 0 | J87: 0 | K87: 0 | L87: 0 | M87: 0 | N87: 0 | O87: =SUM(C87:N87) -> 0
A88: Soum | C88: =C89 -> 4 | D88: =D89 -> 4 | E88: =E89 -> 4 | F88: =F89 -> 4 | G88: =G89 -> 4 | H88: =H89 -> 4 | I88: =I89 -> 4 | J88: =J89 -> 4 | ... N88: =N89 -> 4 | O88: =SUM(C88:N88) -> 48
B89: DS Djibo | C89: 4 | D89: 4 | E89: 4 | F89: 4 | G89: 4 | H89: 4 | I89: 4 | J89: 4 | K89: 4 | L89: 4 | M89: 4 | N89: 4 | O89: =SUM(C89:N89) -> 48
A90: Sourou | C90: =SUM(C91:C93) -> 0 | D90: =SUM(D91:D93) -> 0 | E90: =SUM(E91:E93) -> 0 | F90: =SUM(F91:F93) -> 0 | G90: =SUM(G91:G93) -> 0 | H90: =SUM(H91:H93) -> 0 | I90: =SUM(I91:I93) -> 0 | J90: =SUM(J91:J93) -> 0 | ... N90: =SUM(N91:N93) -> 0 | O90: =SUM(C90:N90) -> 0
B91: DS Nouna | C91: 0 | D91: 0 | E91: 0 | F91: 0 | G91: 0 | H91: 0 | I91: 0 | J91: 0 | K91: 0 | L91: 0 | M91: 0 | N91: 0 | O91: =SUM(C91:N91) -> 0
B92: DS Toma | C92: 0 | D92: 0 | E92: 0 | F92: 0 | G92: 0 | H92: 0 | I92: 0 | J92: 0 | K92: 0 | L92: 0 | M92: 0 | N92: 0 | O92: =SUM(C92:N92) -> 0
B93: DS Tougan | C93: 0 | D93: 0 | E93: 0 | F93: 0 | G93: 0 | H93: 0 | I93: 0 | J93: 0 | K93: 0 | L93: 0 | M93: 0 | N93: 0 | O93: =SUM(C93:N93) -> 0
A94: Tannounyan | C94: =SUM(C95:C98) -> 0 | D94: =SUM(D95:D98) -> 0 | E94: =SUM(E95:E98) -> 0 | F94: =SUM(F95:F98) -> 0 | G94: =SUM(G95:G98) -> 0 | H94: =SUM(H95:H98) -> 0 | I94: =SUM(I95:I98) -> 0 | J94: =SUM(J95:J98) -> 0 | ... N94: =SUM(N95:N98) -> 0 | O94: =SUM(C94:N94) -> 0
B95: CHR Banfora | C95: 0 | D95: 0 | E95: 0 | F95: 0 | G95: 0 | H95: 0 | I95: 0 | J95: 0 | K95: 0 | L95: 0 | M95: 0 | N95: 0 | O95: =SUM(C95:N95) -> 0
B96: DS Banfora | C96: 0 | D96: 0 | E96: 0 | F96: 0 | G96: 0 | H96: 0 | I96: 0 | J96: 0 | K96: 0 | L96: 0 | M96: 0 | N96: 0 | O96: =SUM(C96:N96) -> 0
B97: DS Mangodara | C97: 0 | D97: 0 | E97: 0 | F97: 0 | G97: 0 | H97: 0 | I97: 0 | J97: 0 | K97: 0 | L97: 0 | M97: 0 | N97: 0 | O97: =SUM(C97:N97) -> 0
B98: DS Sindou | C98: 0 | D98: 0 | E98: 0 | F98: 0 | G98: 0 | H98: 0 | I98: 0 | J98: 0 | K98: 0 | L98: 0 | M98: 0 | N98: 0 | O98: =SUM(C98:N98) -> 0
A99: Tapoa | C99: =SUM(C100) -> 1 | D99: =SUM(D100) -> 0 | E99: =SUM(E100) -> 1 | F99: =SUM(F100) -> 1 | G99: =SUM(G100) -> 1 | H99: =SUM(H100) -> 4 | I99: =SUM(I100) -> 2 | J99: =SUM(J100) -> 4 | ... N99: =SUM(N100) -> 4 | O99: =SUM(C99:N99) -> 30
B100: DS Diapaga | C100: 1 | D100: 0 | E100: 1 | F100: 1 | G100: 1 | H100: 4 | I100: 2 | J100: 4 | K100: 4 | L100: 4 | M100: 4 | N100: 4 | O100: =SUM(C100:N100) -> 30
...

Sheet ComplétudeCorrige
A1: Tableau 1.11: complétude des rapports mensuels des formations sanitaires prenant en compte la non transmission de rapport pour fait d'insecurité en 2025
A2: Régions / districts | C2: Formations sanitaires publiques | F2: Formations sanitaires privées | I2: Formations sanitaires publiques et privées
C3: Nombre de rapports attendus | D3: Nombre de rapports saisis | E3: Complétude (%) des rapports dans la base | F3: Nombre de rapports attendus | G3: Nombre de rapports saisis | H3: Complétude (%) des rapports dans la base | I3: Nombre de rapports attendus | J3: Nombre de rapports saisis | K3: Complétude (%) des rapports dans la base | L3: Nombre de rapports saisis à temps | M3: Promptitude (%) des rapports dans la base
A4: Bankui | C4: =Complétude!C4-'Sécurité précaire_Publique'!O3 -> -236 | D4: =Complétude!D4 -> 0 | E4: =IFERROR(D4/C4*100,"") -> 0 | F4: =Complétude!F4-'Sécurité précaire_Privee'!O3 -> 0 | G4: =Complétude!G4 -> 0 | H4: =IFERROR(G4/F4*100,"") | I4: =C4+F4 -> -236 | J4: =D4+G4 -> 0 | K4: =IFERROR(J4/I4*100,"") -> 0 | L4: =Complétude!L4 -> 0 | M4: =IFERROR(L4/I4*100,"") -> 0
B5: CHR Dédougou | C5: =Complétude!C5-'Sécurité précaire_Publique'!O4 -> 0 | D5: =Complétude!D5 -> 0 | E5: =IFERROR(D5/C5*100,"") | F5: =Complétude!F5-'Sécurité précaire_Privee'!O4 -> 0 | G5: =Complétude!G5 -> 0 | H5: =IFERROR(G5/F5*100,"") | I5: =C5+F5 -> 0 | J5: =D5+G5 -> 0 | K5: =IFERROR(J5/I5*100,"") | L5: =Complétude!L5 -> 0 | M5: =IFERROR(L5/I5*100,"")
B6: DS Boromo | C6: =Complétude!C6-'Sécurité précaire_Publique'!O5 -> 0 | D6: =Complétude!D6 -> 0 | E6: =IFERROR(D6/C6*100,"") | F6: =Complétude!F6-'Sécurité précaire_Privee'!O5 -> 0 | G6: =Complétude!G6 -> 0 | H6: =IFERROR(G6/F6*100,"") | I6: =C6+F6 -> 0 | J6: =D6+G6 -> 0 | K6: =IFERROR(J6/I6*100,"") | L6: =Complétude!L6 -> 0 | M6: =IFERROR(L6/I6*100,"")
B7: DS Dedougou | C7: =Complétude!C7-'Sécurité précaire_Publique'!O6 -> -69 | D7: =Complétude!D7 -> 0 | E7: =IFERROR(D7/C7*100,"") -> 0 | F7: =Complétude!F7-'Sécurité précaire_Privee'!O6 -> 0 | G7: =Complétude!G7 -> 0 | H7: =IFERROR(G7/F7*100,"") | I7: =C7+F7 -> -69 | J7: =D7+G7 -> 0 | K7: =IFERROR(J7/I7*100,"") -> 0 | L7: =Complétude!L7 -> 0 | M7: =IFERROR(L7/I7*100,"") -> 0
B8: DS Solenzo | C8: =Complétude!C8-'Sécurité précaire_Publique'!O7 -> -167 | D8: =Complétude!D8 -> 0 | E8: =IFERROR(D8/C8*100,"") -> 0 | F8: =Complétude!F8-'Sécurité précaire_Privee'!O7 -> 0 | G8: =Complétude!G8 -> 0 | H8: =IFERROR(G8/F8*100,"") | I8: =C8+F8 -> -167 | J8: =D8+G8 -> 0 | K8: =IFERROR(J8/I8*100,"") -> 0 | L8: =Complétude!L8 -> 0 | M8: =IFERROR(L8/I8*100,"") -> 0
A9: Djoro | C9: =Complétude!C9-'Sécurité précaire_Publique'!O8 -> -12 | D9: =Complétude!D9 -> 0 | E9: =IFERROR(D9/C9*100,"") -> 0 | F9: =Complétude!F9-'Sécurité précaire_Privee'!O8 -> 0 | G9: =Complétude!G9 -> 0 | H9: =IFERROR(G9/F9*100,"") | I9: =C9+F9 -> -12 | J9: =D9+G9 -> 0 | K9: =IFERROR(J9/I9*100,"") -> 0 | L9: =Complétude!L9 -> 0 | M9: =IFERROR(L9/I9*100,"") -> 0
B10: CHR Gaoua | C10: =Complétude!C10-'Sécurité précaire_Publique'!O9 -> 0 | D10: =Complétude!D10 -> 0 | E10: =IFERROR(D10/C10*100,"") | F10: =Complétude!F10-'Sécurité précaire_Privee'!O9 -> 0 | G10: =Complétude!G10 -> 0 | H10: =IFERROR(G10/F10*100,"") | I10: =C10+F10 -> 0 | J10: =D10+G10 -> 0 | K10: =IFERROR(J10/I10*100,"") | L10: =Complétude!L10 -> 0 | M10: =IFERROR(L10/I10*100,"")
B11: DS Batié | C11: =Complétude!C11-'Sécurité précaire_Publique'!O10 -> 0 | D11: =Complétude!D11 -> 0 | E11: =IFERROR(D11/C11*100,"") | F11: =Complétude!F11-'Sécurité précaire_Privee'!O10 -> 0 | G11: =Complétude!G11 -> 0 | H11: =IFERROR(G11/F11*100,"") | I11: =C11+F11 -> 0 | J11: =D11+G11 -> 0 | K11: =IFERROR(J11/I11*100,"") | L11: =Complétude!L11 -> 0 | M11: =IFERROR(L11/I11*100,"")
B12: DS Dano | C12: =Complétude!C12-'Sécurité précaire_Publique'!O11 -> 0 | D12: =Complétude!D12 -> 0 | E12: =IFERROR(D12/C12*100,"") | F12: =Complétude!F12-'Sécurité précaire_Privee'!O11 -> 0 | G12: =Complétude!G12 -> 0 | H12: =IFERROR(G12/F12*100,"") | I12: =C12+F12 -> 0 | J12: =D12+G12 -> 0 | K12: =IFERROR(J12/I12*100,"") | L12: =Complétude!L12 -> 0 | M12: =IFERROR(L12/I12*100,"")
B13: DS Diébougou | C13: =Complétude!C13-'Sécurité précaire_Publique'!O12 -> 0 | D13: =Complétude!D13 -> 0 | E13: =IFERROR(D13/C13*100,"") | F13: =Complétude!F13-'Sécurité précaire_Privee'!O12 -> 0 | G13: =Complétude!G13 -> 0 | H13: =IFERROR(G13/F13*100,"") | I13: =C13+F13 -> 0 | J13: =D13+G13 -> 0 | K13: =IFERROR(J13/I13*100,"") | L13: =Complétude!L13 -> 0 | M13: =IFERROR(L13/I13*100,"")
B14: DS Gaoua | C14: =Complétude!C14-'Sécurité précaire_Publique'!O13 -> 0 | D14: =Complétude!D14 -> 0 | E14: =IFERROR(D14/C14*100,"") | F14: =Complétude!F14-'Sécurité précaire_Privee'!O13 -> 0 | G14: =Complétude!G14 -> 0 | H14: =IFERROR(G14/F14*100,"") | I14: =C14+F14 -> 0 | J14: =D14+G14 -> 0 | K14: =IFERROR(J14/I14*100,"") | L14: =Complétude!L14 -> 0 | M14: =IFERROR(L14/I14*100,"")
B15: DS Kampti | C15: =Complétude!C15-'Sécurité précaire_Publique'!O14 -> -12 | D15: =Complétude!D15 -> 0 | E15: =IFERROR(D15/C15*100,"") -> 0 | F15: =Complétude!F15-'Sécurité précaire_Privee'!O14 -> 0 | G15: =Complétude!G15 -> 0 | H15: =IFERROR(G15/F15*100,"") | I15: =C15+F15 -> -12 | J15: =D15+G15 -> 0 | K15: =IFERROR(J15/I15*100,"") -> 0 | L15: =Complétude!L15 -> 0 | M15: =IFERROR(L15/I15*100,"") -> 0
A16: Goulmou | C16: =Complétude!C16-'Sécurité précaire_Publique'!O15 -> -415 | D16: =Complétude!D16 -> 0 | E16: =IFERROR(D16/C16*100,"") -> 0 | F16: =Complétude!F16-'Sécurité précaire_Privee'!O15 -> -24 | G16: =Complétude!G16 -> 0 | H16: =IFERROR(G16/F16*100,"") -> 0 | I16: =C16+F16 -> -439 | J16: =D16+G16 -> 0 | K16: =IFERROR(J16/I16*100,"") -> 0 | L16: =Complétude!L16 -> 0 | M16: =IFERROR(L16/I16*100,"") -> 0
B17: CHR Fada N'Gourma | C17: =Complétude!C17-'Sécurité précaire_Publique'!O16 -> 0 | D17: =Complétude!D17 -> 0 | E17: =IFERROR(D17/C17*100,"") | F17: =Complétude!F17-'Sécurité précaire_Privee'!O16 -> 0 | G17: =Complétude!G17 -> 0 | H17: =IFERROR(G17/F17*100,"") | I17: =C17+F17 -> 0 | J17: =D17+G17 -> 0 | K17: =IFERROR(J17/I17*100,"") | L17: =Complétude!L17 -> 0 | M17: =IFERROR(L17/I17*100,"")
B18: DS Fada | C18: =Complétude!C18-'Sécurité précaire_Publique'!O17 -> -307 | D18: =Complétude!D18 -> 0 | E18: =IFERROR(D18/C18*100,"") -> 0 | F18: =Complétude!F18-'Sécurité précaire_Privee'!O17 -> -12 | G18: =Complétude!G18 -> 0 | H18: =IFERROR(G18/F18*100,"") -> 0 | I18: =C18+F18 -> -319 | J18: =D18+G18 -> 0 | K18: =IFERROR(J18/I18*100,"") -> 0 | L18: =Complétude!L18 -> 0 | M18: =IFERROR(L18/I18*100,"") -> 0
B19: DS Pama | C19: =Complétude!C19-'Sécurité précaire_Publique'!O18 -> -108 | D19: =Complétude!D19 -> 0 | E19: =IFERROR(D19/C19*100,"") -> 0 | F19: =Complétude!F19-'Sécurité précaire_Privee'!O18 -> -12 | G19: =Complétude!G19 -> 0 | H19: =IFERROR(G19/F19*100,"") -> 0 | I19: =C19+F19 -> -120 | J19: =D19+G19 -> 0 | K19: =IFERROR(J19/I19*100,"") -> 0 | L19: =Complétude!L19 -> 0 | M19: =IFERROR(L19/I19*100,"") -> 0
A20: Guiriko | C20: =Complétude!C20-'Sécurité précaire_Publique'!O19 -> -96 | D20: =Complétude!D20 -> 0 | E20: =IFERROR(D20/C20*100,"") -> 0 | F20: =Complétude!F20-'Sécurité précaire_Privee'!O19 -> 0 | G20: =Complétude!G20 -> 0 | H20: =IFERROR(G20/F20*100,"") | I20: =C20+F20 -> -96 | J20: =D20+G20 -> 0 | K20: =IFERROR(J20/I20*100,"") -> 0 | L20: =Complétude!L20 -> 0 | M20: =IFERROR(L20/I20*100,"") -> 0
B21: CHU Sanou Souro | C21: =Complétude!C21-'Sécurité précaire_Publique'!O20 -> 0 | D21: =Complétude!D21 -> 0 | E21: =IFERROR(D21/C21*100,"") | F21: =Complétude!F21-'Sécurité précaire_Privee'!O20 -> 0 | G21: =Complétude!G21 -> 0 | H21: =IFERROR(G21/F21*100,"") | I21: =C21+F21 -> 0 | J21: =D21+G21 -> 0 | K21: =IFERROR(J21/I21*100,"") | L21: =Complétude!L21 -> 0 | M21: =IFERROR(L21/I21*100,"")
B22: DS Dafra | C22: =Complétude!C22-'Sécurité précaire_Publique'!O21 -> 0 | D22: =Complétude!D22 -> 0 | E22: =IFERROR(D22/C22*100,"") | F22: =Complétude!F22-'Sécurité précaire_Privee'!O21 -> 0 | G22: =Complétude!G22 -> 0 | H22: =IFERROR(G22/F22*100,"") | I22: =C22+F22 -> 0 | J22: =D22+G22 -> 0 | K22: =IFERROR(J22/I22*100,"") | L22: =Complétude!L22 -> 0 | M22: =IFERROR(L22/I22*100,"")
B23: DS Dande | C23: =Complétude!C23-'Sécurité précaire_Publique'!O22 -> -18 | D23: =Complétude!D23 -> 0 | E23: =IFERROR(D23/C23*100,"") -> 0 | F23: =Complétude!F23-'Sécurité précaire_Privee'!O22 -> 0 | G23: =Complétude!G23 -> 0 | H23: =IFERROR(G23/F23*100,"") | I23: =C23+F23 -> -18 | J23: =D23+G23 -> 0 | K23: =IFERROR(J23/I23*100,"") -> 0 | L23: =Complétude!L23 -> 0 | M23: =IFERROR(L23/I23*100,"") -> 0
B24: DS Do | C24: =Complétude!C24-'Sécurité précaire_Publique'!O23 -> 0 | D24: =Complétude!D24 -> 0 | E24: =IFERROR(D24/C24*100,"") | F24: =Complétude!F24-'Sécurité précaire_Privee'!O23 -> 0 | G24: =Complétude!G24 -> 0 | H24: =IFERROR(G24/F24*100,"") | I24: =C24+F24 -> 0 | J24: =D24+G24 -> 0 | K24: =IFERROR(J24/I24*100,"") | L24: =Complétude!L24 -> 0 | M24: =IFERROR(L24/I24*100,"")
B25: DS Hounde | C25: =Complétude!C25-'Sécurité précaire_Publique'!O24 -> -12 | D25: =Complétude!D25 -> 0 | E25: =IFERROR(D25/C25*100,"") -> 0 | F25: =Complétude!F25-'Sécurité précaire_Privee'!O24 -> 0 | G25: =Complétude!G25 -> 0 | H25: =IFERROR(G25/F25*100,"") | I25: =C25+F25 -> -12 | J25: =D25+G25 -> 0 | K25: =IFERROR(J25/I25*100,"") -> 0 | L25: =Complétude!L25 -> 0 | M25: =IFERROR(L25/I25*100,"") -> 0
B26: DS Karangasso Vigue | C26: =Complétude!C26-'Sécurité précaire_Publique'!O25 -> 0 | D26: =Complétude!D26 -> 0 | E26: =IFERROR(D26/C26*100,"") | F26: =Complétude!F26-'Sécurité précaire_Privee'!O25 -> 0 | G26: =Complétude!G26 -> 0 | H26: =IFERROR(G26/F26*100,"") | I26: =C26+F26 -> 0 | J26: =D26+G26 -> 0 | K26: =IFERROR(J26/I26*100,"") | L26: =Complétude!L26 -> 0 | M26: =IFERROR(L26/I26*100,"")
B27: DS Léna | C27: =Complétude!C27-'Sécurité précaire_Publique'!O26 -> 0 | D27: =Complétude!D27 -> 0 | E27: =IFERROR(D27/C27*100,"") | F27: =Complétude!F27-'Sécurité précaire_Privee'!O26 -> 0 | G27: =Complétude!G27 -> 0 | H27: =IFERROR(G27/F27*100,"") | I27: =C27+F27 -> 0 | J27: =D27+G27 -> 0 | K27: =IFERROR(J27/I27*100,"") | L27: =Complétude!L27 -> 0 | M27: =IFERROR(L27/I27*100,"")
B28: DS N'Dorola | C28: =Complétude!C28-'Sécurité précaire_Publique'!O27 -> -36 | D28: =Complétude!D28 -> 0 | E28: =IFERROR(D28/C28*100,"") -> 0 | F28: =Complétude!F28-'Sécurité précaire_Privee'!O27 -> 0 | G28: =Complétude!G28 -> 0 | H28: =IFERROR(G28/F28*100,"") | I28: =C28+F28 -> -36 | J28: =D28+G28 -> 0 | K28: =IFERROR(J28/I28*100,"") -> 0 | L28: =Complétude!L28 -> 0 | M28: =IFERROR(L28/I28*100,"") -> 0
B29: DS Orodara | C29: =Complétude!C29-'Sécurité précaire_Publique'!O28 -> -30 | D29: =Complétude!D29 -> 0 | E29: =IFERROR(D29/C29*100,"") -> 0 | F29: =Complétude!F29-'Sécurité précaire_Privee'!O28 -> 0 | G29: =Complétude!G29 -> 0 | H29: =IFERROR(G29/F29*100,"") | I29: =C29+F29 -> -30 | J29: =D29+G29 -> 0 | K29: =IFERROR(J29/I29*100,"") -> 0 | L29: =Complétude!L29 -> 0 | M29: =IFERROR(L29/I29*100,"") -> 0
A30: Kadiogo | C30: =Complétude!C30-'Sécurité précaire_Publique'!O29 -> 0 | D30: =Complétude!D30 -> 0 | E30: =IFERROR(D30/C30*100,"") | F30: =Complétude!F30-'Sécurité précaire_Privee'!O29 -> 0 | G30: =Complétude!G30 -> 0 | H30: =IFERROR(G30/F30*100,"") | I30: =C30+F30 -> 0 | J30: =D30+G30 -> 0 | K30: =IFERROR(J30/I30*100,"") | L30: =Complétude!L30 -> 0 | M30: =IFERROR(L30/I30*100,"")
B31: CHU Bogodogo | C31: =Complétude!C31-'Sécurité précaire_Publique'!O30 -> 0 | D31: =Complétude!D31 -> 0 | E31: =IFERROR(D31/C31*100,"") | F31: =Complétude!F31-'Sécurité précaire_Privee'!O30 -> 0 | G31: =Complétude!G31 -> 0 | H31: =IFERROR(G31/F31*100,"") | I31: =C31+F31 -> 0 | J31: =D31+G31 -> 0 | K31: =IFERROR(J31/I31*100,"") | L31: =Complétude!L31 -> 0 | M31: =IFERROR(L31/I31*100,"")
B32: CHU Pédiatrique CDG | C32: =Complétude!C32-'Sécurité précaire_Publique'!O31 -> 0 | D32: =Complétude!D32 -> 0 | E32: =IFERROR(D32/C32*100,"") | F32: =Complétude!F32-'Sécurité précaire_Privee'!O31 -> 0 | G32: =Complétude!G32 -> 0 | H32: =IFERROR(G32/F32*100,"") | I32: =C32+F32 -> 0 | J32: =D32+G32 -> 0 | K32: =IFERROR(J32/I32*100,"") | L32: =Complétude!L32 -> 0 | M32: =IFERROR(L32/I32*100,"")
B33: CHU Tengandogo | C33: =Complétude!C33-'Sécurité précaire_Publique'!O32 -> 0 | D33: =Complétude!D33 -> 0 | E33: =IFERROR(D33/C33*100,"") | F33: =Complétude!F33-'Sécurité précaire_Privee'!O32 -> 0 | G33: =Complétude!G33 -> 0 | H33: =IFERROR(G33/F33*100,"") | I33: =C33+F33 -> 0 | J33: =D33+G33 -> 0 | K33: =IFERROR(J33/I33*100,"") | L33: =Complétude!L33 -> 0 | M33: =IFERROR(L33/I33*100,"")
B34: CHU Yalgado | C34: =Complétude!C34-'Sécurité précaire_Publique'!O33 -> 0 | D34: =Complétude!D34 -> 0 | E34: =IFERROR(D34/C34*100,"") | F34: =Complétude!F34-'Sécurité précaire_Privee'!O33 -> 0 | G34: =Complétude!G34 -> 0 | H34: =IFERROR(G34/F34*100,"") | I34: =C34+F34 -> 0 | J34: =D34+G34 -> 0 | K34: =IFERROR(J34/I34*100,"") | L34: =Complétude!L34 -> 0 | M34: =IFERROR(L34/I34*100,"")
B35: Hôpital Paul VI | C35: =Complétude!C35-'Sécurité précaire_Publique'!O34 -> 0 | D35: =Complétude!D35 -> 0 | E35: =IFERROR(D35/C35*100,"") | F35: =Complétude!F35-'Sécurité précaire_Privee'!O34 -> 0 | G35: =Complétude!G35 -> 0 | H35: =IFERROR(G35/F35*100,"") | I35: =C35+F35 -> 0 | J35: =D35+G35 -> 0 | K35: =IFERROR(J35/I35*100,"") | L35: =Complétude!L35 -> 0 | M35: =IFERROR(L35/I35*100,"")
B36: Hôpital Saint Camille | C36: =Complétude!C36-'Sécurité précaire_Publique'!O35 -> 0 | D36: =Complétude!D36 -> 0 | E36: =IFERROR(D36/C36*100,"") | F36: =Complétude!F36-'Sécurité précaire_Privee'!O35 -> 0 | G36: =Complétude!G36 -> 0 | H36: =IFERROR(G36/F36*100,"") | I36: =C36+F36 -> 0 | J36: =D36+G36 -> 0 | K36: =IFERROR(J36/I36*100,"") | L36: =Complétude!L36 -> 0 | M36: =IFERROR(L36/I36*100,"")
B37: Hôpital SCHIPHRA | C37: =Complétude!C37-'Sécurité précaire_Publique'!O36 -> 0 | D37: =Complétude!D37 -> 0 | E37: =IFERROR(D37/C37*100,"") | F37: =Complétude!F37-'Sécurité précaire_Privee'!O36 -> 0 | G37: =Complétude!G37 -> 0 | H37: =IFERROR(G37/F37*100,"") | I37: =C37+F37 -> 0 | J37: =D37+G37 -> 0 | K37: =IFERROR(J37/I37*100,"") | L37: =Complétude!L37 -> 0 | M37: =IFERROR(L37/I37*100,"")
B38: DS Baskuy | C38: =Complétude!C38-'Sécurité précaire_Publique'!O37 -> 0 | D38: =Complétude!D38 -> 0 | E38: =IFERROR(D38/C38*100,"") | F38: =Complétude!F38-'Sécurité précaire_Privee'!O37 -> 0 | G38: =Complétude!G38 -> 0 | H38: =IFERROR(G38/F38*100,"") | I38: =C38+F38 -> 0 | J38: =D38+G38 -> 0 | K38: =IFERROR(J38/I38*100,"") | L38: =Complétude!L38 -> 0 | M38: =IFERROR(L38/I38*100,"")
B39: DS Bogodogo | C39: =Complétude!C39-'Sécurité précaire_Publique'!O38 -> 0 | D39: =Complétude!D39 -> 0 | E39: =IFERROR(D39/C39*100,"") | F39: =Complétude!F39-'Sécurité précaire_Privee'!O38 -> 0 | G39: =Complétude!G39 -> 0 | H39: =IFERROR(G39/F39*100,"") | I39: =C39+F39 -> 0 | J39: =D39+G39 -> 0 | K39: =IFERROR(J39/I39*100,"") | L39: =Complétude!L39 -> 0 | M39: =IFERROR(L39/I39*100,"")
B40: DS Boulmiougou | C40: =Complétude!C40-'Sécurité précaire_Publique'!O39 -> 0 | D40: =Complétude!D40 -> 0 | E40: =IFERROR(D40/C40*100,"") | F40: =Complétude!F40-'Sécurité précaire_Privee'!O39 -> 0 | G40: =Complétude!G40 -> 0 | H40: =IFERROR(G40/F40*100,"") | I40: =C40+F40 -> 0 | J40: =D40+G40 -> 0 | K40: =IFERROR(J40/I40*100,"") | L40: =Complétude!L40 -> 0 | M40: =IFERROR(L40/I40*100,"")
B41: DS Nongr-Massom | C41: =Complétude!C41-'Sécurité précaire_Publique'!O40 -> 0 | D41: =Complétude!D41 -> 0 | E41: =IFERROR(D41/C41*100,"") | F41: =Complétude!F41-'Sécurité précaire_Privee'!O40 -> 0 | G41: =Complétude!G41 -> 0 | H41: =IFERROR(G41/F41*100,"") | I41: =C41+F41 -> 0 | J41: =D41+G41 -> 0 | K41: =IFERROR(J41/I41*100,"") | L41: =Complétude!L41 -> 0 | M41: =IFERROR(L41/I41*100,"")
B42: DS Sig-Noghin | C42: =Complétude!C42-'Sécurité précaire_Publique'!O41 -> 0 | D42: =Complétude!D42 -> 0 | E42: =IFERROR(D42/C42*100,"") | F42: =Complétude!F42-'Sécurité précaire_Privee'!O41 -> 0 | G42: =Complétude!G42 -> 0 | H42: =IFERROR(G42/F42*100,"") | I42: =C42+F42 -> 0 | J42: =D42+G42 -> 0 | K42: =IFERROR(J42/I42*100,"") | L42: =Complétude!L42 -> 0 | M42: =IFERROR(L42/I42*100,"")
A43: Koulsé | C43: =Complétude!C43-'Sécurité précaire_Publique'!O42 -> -950 | D43: =Complétude!D43 -> 0 | E43: =IFERROR(D43/C43*100,"") -> 0 | F43: =Complétude!F43-'Sécurité précaire_Privee'!O42 -> -48 | G43: =Complétude!G43 -> 0 | H43: =IFERROR(G43/F43*100,"") -> 0 | I43: =C43+F43 -> -998 | J43: =D43+G43 -> 0 | K43: =IFERROR(J43/I43*100,"") -> 0 | L43: =Complétude!L43 -> 0 | M43: =IFERROR(L43/I43*100,"") -> 0
B44: CHR Kaya | C44: =Complétude!C44-'Sécurité précaire_Publique'!O43 -> 0 | D44: =Complétude!D44 -> 0 | E44: =IFERROR(D44/C44*100,"") | F44: =Complétude!F44-'Sécurité précaire_Privee'!O43 -> 0 | G44: =Complétude!G44 -> 0 | H44: =IFERROR(G44/F44*100,"") | I44: =C44+F44 -> 0 | J44: =D44+G44 -> 0 | K44: =IFERROR(J44/I44*100,"") | L44: =Complétude!L44 -> 0 | M44: =IFERROR(L44/I44*100,"")
B45: DS Barsalogho | C45: =Complétude!C45-'Sécurité précaire_Publique'!O44 -> -124 | D45: =Complétude!D45 -> 0 | E45: =IFERROR(D45/C45*100,"") -> 0 | F45: =Complétude!F45-'Sécurité précaire_Privee'!O44 -> -12 | G45: =Complétude!G45 -> 0 | H45: =IFERROR(G45/F45*100,"") -> 0 | I45: =C45+F45 -> -136 | J45: =D45+G45 -> 0 | K45: =IFERROR(J45/I45*100,"") -> 0 | L45: =Complétude!L45 -> 0 | M45: =IFERROR(L45/I45*100,"") -> 0
B46: DS Boulsa | C46: =Complétude!C46-'Sécurité précaire_Publique'!O45 -> -96 | D46: =Complétude!D46 -> 0 | E46: =IFERROR(D46/C46*100,"") -> 0 | F46: =Complétude!F46-'Sécurité précaire_Privee'!O45 -> 0 | G46: =Complétude!G46 -> 0 | H46: =IFERROR(G46/F46*100,"") | I46: =C46+F46 -> -96 | J46: =D46+G46 -> 0 | K46: =IFERROR(J46/I46*100,"") -> 0 | L46: =Complétude!L46 -> 0 | M46: =IFERROR(L46/I46*100,"") -> 0
B47: DS Boussouma | C47: =Complétude!C47-'Sécurité précaire_Publique'!O46 -> -5 | D47: =Complétude!D47 -> 0 | E47: =IFERROR(D47/C47*100,"") -> 0 | F47: =Complétude!F47-'Sécurité précaire_Privee'!O46 -> 0 | G47: =Complétude!G47 -> 0 | H47: =IFERROR(G47/F47*100,"") | I47: =C47+F47 -> -5 | J47: =D47+G47 -> 0 | K47: =IFERROR(J47/I47*100,"") -> 0 | L47: =Complétude!L47 -> 0 | M47: =IFERROR(L47/I47*100,"") -> 0
B48: DS Kaya | C48: =Complétude!C48-'Sécurité précaire_Publique'!O47 -> -148 | D48: =Complétude!D48 -> 0 | E48: =IFERROR(D48/C48*100,"") -> 0 | F48: =Complétude!F48-'Sécurité précaire_Privee'!O47 -> 0 | G48: =Complétude!G48 -> 0 | H48: =IFERROR(G48/F48*100,"") | I48: =C48+F48 -> -148 | J48: =D48+G48 -> 0 | K48: =IFERROR(J48/I48*100,"") -> 0 | L48: =Complétude!L48 -> 0 | M48: =IFERROR(L48/I48*100,"") -> 0
B49: DS Kongoussi | C49: =Complétude!C49-'Sécurité précaire_Publique'!O48 -> -336 | D49: =Complétude!D49 -> 0 | E49: =IFERROR(D49/C49*100,"") -> 0 | F49: =Complétude!F49-'Sécurité précaire_Privee'!O48 -> -24 | G49: =Complétude!G49 -> 0 | H49: =IFERROR(G49/F49*100,"") -> 0 | I49: =C49+F49 -> -360 | J49: =D49+G49 -> 0 | K49: =IFERROR(J49/I49*100,"") -> 0 | L49: =Complétude!L49 -> 0 | M49: =IFERROR(L49/I49*100,"") -> 0
B50: DS Tougouri | C50: =Complétude!C50-'Sécurité précaire_Publique'!O49 -> -241 | D50: =Complétude!D50 -> 0 | E50: =IFERROR(D50/C50*100,"") -> 0 | F50: =Complétude!F50-'Sécurité précaire_Privee'!O49 -> -12 | G50: =Complétude!G50 -> 0 | H50: =IFERROR(G50/F50*100,"") -> 0 | I50: =C50+F50 -> -253 | J50: =D50+G50 -> 0 | K50: =IFERROR(J50/I50*100,"") -> 0 | L50: =Complétude!L50 -> 0 | M50: =IFERROR(L50/I50*100,"") -> 0
A51: Liptako | C51: =Complétude!C51-'Sécurité précaire_Publique'!O50 -> -656 | D51: =Complétude!D51 -> 0 | E51: =IFERROR(D51/C51*100,"") -> 0 | F51: =Complétude!F51-'Sécurité précaire_Privee'!O50 -> -12 | G51: =Complétude!G51 -> 0 | H51: =IFERROR(G51/F51*100,"") -> 0 | I51: =C51+F51 -> -668 | J51: =D51+G51 -> 0 | K51: =IFERROR(J51/I51*100,"") -> 0 | L51: =Complétude!L51 -> 0 | M51: =IFERROR(L51/I51*100,"") -> 0
B52: CHR Dori | C52: =Complétude!C52-'Sécurité précaire_Publique'!O51 -> 0 | D52: =Complétude!D52 -> 0 | E52: =IFERROR(D52/C52*100,"") | F52: =Complétude!F52-'Sécurité précaire_Privee'!O51 -> 0 | G52: =Complétude!G52 -> 0 | H52: =IFERROR(G52/F52*100,"") | I52: =C52+F52 -> 0 | J52: =D52+G52 -> 0 | K52: =IFERROR(J52/I52*100,"") | L52: =Complétude!L52 -> 0 | M52: =IFERROR(L52/I52*100,"")
B53: DS Dori | C53: =Complétude!C53-'Sécurité précaire_Publique'!O52 -> -276 | D53: =Complétude!D53 -> 0 | E53: =IFERROR(D53/C53*100,"") -> 0 | F53: =Complétude!F53-'Sécurité précaire_Privee'!O52 -> 0 | G53: =Complétude!G53 -> 0 | H53: =IFERROR(G53/F53*100,"") | I53: =C53+F53 -> -276 | J53: =D53+G53 -> 0 | K53: =IFERROR(J53/I53*100,"") -> 0 | L53: =Complétude!L53 -> 0 | M53: =IFERROR(L53/I53*100,"") -> 0
B54: DS Gorom-Gorom | C54: =Complétude!C54-'Sécurité précaire_Publique'!O53 -> -200 | D54: =Complétude!D54 -> 0 | E54: =IFERROR(D54/C54*100,"") -> 0 | F54: =Complétude!F54-'Sécurité précaire_Privee'!O53 -> 0 | G54: =Complétude!G54 -> 0 | H54: =IFERROR(G54/F54*100,"") | I54: =C54+F54 -> -200 | J54: =D54+G54 -> 0 | K54: =IFERROR(J54/I54*100,"") -> 0 | L54: =Complétude!L54 -> 0 | M54: =IFERROR(L54/I54*100,"") -> 0
B55: DS Sebba | C55: =Complétude!C55-'Sécurité précaire_Publique'!O54 -> -180 | D55: =Complétude!D55 -> 0 | E55: =IFERROR(D55/C55*100,"") -> 0 | F55: =Complétude!F55-'Sécurité précaire_Privee'!O54 -> -12 | G55: =Complétude!G55 -> 0 | H55: =IFERROR(G55/F55*100,"") -> 0 | I55: =C55+F55 -> -192 | J55: =D55+G55 -> 0 | K55: =IFERROR(J55/I55*100,"") -> 0 | L55: =Complétude!L55 -> 0 | M55: =IFERROR(L55/I55*100,"") -> 0
A56: Nakambé | C56: =Complétude!C56-'Sécurité précaire_Publique'!O55 -> -297 | D56: =Complétude!D56 -> 0 | E56: =IFERROR(D56/C56*100,"") -> 0 | F56: =Complétude!F56-'Sécurité précaire_Privee'!O55 -> 0 | G56: =Complétude!G56 -> 0 | H56: =IFERROR(G56/F56*100,"") | I56: =C56+F56 -> -297 | J56: =D56+G56 -> 0 | K56: =IFERROR(J56/I56*100,"") -> 0 | L56: =Complétude!L56 -> 0 | M56: =IFERROR(L56/I56*100,"") -> 0
B57: CHR Tenkodogo | C57: =Complétude!C57-'Sécurité précaire_Publique'!O56 -> 0 | D57: =Complétude!D57 -> 0 | E57: =IFERROR(D57/C57*100,"") | F57: =Complétude!F57-'Sécurité précaire_Privee'!O56 -> 0 | G57: =Complétude!G57 -> 0 | H57: =IFERROR(G57/F57*100,"") | I57: =C57+F57 -> 0 | J57: =D57+G57 -> 0 | K57: =IFERROR(J57/I57*100,"") | L57: =Complétude!L57 -> 0 | M57: =IFERROR(L57/I57*100,"")
B58: DS Bittou | C58: =Complétude!C58-'Sécurité précaire_Publique'!O57 -> -36 | D58: =Complétude!D58 -> 0 | E58: =IFERROR(D58/C58*100,"") -> 0 | F58: =Complétude!F58-'Sécurité précaire_Privee'!O57 -> 0 | G58: =Complétude!G58 -> 0 | H58: =IFERROR(G58/F58*100,"") | I58: =C58+F58 -> -36 | J58: =D58+G58 -> 0 | K58: =IFERROR(J58/I58*100,"") -> 0 | L58: =Complétude!L58 -> 0 | M58: =IFERROR(L58/I58*100,"") -> 0
B59: DS Garango | C59: =Complétude!C59-'Sécurité précaire_Publique'!O58 -> 0 | D59: =Complétude!D59 -> 0 | E59: =IFERROR(D59/C59*100,"") | F59: =Complétude!F59-'Sécurité précaire_Privee'!O58 -> 0 | G59: =Complétude!G59 -> 0 | H59: =IFERROR(G59/F59*100,"") | I59: =C59+F59 -> 0 | J59: =D59+G59 -> 0 | K59: =IFERROR(J59/I59*100,"") | L59: =Complétude!L59 -> 0 | M59: =IFERROR(L59/I59*100,"")
B60: DS Koupéla | C60: =Complétude!C60-'Sécurité précaire_Publique'!O59 -> 0 | D60: =Complétude!D60 -> 0 | E60: =IFERROR(D60/C60*100,"") | F60: =Complétude!F60-'Sécurité précaire_Privee'!O59 -> 0 | G60: =Complétude!G60 -> 0 | H60: =IFERROR(G60/F60*100,"") | I60: =C60+F60 -> 0 | J60: =D60+G60 -> 0 | K60: =IFERROR(J60/I60*100,"") | L60: =Complétude!L60 -> 0 | M60: =IFERROR(L60/I60*100,"")
B61: DS Ouargaye | C61: =Complétude!C61-'Sécurité précaire_Publique'!O60 -> -244 | D61: =Complétude!D61 -> 0 | E61: =IFERROR(D61/C61*100,"") -> 0 | F61: =Complétude!F61-'Sécurité précaire_Privee'!O60 -> 0 | G61: =Complétude!G61 -> 0 | H61: =IFERROR(G61/F61*100,"") | I61: =C61+F61 -> -244 | J61: =D61+G61 -> 0 | K61: =IFERROR(J61/I61*100,"") -> 0 | L61: =Complétude!L61 -> 0 | M61: =IFERROR(L61/I61*100,"") -> 0
B62: DS Pouytenga | C62: =Complétude!C62-'Sécurité précaire_Publique'!O61 -> 0 | D62: =Complétude!D62 -> 0 | E62: =IFERROR(D62/C62*100,"") | F62: =Complétude!F62-'Sécurité précaire_Privee'!O61 -> 0 | G62: =Complétude!G62 -> 0 | H62: =IFERROR(G62/F62*100,"") | I62: =C62+F62 -> 0 | J62: =D62+G62 -> 0 | K62: =IFERROR(J62/I62*100,"") | L62: =Complétude!L62 -> 0 | M62: =IFERROR(L62/I62*100,"")
B63: DS Tenkodogo | C63: =Complétude!C63-'Sécurité précaire_Publique'!O62 -> -17 | D63: =Complétude!D63 -> 0 | E63: =IFERROR(D63/C63*100,"") -> 0 | F63: =Complétude!F63-'Sécurité précaire_Privee'!O62 -> 0 | G63: =Complétude!G63 -> 0 | H63: =IFERROR(G63/F63*100,"") | I63: =C63+F63 -> -17 | J63: =D63+G63 -> 0 | K63: =IFERROR(J63/I63*100,"") -> 0 | L63: =Complétude!L63 -> 0 | M63: =IFERROR(L63/I63*100,"") -> 0
B64: DS Zabré | C64: =Complétude!C64-'Sécurité précaire_Publique'!O63 -> 0 | D64: =Complétude!D64 -> 0 | E64: =IFERROR(D64/C64*100,"") | F64: =Complétude!F64-'Sécurité précaire_Privee'!O63 -> 0 | G64: =Complétude!G64 -> 0 | H64: =IFERROR(G64/F64*100,"") | I64: =C64+F64 -> 0 | J64: =D64+G64 -> 0 | K64: =IFERROR(J64/I64*100,"") | L64: =Complétude!L64 -> 0 | M64: =IFERROR(L64/I64*100,"")
A65: Nando | C65: =Complétude!C65-'Sécurité précaire_Publique'!O64 -> 0 | D65: =Complétude!D65 -> 0 | E65: =IFERROR(D65/C65*100,"") | F65: =Complétude!F65-'Sécurité précaire_Privee'!O64 -> 0 | G65: =Complétude!G65 -> 0 | H65: =IFERROR(G65/F65*100,"") | I65: =C65+F65 -> 0 | J65: =D65+G65 -> 0 | K65: =IFERROR(J65/I65*100,"") | L65: =Complétude!L65 -> 0 | M65: =IFERROR(L65/I65*100,"")
B66: CHR Koudougou | C66: =Complétude!C66-'Sécurité précaire_Publique'!O65 -> 0 | D66: =Complétude!D66 -> 0 | E66: =IFERROR(D66/C66*100,"") | F66: =Complétude!F66-'Sécurité précaire_Privee'!O65 -> 0 | G66: =Complétude!G66 -> 0 | H66: =IFERROR(G66/F66*100,"") | I66: =C66+F66 -> 0 | J66: =D66+G66 -> 0 | K66: =IFERROR(J66/I66*100,"") | L66: =Complétude!L66 -> 0 | M66: =IFERROR(L66/I66*100,"")
B67: DS Koudougou | C67: =Complétude!C67-'Sécurité précaire_Publique'!O66 -> 0 | D67: =Complétude!D67 -> 0 | E67: =IFERROR(D67/C67*100,"") | F67: =Complétude!F67-'Sécurité précaire_Privee'!O66 -> 0 | G67: =Complétude!G67 -> 0 | H67: =IFERROR(G67/F67*100,"") | I67: =C67+F67 -> 0 | J67: =D67+G67 -> 0 | K67: =IFERROR(J67/I67*100,"") | L67: =Complétude!L67 -> 0 | M67: =IFERROR(L67/I67*100,"")
B68: DS Léo | C68: =Complétude!C68-'Sécurité précaire_Publique'!O67 -> 0 | D68: =Complétude!D68 -> 0 | E68: =IFERROR(D68/C68*100,"") | F68: =Complétude!F68-'Sécurité précaire_Privee'!O67 -> 0 | G68: =Complétude!G68 -> 0 | H68: =IFERROR(G68/F68*100,"") | I68: =C68+F68 -> 0 | J68: =D68+G68 -> 0 | K68: =IFERROR(J68/I68*100,"") | L68: =Complétude!L68 -> 0 | M68: =IFERROR(L68/I68*100,"")
B69: DS Nanoro | C69: =Complétude!C69-'Sécurité précaire_Publique'!O68 -> 0 | D69: =Complétude!D69 -> 0 | E69: =IFERROR(D69/C69*100,"") | F69: =Complétude!F69-'Sécurité précaire_Privee'!O68 -> 0 | G69: =Complétude!G69 -> 0 | H69: =IFERROR(G69/F69*100,"") | I69: =C69+F69 -> 0 | J69: =D69+G69 -> 0 | K69: =IFERROR(J69/I69*100,"") | L69: =Complétude!L69 -> 0 | M69: =IFERROR(L69/I69*100,"")
B70: DS Réo | C70: =Complétude!C70-'Sécurité précaire_Publique'!O69 -> 0 | D70: =Complétude!D70 -> 0 | E70: =IFERROR(D70/C70*100,"") | F70: =Complétude!F70-'Sécurité précaire_Privee'!O69 -> 0 | G70: =Complétude!G70 -> 0 | H70: =IFERROR(G70/F70*100,"") | I70: =C70+F70 -> 0 | J70: =D70+G70 -> 0 | K70: =IFERROR(J70/I70*100,"") | L70: =Complétude!L70 -> 0 | M70: =IFERROR(L70/I70*100,"")
B71: DS Sabou | C71: =Complétude!C71-'Sécurité précaire_Publique'!O70 -> 0 | D71: =Complétude!D71 -> 0 | E71: =IFERROR(D71/C71*100,"") | F71: =Complétude!F71-'Sécurité précaire_Privee'!O70 -> 0 | G71: =Complétude!G71 -> 0 | H71: =IFERROR(G71/F71*100,"") | I71: =C71+F71 -> 0 | J71: =D71+G71 -> 0 | K71: =IFERROR(J71/I71*100,"") | L71: =Complétude!L71 -> 0 | M71: =IFERROR(L71/I71*100,"")
B72: DS Sapouy | C72: =Complétude!C72-'Sécurité précaire_Publique'!O71 -> 0 | D72: =Complétude!D72 -> 0 | E72: =IFERROR(D72/C72*100,"") | F72: =Complétude!F72-'Sécurité précaire_Privee'!O71 -> 0 | G72: =Complétude!G72 -> 0 | H72: =IFERROR(G72/F72*100,"") | I72: =C72+F72 -> 0 | J72: =D72+G72 -> 0 | K72: =IFERROR(J72/I72*100,"") | L72: =Complétude!L72 -> 0 | M72: =IFERROR(L72/I72*100,"")
B73: DS Tenado | C73: =Complétude!C73-'Sécurité précaire_Publique'!O72 -> 0 | D73: =Complétude!D73 -> 0 | E73: =IFERROR(D73/C73*100,"") | F73: =Complétude!F73-'Sécurité précaire_Privee'!O72 -> 0 | G73: =Complétude!G73 -> 0 | H73: =IFERROR(G73/F73*100,"") | I73: =C73+F73 -> 0 | J73: =D73+G73 -> 0 | K73: =IFERROR(J73/I73*100,"") | L73: =Complétude!L73 -> 0 | M73: =IFERROR(L73/I73*100,"")
A74: Nazinon | C74: =Complétude!C74-'Sécurité précaire_Publique'!O73 -> 0 | D74: =Complétude!D74 -> 0 | E74: =IFERROR(D74/C74*100,"") | F74: =Complétude!F74-'Sécurité précaire_Privee'!O73 -> 0 | G74: =Complétude!G74 -> 0 | H74: =IFERROR(G74/F74*100,"") | I74: =C74+F74 -> 0 | J74: =D74+G74 -> 0 | K74: =IFERROR(J74/I74*100,"") | L74: =Complétude!L74 -> 0 | M74: =IFERROR(L74/I74*100,"")
B75: CHR Manga | C75: =Complétude!C75-'Sécurité précaire_Publique'!O74 -> 0 | D75: =Complétude!D75 -> 0 | E75: =IFERROR(D75/C75*100,"") | F75: =Complétude!F75-'Sécurité précaire_Privee'!O74 -> 0 | G75: =Complétude!G75 -> 0 | H75: =IFERROR(G75/F75*100,"") | I75: =C75+F75 -> 0 | J75: =D75+G75 -> 0 | K75: =IFERROR(J75/I75*100,"") | L75: =Complétude!L75 -> 0 | M75: =IFERROR(L75/I75*100,"")
B76: DS Kombissiri | C76: =Complétude!C76-'Sécurité précaire_Publique'!O75 -> 0 | D76: =Complétude!D76 -> 0 | E76: =IFERROR(D76/C76*100,"") | F76: =Complétude!F76-'Sécurité précaire_Privee'!O75 -> 0 | G76: =Complétude!G76 -> 0 | H76: =IFERROR(G76/F76*100,"") | I76: =C76+F76 -> 0 | J76: =D76+G76 -> 0 | K76: =IFERROR(J76/I76*100,"") | L76: =Complétude!L76 -> 0 | M76: =IFERROR(L76/I76*100,"")
B77: DS Manga | C77: =Complétude!C77-'Sécurité précaire_Publique'!O76 -> 0 | D77: =Complétude!D77 -> 0 | E77: =IFERROR(D77/C77*100,"") | F77: =Complétude!F77-'Sécurité précaire_Privee'!O76 -> 0 | G77: =Complétude!G77 -> 0 | H77: =IFERROR(G77/F77*100,"") | I77: =C77+F77 -> 0 | J77: =D77+G77 -> 0 | K77: =IFERROR(J77/I77*100,"") | L77: =Complétude!L77 -> 0 | M77: =IFERROR(L77/I77*100,"")
B78: DS Po | C78: =Complétude!C78-'Sécurité précaire_Publique'!O77 -> 0 | D78: =Complétude!D78 -> 0 | E78: =IFERROR(D78/C78*100,"") | F78: =Complétude!F78-'Sécurité précaire_Privee'!O77 -> 0 | G78: =Complétude!G78 -> 0 | H78: =IFERROR(G78/F78*100,"") | I78: =C78+F78 -> 0 | J78: =D78+G78 -> 0 | K78: =IFERROR(J78/I78*100,"") | L78: =Complétude!L78 -> 0 | M78: =IFERROR(L78/I78*100,"")
B79: DS Sapone | C79: =Complétude!C79-'Sécurité précaire_Publique'!O78 -> 0 | D79: =Complétude!D79 -> 0 | E79: =IFERROR(D79/C79*100,"") | F79: =Complétude!F79-'Sécurité précaire_Privee'!O78 -> 0 | G79: =Complétude!G79 -> 0 | H79: =IFERROR(G79/F79*100,"") | I79: =C79+F79 -> 0 | J79: =D79+G79 -> 0 | K79: =IFERROR(J79/I79*100,"") | L79: =Complétude!L79 -> 0 | M79: =IFERROR(L79/I79*100,"")
A80: Oubri | C80: =Complétude!C80-'Sécurité précaire_Publique'!O79 -> 0 | D80: =Complétude!D80 -> 0 | E80: =IFERROR(D80/C80*100,"") | F80: =Complétude!F80-'Sécurité précaire_Privee'!O79 -> 0 | G80: =Complétude!G80 -> 0 | H80: =IFERROR(G80/F80*100,"") | I80: =C80+F80 -> 0 | J80: =D80+G80 -> 0 | K80: =IFERROR(J80/I80*100,"") | L80: =Complétude!L80 -> 0 | M80: =IFERROR(L80/I80*100,"")
B81: CHR Ziniaré | C81: =Complétude!C81-'Sécurité précaire_Publique'!O80 -> 0 | D81: =Complétude!D81 -> 0 | E81: =IFERROR(D81/C81*100,"") | F81: =Complétude!F81-'Sécurité précaire_Privee'!O80 -> 0 | G81: =Complétude!G81 -> 0 | H81: =IFERROR(G81/F81*100,"") | I81: =C81+F81 -> 0 | J81: =D81+G81 -> 0 | K81: =IFERROR(J81/I81*100,"") | L81: =Complétude!L81 -> 0 | M81: =IFERROR(L81/I81*100,"")
B82: DS Boussé | C82: =Complétude!C82-'Sécurité précaire_Publique'!O81 -> 0 | D82: =Complétude!D82 -> 0 | E82: =IFERROR(D82/C82*100,"") | F82: =Complétude!F82-'Sécurité précaire_Privee'!O81 -> 0 | G82: =Complétude!G82 -> 0 | H82: =IFERROR(G82/F82*100,"") | I82: =C82+F82 -> 0 | J82: =D82+G82 -> 0 | K82: =IFERROR(J82/I82*100,"") | L82: =Complétude!L82 -> 0 | M82: =IFERROR(L82/I82*100,"")
B83: DS Ziniaré | C83: =Complétude!C83-'Sécurité précaire_Publique'!O82 -> 0 | D83: =Complétude!D83 -> 0 | E83: =IFERROR(D83/C83*100,"") | F83: =Complétude!F83-'Sécurité précaire_Privee'!O82 -> 0 | G83: =Complétude!G83 -> 0 | H83: =IFERROR(G83/F83*100,"") | I83: =C83+F83 -> 0 | J83: =D83+G83 -> 0 | K83: =IFERROR(J83/I83*100,"") | L83: =Complétude!L83 -> 0 | M83: =IFERROR(L83/I83*100,"")
B84: DS Zorgho | C84: =Complétude!C84-'Sécurité précaire_Publique'!O83 -> 0 | D84: =Complétude!D84 -> 0 | E84: =IFERROR(D84/C84*100,"") | F84: =Complétude!F84-'Sécurité précaire_Privee'!O83 -> 0 | G84: =Complétude!G84 -> 0 | H84: =IFERROR(G84/F84*100,"") | I84: =C84+F84 -> 0 | J84: =D84+G84 -> 0 | K84: =IFERROR(J84/I84*100,"") | L84: =Complétude!L84 -> 0 | M84: =IFERROR(L84/I84*100,"")
A85: Sirba | C85: =Complétude!C85-'Sécurité précaire_Publique'!O84 -> -331 | D85: =Complétude!D85 -> 0 | E85: =IFERROR(D85/C85*100,"") -> 0 | F85: =Complétude!F85-'Sécurité précaire_Privee'!O84 -> -9 | G85: =Complétude!G85 -> 0 | H85: =IFERROR(G85/F85*100,"") -> 0 | I85: =C85+F85 -> -340 | J85: =D85+G85 -> 0 | K85: =IFERROR(J85/I85*100,"") -> 0 | L85: =Complétude!L85 -> 0 | M85: =IFERROR(L85/I85*100,"") -> 0
B86: DS Bogande | C86: =Complétude!C86-'Sécurité précaire_Publique'!O85 -> -102 | D86: =Complétude!D86 -> 0 | E86: =IFERROR(D86/C86*100,"") -> 0 | F86: =Complétude!F86-'Sécurité précaire_Privee'!O85 -> -9 | G86: =Complétude!G86 -> 0 | H86: =IFERROR(G86/F86*100,"") -> 0 | I86: =C86+F86 -> -111 | J86: =D86+G86 -> 0 | K86: =IFERROR(J86/I86*100,"") -> 0 | L86: =Complétude!L86 -> 0 | M86: =IFERROR(L86/I86*100,"") -> 0
B87: DS Gayeri | C87: =Complétude!C87-'Sécurité précaire_Publique'!O86 -> -83 | D87: =Complétude!D87 -> 0 | E87: =IFERROR(D87/C87*100,"") -> 0 | F87: =Complétude!F87-'Sécurité précaire_Privee'!O86 -> 0 | G87: =Complétude!G87 -> 0 | H87: =IFERROR(G87/F87*100,"") | I87: =C87+F87 -> -83 | J87: =D87+G87 -> 0 | K87: =IFERROR(J87/I87*100,"") -> 0 | L87: =Complétude!L87 -> 0 | M87: =IFERROR(L87/I87*100,"") -> 0
B88: DS Manni | C88: =Complétude!C88-'Sécurité précaire_Publique'!O87 -> -146 | D88: =Complétude!D88 -> 0 | E88: =IFERROR(D88/C88*100,"") -> 0 | F88: =Complétude!F88-'Sécurité précaire_Privee'!O87 -> 0 | G88: =Complétude!G88 -> 0 | H88: =IFERROR(G88/F88*100,"") | I88: =C88+F88 -> -146 | J88: =D88+G88 -> 0 | K88: =IFERROR(J88/I88*100,"") -> 0 | L88: =Complétude!L88 -> 0 | M88: =IFERROR(L88/I88*100,"") -> 0
A89: Soum | C89: =Complétude!C89-'Sécurité précaire_Publique'!O88 -> -432 | D89: =Complétude!D89 -> 0 | E89: =IFERROR(D89/C89*100,"") -> 0 | F89: =Complétude!F89-'Sécurité précaire_Privee'!O88 -> -48 | G89: =Complétude!G89 -> 0 | H89: =IFERROR(G89/F89*100,"") -> 0 | I89: =C89+F89 -> -480 | J89: =D89+G89 -> 0 | K89: =IFERROR(J89/I89*100,"") -> 0 | L89: =Complétude!L89 -> 0 | M89: =IFERROR(L89/I89*100,"") -> 0
B90: DS Djibo | C90: =Complétude!C90-'Sécurité précaire_Publique'!O89 -> -432 | D90: =Complétude!D90 -> 0 | E90: =IFERROR(D90/C90*100,"") -> 0 | F90: =Complétude!F90-'Sécurité précaire_Privee'!O89 -> -48 | G90: =Complétude!G90 -> 0 | H90: =IFERROR(G90/F90*100,"") -> 0 | I90: =C90+F90 -> -480 | J90: =D90+G90 -> 0 | K90: =IFERROR(J90/I90*100,"") -> 0 | L90: =Complétude!L90 -> 0 | M90: =IFERROR(L90/I90*100,"") -> 0
A91: Sourou | C91: =Complétude!C91-'Sécurité précaire_Publique'!O90 -> -699 | D91: =Complétude!D91 -> 0 | E91: =IFERROR(D91/C91*100,"") -> 0 | F91: =Complétude!F91-'Sécurité précaire_Privee'!O90 -> 0 | G91: =Complétude!G91 -> 0 | H91: =IFERROR(G91/F91*100,"") | I91: =C91+F91 -> -699 | J91: =D91+G91 -> 0 | K91: =IFERROR(J91/I91*100,"") -> 0 | L91: =Complétude!L91 -> 0 | M91: =IFERROR(L91/I91*100,"") -> 0
B92: DS Nouna | C92: =Complétude!C92-'Sécurité précaire_Publique'!O91 -> -233 | D92: =Complétude!D92 -> 0 | E92: =IFERROR(D92/C92*100,"") -> 0 | F92: =Complétude!F92-'Sécurité précaire_Privee'!O91 -> 0 | G92: =Complétude!G92 -> 0 | H92: =IFERROR(G92/F92*100,"") | I92: =C92+F92 -> -233 | J92: =D92+G92 -> 0 | K92: =IFERROR(J92/I92*100,"") -> 0 | L92: =Complétude!L92 -> 0 | M92: =IFERROR(L92/I92*100,"") -> 0
B93: DS Toma | C93: =Complétude!C93-'Sécurité précaire_Publique'!O92 -> -135 | D93: =Complétude!D93 -> 0 | E93: =IFERROR(D93/C93*100,"") -> 0 | F93: =Complétude!F93-'Sécurité précaire_Privee'!O92 -> 0 | G93: =Complétude!G93 -> 0 | H93: =IFERROR(G93/F93*100,"") | I93: =C93+F93 -> -135 | J93: =D93+G93 -> 0 | K93: =IFERROR(J93/I93*100,"") -> 0 | L93: =Complétude!L93 -> 0 | M93: =IFERROR(L93/I93*100,"") -> 0
B94: DS Tougan | C94: =Complétude!C94-'Sécurité précaire_Publique'!O93 -> -331 | D94: =Complétude!D94 -> 0 | E94: =IFERROR(D94/C94*100,"") -> 0 | F94: =Complétude!F94-'Sécurité précaire_Privee'!O93 -> 0 | G94: =Complétude!G94 -> 0 | H94: =IFERROR(G94/F94*100,"") | I94: =C94+F94 -> -331 | J94: =D94+G94 -> 0 | K94: =IFERROR(J94/I94*100,"") -> 0 | L94: =Complétude!L94 -> 0 | M94: =IFERROR(L94/I94*100,"") -> 0
A95: Tannounyan | C95: =Complétude!C95-'Sécurité précaire_Publique'!O94 -> -2 | D95: =Complétude!D95 -> 0 | E95: =IFERROR(D95/C95*100,"") -> 0 | F95: =Complétude!F95-'Sécurité précaire_Privee'!O94 -> 0 | G95: =Complétude!G95 -> 0 | H95: =IFERROR(G95/F95*100,"") | I95: =C95+F95 -> -2 | J95: =D95+G95 -> 0 | K95: =IFERROR(J95/I95*100,"") -> 0 | L95: =Complétude!L95 -> 0 | M95: =IFERROR(L95/I95*100,"") -> 0
B96: CHR Banfora | C96: =Complétude!C96-'Sécurité précaire_Publique'!O95 -> 0 | D96: =Complétude!D96 -> 0 | E96: =IFERROR(D96/C96*100,"") | F96: =Complétude!F96-'Sécurité précaire_Privee'!O95 -> 0 | G96: =Complétude!G96 -> 0 | H96: =IFERROR(G96/F96*100,"") | I96: =C96+F96 -> 0 | J96: =D96+G96 -> 0 | K96: =IFERROR(J96/I96*100,"") | L96: =Complétude!L96 -> 0 | M96: =IFERROR(L96/I96*100,"")
B97: DS Banfora | C97: =Complétude!C97-'Sécurité précaire_Publique'!O96 -> 0 | D97: =Complétude!D97 -> 0 | E97: =IFERROR(D97/C97*100,"") | F97: =Complétude!F97-'Sécurité précaire_Privee'!O96 -> 0 | G97: =Complétude!G97 -> 0 | H97: =IFERROR(G97/F97*100,"") | I97: =C97+F97 -> 0 | J97: =D97+G97 -> 0 | K97: =IFERROR(J97/I97*100,"") | L97: =Complétude!L97 -> 0 | M97: =IFERROR(L97/I97*100,"")
B98: DS Mangodara | C98: =Complétude!C98-'Sécurité précaire_Publique'!O97 -> -2 | D98: =Complétude!D98 -> 0 | E98: =IFERROR(D98/C98*100,"") -> 0 | F98: =Complétude!F98-'Sécurité précaire_Privee'!O97 -> 0 | G98: =Complétude!G98 -> 0 | H98: =IFERROR(G98/F98*100,"") | I98: =C98+F98 -> -2 | J98: =D98+G98 -> 0 | K98: =IFERROR(J98/I98*100,"") -> 0 | L98: =Complétude!L98 -> 0 | M98: =IFERROR(L98/I98*100,"") -> 0
B99: DS Sindou | C99: =Complétude!C99-'Sécurité précaire_Publique'!O98 -> 0 | D99: =Complétude!D99 -> 0 | E99: =IFERROR(D99/C99*100,"") | F99: =Complétude!F99-'Sécurité précaire_Privee'!O98 -> 0 | G99: =Complétude!G99 -> 0 | H99: =IFERROR(G99/F99*100,"") | I99: =C99+F99 -> 0 | J99: =D99+G99 -> 0 | K99: =IFERROR(J99/I99*100,"") | L99: =Complétude!L99 -> 0 | M99: =IFERROR(L99/I99*100,"")
A100: Tapoa | C100: =Complétude!C100-'Sécurité précaire_Publique'!O99 -> -321 | D100: =Complétude!D100 -> 0 | E100: =IFERROR(D100/C100*100,"") -> 0 | F100: =Complétude!F100-'Sécurité précaire_Privee'!O99 -> -30 | G100: =Complétude!G100 -> 0 | H100: =IFERROR(G100/F100*100,"") -> 0 | I100: =C100+F100 -> -351 | J100: =D100+G100 -> 0 | K100: =IFERROR(J100/I100*100,"") -> 0 | L100: =Complétude!L100 -> 0 | M100: =IFERROR(L100/I100*100,"") -> 0
...

Sheet Partie 2
A1: 2. ADMINISTRATION ET GESTION
A2: Bilan physique et financier des plans d'ations | B2: pp 38 - 44
A3: Disponibilité des MEG dans les formations sanitaires | B3: pp 45 - 46
A4: Disponibilité des MEG traceurs dans les DRD par régions | B4: pp 47 - 49
A5: Ruptures de stock des 25 medicaments traceurs dans les DMEG témoins/région | B5: p 50
A6: Quleques résultats de la gratuité des soins | B6: pp 51 - 52

Sheet Bilan PA _1
A1: Tableau 2.01: Bilan physique et financier par effet du PNDS 2024
A2: Programme | B2: Nbre de produits | C2: Activités programmées | D2: Activités entièrement réalisées (%) | E2: Bilan financier
E3: Coût planifié | F3: Montant mobilisé | G3: Montant alloué | H3: Montant dépensé | I3: Taux d'absorption (%)
A4: EFFET 1 | I4: =IFERROR(H4/G4*100,"")
A5: EFFET 2 | I5: =IFERROR(H5/G5*100,"")
A6: EFFET 3 | I6: =IFERROR(H6/G6*100,"")
A7: EFFET 4 | I7: =IFERROR(H7/G7*100,"")
A8: EFFET 5 | I8: =IFERROR(H8/G8*100,"")
A9: Total général | I9: =IFERROR(H9/G9*100,"")
A10: source:DPPSE
A12: Tableau 2.02: Bilan physique et financier par programme budgétaire du PNDS 2025
A13: Programme Budgétaire | C13: Activités programmées | D13: Activités entièrement réalisées (%) | E13: Bilan financier
E14: Coût planifié | F14: Montant mobilisé | G14: Montant alloué | H14: Montant dépensé | I14: Taux d'absorption (%)
A15: Programme budgétaire « Accès aux produits de santé » (146) | I15: =IFERROR(H15/G15*100,"")
A16: Programme budgétaire « Offre de soins » (055) | I16: =IFERROR(H16/G16*100,"")
A17: Programme budgétaire « Pilotage et soutien des services du MSHP » (057) | I17: =IFERROR(H17/G17*100,"")
A18: Programme budgétaire « Santé publiquee » (056) | I18: =IFERROR(H18/G18*100,"")
A19: Total général | I19: =IFERROR(H19/G19*100,"")
A20: source:DPPSE

Sheet Bilan PA _2
A1: Tableau 2.03: Bilan physique et financier par structure 2025
A2: Structure | B2: Activités programmées | C2: Activités entièrement réalisées | D2: Activités partiellement réalisées | E2: Bilan financier
E3: Coût planifié | F3: Montant mobilisé | G3: Montant alloué | H3: Montant dépensé | I3: Taux d'absorption (%)
A4: BOUCLE DU MOUHOUN | I4: =IF(G4=0,"",H4/G4*100)
A5: CHR Dédougou | I5: =IF(G5=0,"",H5/G5*100)
A6: DRS BMHN | I6: =IF(G6=0,"",H6/G6*100)
A7: DS Boromo | I7: =IF(G7=0,"",H7/G7*100)
A8: DS Dédougou | I8: =IF(G8=0,"",H8/G8*100)
A9: DS Nouna | I9: =IF(G9=0,"",H9/G9*100)
A10: DS Solenzo | I10: =IF(G10=0,"",H10/G10*100)
A11: DS Toma | I11: =IF(G11=0,"",H11/G11*100)
A12: DS Tougan | I12: =IF(G12=0,"",H12/G12*100)
A13: CASCADES | I13: =IF(G13=0,"",H13/G13*100)
A14: CHR BANFORA | I14: =IF(G14=0,"",H14/G14*100)
A15: DRS Cascades | I15: =IF(G15=0,"",H15/G15*100)
... A159: Total général | I159: =IF(G159=0,"",H159/G159*100)
A160: Source: DPPSE

Sheet Rupture_DMEG
A1: Tableau 2.04: Disponibilité des médicament traceurs dans les formations sanitaires publiques en 2025
A2: Régions/districts | C2: Nombre de DMEG | D2: Nbre de DMEG n'ayant pas connu de rupture de médicaments traceurs | E2: % de DMEG n'ayant pas connu de rupture
A3: Bankui | E3: =IF(C3=0,"",D3/C3*100)
B4: DS Boromo | E4: =IF(C4=0,"",D4/C4*100)
B5: DS Dedougou | E5: =IF(C5=0,"",D5/C5*100)
B6: DS Solenzo | E6: =IF(C6=0,"",D6/C6*100)
A7: Djoro | E7: =IF(C7=0,"",D7/C7*100)
B8: DS Batié | E8: =IF(C8=0,"",D8/C8*100)
B9: DS Dano | E9: =IF(C9=0,"",D9/C9*100)
B10: DS Diébougou | E10: =IF(C10=0,"",D10/C10*100)
B11: DS Gaoua | E11: =IF(C11=0,"",D11/C11*100)
B12: DS Kampti | E12: =IF(C12=0,"",D12/C12*100)
A13: Goulmou | E13: =IF(C13=0,"",D13/C13*100)
B14: DS Fada | E14: =IF(C14=0,"",D14/C14*100)
B15: DS Pama | E15: =IF(C15=0,"",D15/C15*100)
A16: Guiriko | E16: =IF(C16=0,"",D16/C16*100)
B17: DS Dafra | E17: =IF(C17=0,"",D17/C17*100)
B18: DS Dande | E18: =IF(C18=0,"",D18/C18*100)
B19: DS Do | E19: =IF(C19=0,"",D19/C19*100)
B20: DS Hounde | E20: =IF(C20=0,"",D20/C20*100)
B21: DS Karangasso Vigue | E21: =IF(C21=0,"",D21/C21*100)
B22: DS Léna | E22: =IF(C22=0,"",D22/C22*100)
B23: DS N'Dorola | E23: =IF(C23=0,"",D23/C23*100)
B24: DS Orodara | E24: =IF(C24=0,"",D24/C24*100)
A25: Kadiogo | E25: =IF(C25=0,"",D25/C25*100)
B26: DS Baskuy | E26: =IF(C26=0,"",D26/C26*100)
B27: DS Bogodogo | E27: =IF(C27=0,"",D27/C27*100)
B28: DS Boulmiougou | E28: =IF(C28=0,"",D28/C28*100)
B29: DS Nongr-Massom | E29: =IF(C29=0,"",D29/C29*100)
B30: DS Sig-Noghin | E30: =IF(C30=0,"",D30/C30*100)
A31: Koulsé | E31: =IF(C31=0,"",D31/C31*100)
B32: DS Barsalogho | E32: =IF(C32=0,"",D32/C32*100)
B33: DS Boulsa | E33: =IF(C33=0,"",D33/C33*100)
B34: DS Boussouma | E34: =IF(C34=0,"",D34/C34*100)
B35: DS Kaya | E35: =IF(C35=0,"",D35/C35*100)
B36: DS Kongoussi | E36: =IF(C36=0,"",D36/C36*100)
B37: DS Tougouri | E37: =IF(C37=0,"",D37/C37*100)
A38: Liptako | E38: =IF(C38=0,"",D38/C38*100)
B39: DS Dori | E39: =IF(C39=0,"",D39/C39*100)
B40: DS Gorom-Gorom | E40: =IF(C40=0,"",D40/C40*100)
B41: DS Sebba | E41: =IF(C41=0,"",D41/C41*100)
A42: Nakambé | E42: =IF(C42=0,"",D42/C42*100)
B43: DS Bittou | E43: =IF(C43=0,"",D43/C43*100)
B44: DS Garango | E44: =IF(C44=0,"",D44/C44*100)
B45: DS Koupéla | E45: =IF(C45=0,"",D45/C45*100)
B46: DS Ouargaye | E46: =IF(C46=0,"",D46/C46*100)
B47: DS Pouytenga | E47: =IF(C47=0,"",D47/C47*100)
B48: DS Tenkodogo | E48: =IF(C48=0,"",D48/C48*100)
B49: DS Zabré | E49: =IF(C49=0,"",D49/C49*100)
A50: Nando | E50: =IF(C50=0,"",D50/C50*100)
B51: DS Koudougou | E51: =IF(C51=0,"",D51/C51*100)
B52: DS Léo | E52: =IF(C52=0,"",D52/C52*100)
B53: DS Nanoro | E53: =IF(C53=0,"",D53/C53*100)
B54: DS Réo | E54: =IF(C54=0,"",D54/C54*100)
B55: DS Sabou | E55: =IF(C55=0,"",D55/C55*100)
B56: DS Sapouy | E56: =IF(C56=0,"",D56/C56*100)
B57: DS Tenado | E57: =IF(C57=0,"",D57/C57*100)
A58: Nazinon | E58: =IF(C58=0,"",D58/C58*100)
B59: DS Kombissiri | E59: =IF(C59=0,"",D59/C59*100)
B60: DS Manga | E60: =IF(C60=0,"",D60/C60*100)
B61: DS Po | E61: =IF(C61=0,"",D61/C61*100)
B62: DS Sapone | E62: =IF(C62=0,"",D62/C62*100)
A63: Oubri | E63: =IF(C63=0,"",D63/C63*100)
B64: DS Boussé | E64: =IF(C64=0,"",D64/C64*100)
B65: DS Ziniaré | E65: =IF(C65=0,"",D65/C65*100)
B66: DS Zorgho | E66: =IF(C66=0,"",D66/C66*100)
A67: Sirba | E67: =IF(C67=0,"",D67/C67*100)
B68: DS Bogande | E68: =IF(C68=0,"",D68/C68*100)
B69: DS Gayeri | E69: =IF(C69=0,"",D69/C69*100)
B70: DS Manni | E70: =IF(C70=0,"",D70/C70*100)
A71: Soum | E71: =IF(C71=0,"",D71/C71*100)
B72: DS Djibo | E72: =IF(C72=0,"",D72/C72*100)
A73: Sourou | E73: =IF(C73=0,"",D73/C73*100)
B74: DS Nouna | E74: =IF(C74=0,"",D74/C74*100)
B75: DS Toma | E75: =IF(C75=0,"",D75/C75*100)
B76: DS Tougan | E76: =IF(C76=0,"",D76/C76*100)
A77: Tannounyan | E77: =IF(C77=0,"",D77/C77*100)
B78: DS Banfora | E78: =IF(C78=0,"",D78/C78*100)
B79: DS Mangodara | E79: =IF(C79=0,"",D79/C79*100)
B80: DS Sindou | E80: =IF(C80=0,"",D80/C80*100)
A81: Tapoa | E81: =IF(C81=0,"",D81/C81*100)
B82: DS Diapaga | E82: =IF(C82=0,"",D82/C82*100)
A83: Yaadga | E83: =IF(C83=0,"",D83/C83*100)
B84: DS Gourcy | E84: =IF(C84=0,"",D84/C84*100)
B85: DS Ouahigouya | E85: =IF(C85=0,"",D85/C85*100)
B86: DS Séguénéga | E86: =IF(C86=0,"",D86/C86*100)
B87: DS Thiou | E87: =IF(C87=0,"",D87/C87*100)
B88: DS Titao | E88: =IF(C88=0,"",D88/C88*100)
B89: DS Yako | E89: =IF(C89=0,"",D89/C89*100)
A90: Burkina Faso | E90: =IF(C90=0,"",D90/C90*100)

Sheet Rupture_DRD
A1: Tableau 2.05: Disponibilité des MEG traceurs dans les DRD par régions en 2025
A2: Régions | B2: Nombre de DRD | C2: Nombre de DRD n'ayant pas connu de rupture de médicaments traceurs | D2: % de DRD n'ayant pas connu de rupture
A3: Bankui | D3: =IF(B3=0,"",C3/B3*100)
A4: Djoro | D4: =IF(B4=0,"",C4/B4*100)
A5: Goulmou | D5: =IF(B5=0,"",C5/B5*100)
A6: Guiriko | D6: =IF(B6=0,"",C6/B6*100)
A7: Kadiogo | D7: =IF(B7=0,"",C7/B7*100)
A8: Koulsé | D8: =IF(B8=0,"",C8/B8*100)
A9: Liptako | D9: =IF(B9=0,"",C9/B9*100)
A10: Nakambé | D10: =IF(B10=0,"",C10/B10*100)
A11: Nando | D11: =IF(B11=0,"",C11/B11*100)
A12: Nazinon | D12: =IF(B12=0,"",C12/B12*100)
A13: Oubri | D13: =IF(B13=0,"",C13/B13*100)
A14: Sirba | D14: =IF(B14=0,"",C14/B14*100)
... A20: Burkina Faso | D20: =IF(B20=0,"",C20/B20*100)

Sheet TX rupture mensuel DRD traceurs
A1: Tableau 2.06: Taux (%) de rupture de stock des 50 médicaments traceurs dans les DRD en 2025
A2: Régions/Districts | B2: Janv | C2: fév | D2: mars | E2: Avril | F2: Mai | G2: Juin | H2: Juillet | I2: Août | J2: Sept | K2: Oct | L2: Nov | M2: Déc | N2: Moyenne
A3: Bankui | B3: 20.333333 | C3: 17 | D3: 12.333333 | E3: 14 | F3: 17 | G3: 20.666667 | H3: 14.666667 | I3: 10.666667 | J3: 10.666667 | K3: 10.666667 | L3: 9.6666667 | M3: 11 | N3: =IFERROR(AVERAGE(B3:M3),"") -> 14.055556
A4: Djoro | B4: 23.6 | C4: 22.4 | D4: 22.8 | E4: 30 | F4: 20.8 | G4: 18.4 | H4: 21.6 | I4: 22 | J4: 23.2 | K4: 19.2 | L4: 19.6 | M4: 15.2 | N4: =IFERROR(AVERAGE(B4:M4),"") -> 21.566667
A5: Goulmou | B5: 7.6666667 | C5: 8 | D5: 8.3333333 | E5: 8.6666667 | F5: 6.6666667 | G5: 9 | H5: 12 | I5: 7.3333333 | J5: 7.3333333 | K5: 4 | L5: 9 | M5: 7 | N5: =IFERROR(AVERAGE(B5:M5),"") -> 7.9166667
A6: Guiriko | B6: 12.5 | C6: 12 | D6: 9 | E6: 8.5 | F6: 7.75 | G6: 9.25 | H6: 10.75 | I6: 12 | J6: 10 | K6: 10.5 | L6: 2.3333333 | M6: 10.25 | N6: =IFERROR(AVERAGE(B6:M6),"") -> 9.5694444
A7: Kadiogo | B7: 13.2 | C7: 11.2 | D7: 14.8 | E7: 15.2 | F7: 15.2 | G7: 14.4 | H7: 13.2 | I7: 12 | J7: 6.4 | K7: 13.6 | L7: 14.8 | M7: 11.428571 | N7: =IFERROR(AVERAGE(B7:M7),"") -> 12.952381
A8: Koulsé | B8: 9.3333333 | C8: 10.333333 | D8: 10.333333 | E8: 10 | F8: 11.666667 | G8: 11 | H8: 12.333333 | I8: 14.666667 | J8: 14.666667 | K8: 0.33333333 | L8: 16.333333 | M8: 12.666667 | N8: =IFERROR(AVERAGE(B8:M8),"") -> 11.138889
A9: Liptako | B9: ND | C9: ND | D9: ND | E9: ND | F9: ND | G9: ND | H9: ND | I9: ND | J9: ND | K9: ND | L9: 0 | M9: ND | N9: =IFERROR(AVERAGE(B9:M9),"") -> 0
A10: Nakambé | B10: 16.285714 | C10: 5.7142857 | D10: 12.285714 | E10: 10.571429 | F10: 13.714286 | G10: 13.714286 | H10: 13.142857 | I10: 8.8571429 | J10: 8.8571429 | K10: 6.2857143 | L10: 10.857143 | M10: 11.428571 | N10: =IFERROR(AVERAGE(B10:M10),"") -> 10.97619
A11: Nando | B11: 25.714286 | C11: 20.571429 | D11: 17.428571 | E11: 14.571429 | F11: 15.714286 | G11: 15.142857 | H11: 17.714286 | I11: 16.285714 | J11: 15.714286 | K11: 13.142857 | L11: 10.857143 | M11: 15.428571 | N11: =IFERROR(AVERAGE(B11:M11),"") -> 16.52381
A12: Nazinon | B12: 21.5 | C12: 18 | D12: 9.3333333 | E12: 10.5 | F12: 14.666667 | G12: 12.5 | H12: 9.5 | I12: 13.5 | J12: 11.5 | K12: 8 | L12: 8.5 | M12: 15 | N12: =IFERROR(AVERAGE(B12:M12),"") -> 12.708333
A13: Oubri | B13: 20.666667 | C13: 20 | D13: 16 | E13: 16.666667 | F13: 10.666667 | G13: 11.333333 | H13: 18.666667 | I13: 18.666667 | J13: 22.666667 | K13: 22 | L13: 24 | M13: 24 | N13: =IFERROR(AVERAGE(B13:M13),"") -> 18.777778
A14: Sirba | N14: =IFERROR(AVERAGE(B14:M14),"")
A15: Soum | N15: =IFERROR(AVERAGE(B15:M15),"")
A16: Sourou | N16: =IFERROR(AVERAGE(B16:M16),"")
A17: Tannounyan | B17: 23.333333 | C17: 18.666667 | D17: 26.666667 | E17: 23.333333 | F17: 25.333333 | G17: 21.333333 | H17: 22 | I17: 20.666667 | J17: 21.333333 | K17: 14 | L17: 12.666667 | M17: 9.3333333 | N17: =IFERROR(AVERAGE(B17:M17),"") -> 19.888889
A18: Tapoa | N18: =IFERROR(AVERAGE(B18:M18),"")
A19: Yaadga | B19: 22 | C19: 21.333333 | D19: 17 | E19: 17.333333 | F19: 16.666667 | G19: 17.333333 | H19: 16.333333 | I19: 14.666667 | J19: 17 | K19: 15 | L19: 15 | M19: 19 | N19: =IFERROR(AVERAGE(B19:M19),"") -> 17.388889
A20: Burkina Faso | B20: =AVERAGE(B3:B19) -> 18.011111 | C20: =AVERAGE(C3:C19) -> 15.434921 | D20: =AVERAGE(D3:D19) -> 14.692857 | E20: =AVERAGE(E3:E19) -> 14.945238 | F20: =AVERAGE(F3:F19) -> 14.65377 | G20: =AVERAGE(G3:G19) -> 14.506151 | H20: =AVERAGE(H3:H19) -> 15.158929 | I20: =AVERAGE(I3:I19) -> 14.275794 | ... M20: =AVERAGE(M3:M19) -> 13.477976 | N20: =IFERROR(AVERAGE(B20:M20),"") -> 14.373232

Sheet Rupture_DMEG_Temoins
A1: Tableau 2.07: Proportion des DMEG témoins ayant connu une ruptures de stock des 25 médicaments traceurs par région en 2025
A2: Régions:Districts | B2: Janv | C2: fév | D2: mars | E2: Avril | F2: Mai | G2: Juin | H2: Juillet | I2: Août | J2: Sept | K2: Oct | L2: Nov | M2: Déc | N2: Moyenne
A3: Bankui | B3: 18.444444 | C3: 16.666667 | D3: 14.444444 | E3: 16.444444 | F3: 17.333333 | G3: 18.444444 | H3: 15.555556 | I3: 11.555556 | J3: 8.8888889 | K3: 18 | L3: 15.333333 | M3: 14.666667 | N3: =IFERROR(AVERAGE(B3:M3),"") -> 15.481481
A4: Djoro | B4: 20.533333 | C4: 17.066667 | D4: 15.733333 | E4: 20.266667 | F4: 18.666667 | G4: 19.466667 | H4: 17.333333 | I4: 18.133333 | J4: 16.8 | K4: 16.266667 | L4: 16.8 | M4: 13.333333 | N4: =IFERROR(AVERAGE(B4:M4),"") -> 17.533333
A5: Goulmou | B5: 11.111111 | C5: 11.111111 | D5: 13.555556 | E5: 5.5555556 | F5: 15.555556 | G5: 15.555556 | H5: 11.777778 | I5: 18.222222 | J5: 16.222222 | K5: 3.1111111 | L5: 2.8888889 | M5: 6.8888889 | N5: =IFERROR(AVERAGE(B5:M5),"") -> 10.962963
A6: Guiriko | B6: 13.333333 | C6: 12 | D6: 10.5 | E6: 12 | F6: 11.166667 | G6: 10.166667 | H6: 9.5 | I6: 10.333333 | J6: 9.8333333 | K6: 9.3333333 | L6: 8.6666667 | M6: 8.1666667 | N6: =IFERROR(AVERAGE(B6:M6),"") -> 10.416667
A7: Kadiogo | B7: 15.2 | C7: 8.5333333 | D7: 10.666667 | E7: 10.4 | F7: 10.4 | G7: 9.6 | H7: 8.2666667 | I7: 5.3333333 | J7: 3.7333333 | K7: 5.0666667 | L7: 5.6 | M7: 5.8666667 | N7: =IFERROR(AVERAGE(B7:M7),"") -> 8.2222222
A8: Koulsé | B8: 7.5555556 | C8: 8.2222222 | D8: 7.1111111 | E8: 6.6666667 | F8: 6.4444444 | G8: 11.111111 | H8: 10.444444 | I8: 10 | J8: 10.888889 | K8: 12.444444 | L8: 9.1111111 | M8: 8.8888889 | N8: =IFERROR(AVERAGE(B8:M8),"") -> 9.0740741
A9: Liptako | B9: ND | C9: ND | D9: ND | E9: ND | F9: ND | G9: ND | H9: ND | I9: ND | J9: ND | K9: ND | L9: ND | N9: =IFERROR(AVERAGE(B9:M9),"")
A10: Nakambé | B10: 20.952381 | C10: 11.047619 | D10: 18.285714 | E10: 17.52381 | F10: 13.333333 | G10: 18.285714 | H10: 16.571429 | I10: 12.761905 | J10: 15.238095 | K10: 8.1904762 | L10: 12 | M10: 10.47619 | N10: =IFERROR(AVERAGE(B10:M10),"") -> 14.555556
A11: Nando | B11: 17.333333 | C11: 17.333333 | D11: 13.333333 | E11: 13.714286 | F11: 12.952381 | G11: 12.380952 | H11: 10.666667 | I11: 11.809524 | J11: 10.857143 | K11: 9.9047619 | L11: 11.047619 | M11: 10.095238 | N11: =IFERROR(AVERAGE(B11:M11),"") -> 12.619048
A12: Nazinon | B12: 14.666667 | C12: 15.555556 | D12: 11.111111 | E12: 9.7777778 | F12: 10.666667 | G12: 13.333333 | H12: 9.7777778 | I12: 15.111111 | J12: 14.666667 | K12: 8 | L12: 9.3333333 | M12: 12.444444 | N12: =IFERROR(AVERAGE(B12:M12),"") -> 12.037037
A13: Oubri | B13: 16.888889 | C13: 16 | D13: 15.555556 | E13: 13.333333 | F13: 13.333333 | G13: 12.444444 | H13: 15.111111 | I13: 15.111111 | J13: 15.111111 | K13: 14.222222 | L13: 11.555556 | M13: 10.666667 | N13: =IFERROR(AVERAGE(B13:M13),"") -> 14.111111
A14: Sirba | N14: =IFERROR(AVERAGE(B14:M14),"")
A15: Soum | N15: =IFERROR(AVERAGE(B15:M15),"")
A16: Sourou | N16: =IFERROR(AVERAGE(B16:M16),"")
A17: Tannounyan | B17: 26.222222 | C17: 18.666667 | D17: 14.666667 | E17: 16.888889 | F17: 16.888889 | G17: 17.333333 | H17: 11.111111 | I17: 16 | J17: 20.888889 | K17: 6.6666667 | L17: 13.333333 | M17: 2.0355556 | N17: =IFERROR(AVERAGE(B17:M17),"") -> 15.058519
A18: Tapoa | N18: =IFERROR(AVERAGE(B18:M18),"")
A19: Yaadga | B19: 12 | C19: 14.666667 | D19: 12.666667 | E19: 12.888889 | F19: 14.666667 | G19: 12.222222 | H19: 6.2222222 | I19: 10.444444 | J19: 9.3333333 | K19: 12.222222 | L19: 8.4444444 | M19: 12 | N19: =IFERROR(AVERAGE(B19:M19),"") -> 11.481481
A20: Burkina Faso | B20: =AVERAGE(B3:B19) -> 16.186772 | C20: =AVERAGE(C3:C19) -> 13.90582 | D20: =AVERAGE(D3:D19) -> 13.135847 | E20: =AVERAGE(E3:E19) -> 12.955026 | F20: =AVERAGE(F3:F19) -> 13.450661 | G20: =AVERAGE(G3:G19) -> 14.19537 | H20: =AVERAGE(H3:H19) -> 11.861508 | I20: =AVERAGE(I3:I19) -> 12.901323 | ... N20: =AVERAGE(N3:N19) -> 12.629458
A21: Source: DCAPS | N21: =IFERROR(AVERAGE(B21:M21),"")

Sheet Gratuité_des soins
A1: Tableau 2.08: Activité de la gratuité des soins en 2025
A2: PRESTATIONS GRATUITE | B2: QUANTITE | C2: COÛT
A3: Accouchements normaux
A4: Accouchements assistés à l'aide d'instruments et/ou de produits
A5: Soins d'urgence aux nouveau-nés
A6: Soins obstétricaux d'urgence
A7: Soins curatifs du post partum
A8: Césariennes
A9: Laparotomie pour rupture uterine
A10: Laparotomie pour GEU
A11: Cure de fistules obstétricales
A12: Sous-total Accouchements et interventions obstétricales
A13: Soins curatifs en ambulatoire enfants de moins de 5 ans
A14: Soins curatifs en hospitalisation/mise en observation enfants enfants de moins de 5 ans
... A55: Total général Gratuité
A57: Biens et services | B57: Poids financier
A58: Examens complémentaires
A59: Actes
A60: Médicaments et consommables médicaux
A61: Carburant pour les évacuations à l'intérieur du pays
A62: Mise en observation/Hospitalisation
A63: Source: https://gratuite.sante.gov.bf/dhis-web-pivot/

Sheet Partie 3
A1: 3. RESSOURCES ET INFRASTRUCTURES
A2: Ressources humaines | B2: pp 54 - 67
A3: Infrastructures | B3: pp 68 - 75
A4: Situation des OBC par district | B4: pp 76 - 77
A5: Lits et occupation dans les formations sanitaires | B5: pp 78 - 83
A6: rayon moyen d'action théorique (RMAT) | B6: pp 84 - 85
A7: Ratio habitant/CSPS | B7: pp 86 - 87

Sheet Personnel Région_1 DRH
A1: Tableau 3.01: Effectif de quelques emplois du Ministère de la santé au 31 décembre 2025
A2: Structures | C2: Médecin spécialiste | D2: Médecin généraliste | E2: Pharmacien | F2: Chir. dentiste | G2: Attaché de santé | H2: IDE | I2: IB | J2: SFE-ME | K2: Infirmier | L2: Sage Femme
A3: Niveau Central | C3: =SUM(C4:C23) -> 113 | D3: =SUM(D4:D23) -> 65 | E3: =SUM(E4:E23) -> 87 | F3: =SUM(F4:F23) -> 2 | G3: =SUM(G4:G23) -> 190 | H3: =SUM(H4:H23) -> 11 | I3: =SUM(I4:I23) -> 3 | J3: =SUM(J4:J23) -> 4 | ... L3: =SUM(L4:L23) -> 21
B4: AGSP | C4: 2 | D4: 0 | E4: 3 | F4: 0 | G4: 0 | H4: 1 | I4: 0 | J4: 0 | K4: 0 | L4: 0
B5: ANRP | C5: 0 | D5: 0 | E5: 14 | F5: 0 | G5: 0 | H5: 0 | I5: 0 | J5: 0 | K5: 1 | L5: 0
B6: ANSSEAT | C6: 0 | D6: 0 | E6: 15 | F6: 0 | G6: 3 | H6: 0 | I6: 0 | J6: 0 | K6: 0 | L6: 0
B7: BCMP | C7: 0 | D7: 0 | E7: 0 | F7: 0 | G7: 0 | H7: 0 | I7: 0 | J7: 0 | K7: 0 | L7: 0
B8: Cabinet | C8: 8 | D8: 3 | E8: 1 | F8: 0 | G8: 3 | H8: 0 | I8: 0 | J8: 2 | K8: 0 | L8: 0
B9: CNTS | C9: 3 | D9: 0 | E9: 3 | F9: 0 | G9: 2 | H9: 0 | I9: 0 | J9: 0 | K9: 1 | L9: 0
B10: DAD | C10: 0 | D10: 0 | E10: 0 | F10: 0 | G10: 0 | H10: 0 | I10: 0 | J10: 0 | K10: 0 | L10: 0
B11: DDII | C11: 2 | D11: 1 | E11: 0 | F11: 0 | G11: 1 | H11: 0 | I11: 0 | J11: 0 | K11: 0 | L11: 0
B12: DGAP | C12: 0 | D12: 1 | E12: 34 | F12: 0 | G12: 2 | H12: 1 | I12: 0 | J12: 0 | K12: 1 | L12: 0
B13: DGESS | C13: 9 | D13: 5 | E13: 0 | F13: 0 | G13: 29 | H13: 0 | I13: 0 | J13: 0 | K13: 1 | L13: 0
B14: DGOS | C14: 16 | D14: 4 | E14: 4 | F14: 1 | G14: 3 | H14: 0 | I14: 0 | J14: 0 | K14: 2 | L14: 2
B15: DGSHP | C15: 45 | D15: 28 | E15: 8 | F15: 1 | G15: 91 | H15: 8 | I15: 3 | J15: 2 | K15: 2 | L15: 16
... B23: Secrétariat Général | C23: 1 | D23: 0 | E23: 0 | F23: 0 | G23: 0 | H23: 0 | I23: 0 | J23: 0 | K23: 0 | L23: 0
A24: Bankui | C24: =SUM(C25:C33) -> 31 | D24: =SUM(D25:D33) -> 62 | E24: =SUM(E25:E33) -> 10 | F24: =SUM(F25:F33) -> 1 | G24: =SUM(G25:G33) -> 109 | H24: =SUM(H25:H33) -> 191 | I24: =SUM(I25:I33) -> 16 | J24: =SUM(J25:J33) -> 155 | ... L24: =SUM(L25:L33) -> 141
B25: Administration DRS | C25: 3 | D25: 0 | E25: 1 | F25: 0 | G25: 4 | H25: 0 | I25: 0 | J25: 0 | K25: 1 | L25: 0
B26: CHR Dedougou | C26: 22 | D26: 29 | E26: 6 | F26: 1 | G26: 51 | H26: 63 | I26: 3 | J26: 28 | K26: 87 | L26: 54
B27: CNTS | C27: 0 | D27: 2 | E27: 0 | F27: 0 | G27: 5 | H27: 0 | I27: 3 | J27: 0 | K27: 2 | L27: 0
B28: DS Boromo | C28: 1 | D28: 14 | E28: 1 | F28: 0 | G28: 19 | H28: 47 | I28: 4 | J28: 48 | K28: 42 | L28: 33
B29: DS Dedougou | C29: 0 | D29: 11 | E29: 1 | F29: 0 | G29: 6 | H29: 51 | I29: 5 | J29: 57 | K29: 59 | L29: 36
B30: DS Solenzo | C30: 0 | E30: 1 | F30: 0 | G30: 13 | H30: 30 | I30: 1 | J30: 22 | K30: 37 | L30: 18
B31: ENSP | C31: 0 | D31: 0 | E31: 0 | F31: 0 | G31: 3 | H31: 0 | I31: 0 | J31: 0 | K31: 0 | L31: 0
B32: INSP | C32: 5 | D32: 5 | E32: 0 | F32: 0 | G32: 2 | H32: 0 | I32: 0 | J32: 0 | K32: 0 | L32: 0
B33: OST | C33: 0 | D33: 1 | E33: 0 | F33: 0 | G33: 6 | H33: 0 | I33: 0 | J33: 0 | K33: 0 | L33: 0
A34: Djoro | C34: =SUM(C35:C44) -> 27 | D34: =SUM(D35:D44) -> 91 | E34: =SUM(E35:E44) -> 16 | F34: =SUM(F35:F44) -> 2 | G34: =SUM(G35:G44) -> 111 | H34: =SUM(H35:H44) -> 196 | I34: =SUM(I35:I44) -> 15 | J34: =SUM(J35:J44) -> 161 | ... L34: =SUM(L35:L44) -> 146
B35: Administration DRS | C35: 2 | D35: 0 | E35: 1 | F35: 0 | G35: 5 | H35: 0 | I35: 0 | J35: 0 | K35: 2 | L35: 0
B36: CHR de GAOUA | C36: 25 | D36: 29 | E36: 5 | F36: 2 | G36: 66 | H36: 83 | I36: 2 | J36: 32 | K36: 33 | L36: 46
B37: DS BATIE | C37: 0 | D37: 9 | E37: 3 | F37: 0 | G37: 0 | H37: 16 | I37: 2 | J37: 39 | K37: 38 | L37: 8
B38: DS DANO | C38: 0 | D38: 16 | E38: 2 | F38: 0 | G38: 10 | H38: 31 | I38: 2 | J38: 28 | K38: 36 | L38: 11
B39: DS Diébougou | C39: 0 | D39: 15 | E39: 2 | F39: 0 | G39: 16 | H39: 21 | I39: 6 | J39: 21 | K39: 51 | L39: 37
B40: DS Gaoua | C40: 0 | D40: 11 | E40: 1 | F40: 0 | G40: 4 | H40: 30 | I40: 1 | J40: 29 | K40: 43 | L40: 32
B41: DS KAMPTI | C41: 0 | D41: 9 | E41: 1 | F41: 0 | G41: 2 | H41: 15 | I41: 2 | J41: 12 | K41: 25 | L41: 12
B42: DPD/PS Gaoua | C42: 0 | D42: 1 | E42: 1 | F42: 0 | G42: 4 | H42: 0 | I42: 0 | J42: 0 | K42: 4 | L42: 0
B43: ENSP | C43: 0 | D43: 0 | E43: 0 | F43: 0 | G43: 0 | H43: 0 | I43: 0 | J43: 0 | K43: 0 | L43: 0
B44: OST | C44: 0 | D44: 1 | E44: 0 | F44: 0 | G44: 4 | H44: 0 | I44: 0 | J44: 0 | K44: 0 | L44: 0
A45: Goulmou | C45: =SUM(C46:C52) -> 35 | D45: =SUM(D46:D52) -> 58 | E45: =SUM(E46:E52) -> 12 | F45: =SUM(F46:F52) -> 0 | G45: =SUM(G46:G52) -> 88 | H45: =SUM(H46:H52) -> 128 | I45: =SUM(I46:I52) -> 19 | J45: =SUM(J46:J52) -> 104 | ... L45: =SUM(L46:L52) -> 91
B46: Administration DRS | C46: 2 | D46: 0 | E46: 1 | F46: 0 | G46: 4 | H46: 0 | I46: 0 | J46: 1 | K46: 0 | L46: 0
B47: CHR de Fada | C47: 32 | D47: 37 | E47: 8 | F47: 0 | G47: 69 | H47: 55 | I47: 3 | J47: 27 | K47: 82 | L47: 46
B48: DS Fada | C48: 0 | D48: 15 | E48: 2 | F48: 0 | G48: 4 | H48: 61 | I48: 14 | J48: 67 | K48: 73 | L48: 42
B49: DS Pama | C49: 0 | D49: 4 | E49: 1 | F49: 0 | G49: 0 | H49: 10 | I49: 0 | J49: 9 | K49: 3 | L49: 3
B50: CRTS Fada | C50: 0 | D50: 2 | E50: 0 | F50: 0 | G50: 2 | H50: 2 | I50: 2 | J50: 0 | K50: 6 | L50: 0
B51: ENSP | C51: 0 | D51: 0 | E51: 0 | F51: 0 | G51: 4 | H51: 0 | I51: 0 | J51: 0 | K51: 0 | L51: 0
B52: OST | C52: 1 | D52: 0 | E52: 0 | F52: 0 | G52: 5 | H52: 0 | I52: 0 | J52: 0 | K52: 0 | L52: 0
A53: Guiriko | C53: =SUM(C55:C69) -> 199 | D53: =SUM(D55:D69) -> 228 | E53: =SUM(E55:E69) -> 46 | F53: =SUM(F55:F69) -> 4 | G53: =SUM(G55:G69) -> 488 | H53: =SUM(H55:H69) -> 362 | I53: =SUM(I55:I69) -> 62 | J53: =SUM(J55:J69) -> 188 | ... L53: =SUM(L55:L69) -> 596
B54: Administration DRS | C54: 3 | D54: 7 | E54: 1 | F54: 0 | G54: 10 | H54: 3 | I54: 0 | J54: 0 | K54: 2 | L54: 1
B55: CHUSS | C55: 125 | D55: 56 | E55: 22 | F55: 2 | G55: 235 | H55: 125 | I55: 16 | J55: 35 | K55: 216 | L55: 120
B56: CHU PALA | C56: 42 | D56: 45 | E56: 8 | F56: 0 | G56: 1 | H56: 30 | I56: 0 | J56: 20 | K56: 14 | L56: 27
B57: DS Dafra | C57: 4 | D57: 19 | E57: 2 | F57: 0 | G57: 63 | H57: 36 | I57: 15 | J57: 17 | K57: 121 | L57: 138
B58: DS Dande | C58: 0 | D58: 9 | E58: 2 | F58: 0 | G58: 16 | H58: 77 | I58: 1 | J58: 16 | K58: 5 | L58: 35
B59: DS Do | C59: 8 | D59: 31 | E59: 3 | F59: 1 | G59: 67 | H59: 23 | I59: 15 | J59: 41 | K59: 177 | L59: 144
B60: DS Hounde | C60: 0 | D60: 16 | E60: 2 | F60: 0 | G60: 29 | H60: 26 | I60: 4 | J60: 25 | K60: 84 | L60: 35
B61: DS Karangasso Vigue | C61: 0 | D61: 2 | E61: 1 | F61: 0 | G61: 2 | H61: 14 | I61: 3 | J61: 16 | K61: 28 | L61: 3
B62: DS Léna | C62: 1 | D62: 1 | E62: 1 | F62: 0 | G62: 2 | H62: 13 | I62: 0 | J62: 9 | K62: 15 | L62: 10
B63: DS N'Dorola | C63: 0 | D63: 4 | E63: 1 | F63: 0 | G63: 2 | H63: 4 | I63: 0 | J63: 2 | K63: 44 | L63: 29
B64: DS Orodara | C64: 0 | D64: 12 | E64: 2 | F64: 0 | G64: 30 | H64: 11 | I64: 6 | J64: 7 | K64: 99 | L64: 54
B65: ANSSEAT | C65: 0 | D65: 0 | E65: 0 | F65: 0 | G65: 0 | H65: 0 | I65: 0 | J65: 0 | K65: 0 | L65: 0
... B69: OST | C69: 7 | D69: 16 | E69: 0 | F69: 0 | G69: 33 | H69: 0 | I69: 0 | J69: 0 | K69: 2 | L69: 0
A70: Kadiogo | C70: =SUM(C71:C85) -> 530 | D70: =SUM(D71:D85) -> 280 | E70: =SUM(E71:E85) -> 70 | F70: =SUM(F71:F85) -> 20 | G70: =SUM(G71:G85) -> 986 | H70: =SUM(H71:H85) -> 942 | I70: =SUM(I71:I85) -> 376 | J70: =SUM(J71:J85) -> 760 | ... L70: =SUM(L71:L85) -> 504
B71: Administration DRS | C71: 3 | D71: 3 | E71: 3 | F71: 0 | G71: 9 | H71: 0 | I71: 0 | J71: 0 | K71: 5 | L71: 0
B72: CHU Bogodogo | C72: 124 | D72: 46 | E72: 11 | F72: 5 | G72: 123 | H72: 63 | I72: 1 | J72: 26 | K72: 191 | L72: 101
B73: CHU Pédiatrique CDG | C73: 40 | D73: 18 | E73: 4 | F73: 0 | G73: 64 | H73: 41 | I73: 41 | J73: 12 | K73: 114 | L73: 13
B74: CHU Tengandogo | C74: 121 | D74: 31 | E74: 12 | F74: 2 | G74: 94 | H74: 158 | I74: 64 | J74: 27 | K74: 92 | L74: 39
B75: CHU Yalgado | C75: 166 | D75: 43 | E75: 23 | F75: 7 | G75: 283 | H75: 82 | I75: 105 | J75: 20 | K75: 200 | L75: 135
B76: DS Baskuy | C76: 0 | D76: 17 | E76: 2 | F76: 2 | G76: 22 | H76: 69 | I76: 29 | J76: 46 | K76: 6 | L76: 25
B77: DS Bogodogo | C77: 3 | D77: 22 | E77: 3 | F77: 1 | G77: 19 | H77: 141 | I77: 49 | J77: 154 | K77: 56 | L77: 48
B78: DS Boulmiougou | C78: 27 | D78: 33 | E78: 3 | F78: 1 | G78: 114 | H78: 178 | I78: 24 | J78: 255 | K78: 15 | L78: 6
B79: DS Nongr-Massom | C79: 21 | D79: 20 | E79: 4 | F79: 1 | G79: 115 | H79: 11 | I79: 20 | J79: 71 | K79: 9 | L79: 57
B80: DS Sig-Noghin | C80: 0 | D80: 11 | E80: 2 | F80: 0 | G80: 38 | H80: 192 | I80: 26 | J80: 145 | K80: 17 | L80: 77
B81: ANSSEAT
B82: CRTS Ouagadougou | C82: 3 | D82: 5 | E82: 3 | F82: 0 | G82: 8 | H82: 4 | I82: 17 | J82: 0 | K82: 27 | L82: 0
B83: ENSP
B84: INSP
B85: OST | C85: 22 | D85: 31 | E85: 0 | F85: 1 | G85: 97 | H85: 3 | I85: 0 | J85: 4 | K85: 2 | L85: 3
A86: Koulsé | C86: =SUM(C87:C97) -> 32 | D86: =SUM(D87:D97) -> 97 | E86: =SUM(E87:E97) -> 15 | F86: =SUM(F87:F97) -> 2 | G86: =SUM(G87:G97) -> 65 | H86: =SUM(H87:H97) -> 329 | I86: =SUM(I87:I97) -> 16 | J86: =SUM(J87:J97) -> 222 | ... L86: =SUM(L87:L97) -> 121
B87: Administration DRS | C87: 1 | D87: 3 | E87: 1 | F87: 0 | G87: 5 | H87: 0 | I87: 0 | J87: 0 | K87: 1 | L87: 0
B88: CHR de KAYA | C88: 30 | D88: 39 | E88: 7 | F88: 2 | G88: 1 | H88: 63 | I88: 1 | J88: 21 | K88: 65 | L88: 43
B89: DS Barsalogho | C89: 0 | D89: 5 | E89: 1 | F89: 0 | G89: 9 | H89: 29 | I89: 1 | J89: 18 | K89: 0 | L89: 0
B90: DS Boulsa | C90: 0 | D90: 9 | E90: 1 | F90: 0 | G90: 19 | H90: 30 | I90: 1 | J90: 18 | K90: 16 | L90: 15
B91: DS Boussouma | C91: 0 | D91: 9 | E91: 1 | F91: 0 | G91: 2 | H91: 56 | I91: 1 | J91: 40 | K91: 17 | L91: 11
B92: DS Kaya | C92: 0 | D92: 11 | E92: 2 | F92: 0 | G92: 4 | H92: 51 | I92: 7 | J92: 63 | K92: 60 | L92: 38
B93: DS Kongoussi | C93: 1 | D93: 11 | E93: 1 | F93: 0 | G93: 15 | H93: 64 | I93: 2 | J93: 36 | K93: 9 | L93: 8
B94: DS Tougouri | C94: 0 | D94: 7 | E94: 1 | F94: 0 | G94: 1 | H94: 35 | I94: 1 | J94: 26 | K94: 1 | L94: 4
B95: DPD/PS Kaya | C95: 0 | D95: 3 | E95: 0 | F95: 0 | G95: 6 | H95: 1 | I95: 2 | J95: 0 | K95: 4 | L95: 0
B96: ENSP | C96: 0 | D96: 0 | E96: 0 | F96: 0 | G96: 2 | H96: 0 | I96: 0 | J96: 0 | K96: 0 | L96: 2
B97: OST | C97: 0 | D97: 0 | E97: 0 | F97: 0 | G97: 1 | H97: 0 | I97: 0 | J97: 0 | K97: 0 | L97: 0
A98: Liptako | C98: =SUM(C99:C106) -> 15 | D98: =SUM(D99:D106) -> 44 | E98: =SUM(E99:E106) -> 8 | F98: =SUM(F99:F106) -> 0 | G98: =SUM(G99:G106) -> 58 | H98: =SUM(H99:H106) -> 155 | I98: =SUM(I99:I106) -> 5 | J98: =SUM(J99:J106) -> 163 | ... L98: =SUM(L99:L106) -> 67
B99: Administration DRS | C99: 3 | D99: 0 | E99: 1 | F99: 0 | G99: 4 | H99: 0 | I99: 0 | J99: 0 | K99: 0 | L99: 0
B100: CHR de Dori | C100: 12 | D100: 16 | E100: 4 | F100: 0 | G100: 36 | H100: 75 | I100: 0 | J100: 59 | K100: 32 | L100: 23
B101: DS Dori | C101: 0 | D101: 13 | E101: 1 | F101: 0 | G101: 5 | H101: 42 | I101: 1 | J101: 72 | K101: 37 | L101: 30
B102: DS Gorom Gorom | C102: 0 | D102: 10 | E102: 1 | F102: 0 | G102: 6 | H102: 30 | I102: 4 | J102: 24 | K102: 17 | L102: 6
B103: DS Sebba | C103: 0 | D103: 5 | E103: 1 | F103: 0 | G103: 5 | H103: 8 | I103: 0 | J103: 8 | K103: 0 | L103: 8
B104: DPD/PS Dori | C104: 0 | D104: 0 | E104: 0 | F104: 0 | G104: 1 | H104: 0 | I104: 0 | J104: 0 | K104: 0 | L104: 0
B105: ENSP | C105: 0 | D105: 0 | E105: 0 | F105: 0 | G105: 0 | H105: 0 | I105: 0 | J105: 0 | K105: 0 | L105: 0
B106: OST | C106: 0 | D106: 0 | E106: 0 | F106: 0 | G106: 1 | H106: 0 | I106: 0 | J106: 0 | K106: 0 | L106: 0
A107: Nakambé | C107: =SUM(C108:C120) -> 42 | D107: =SUM(D108:D120) -> 116 | E107: =SUM(E108:E120) -> 16 | F107: =SUM(F108:F120) -> 2 | G107: =SUM(G108:G120) -> 179 | H107: =SUM(H108:H120) -> 295 | I107: =SUM(I108:I120) -> 19 | J107: =SUM(J108:J120) -> 190 | ... L107: =SUM(L108:L120) -> 233
B108: Administration DRS | C108: 4 | D108: 0 | E108: 1 | F108: 0 | G108: 5 | H108: 0 | I108: 0 | J108: 0 | K108: 0 | L108: 0
B109: CHR de TENKODOGO | C109: 35 | D109: 39 | E109: 9 | F109: 2 | G109: 68 | H109: 87 | I109: 1 | J109: 35 | K109: 61 | L109: 51
B110: DS Bittou | C110: 0 | D110: 8 | E110: 0 | F110: 0 | G110: 11 | H110: 13 | I110: 1 | J110: 18 | K110: 19 | L110: 14
...

Sheet Personnel Région_2 DRH
A1: Tableau 3.02: Effectif de quelques emplois du Ministère de la santé au 31 décembre 2025(suite)
A2: Structures | C2: Tech labo/bio | D2: MEER | E2: PEP | F2: Technicien d'Etat du génie sanitaire | G2: AB | H2: AIS | I2: G/F Salle | J2: AA | K2: ACH | L2: GHSS | M2: AHSS
A3: Niveau Central | C3: =SUM(C4:C23) -> 69 | D3: =SUM(D4:D23) -> 2 | E3: =SUM(E4:E23) -> 19 | F3: =SUM(F4:F23) -> 15 | G3: =SUM(G4:G23) -> 1 | H3: =SUM(H4:H23) -> 1 | I3: =SUM(I4:I23) -> 24 | J3: =SUM(J4:J23) -> 0 | ... M3: =SUM(M4:M23) -> 85
B4: AGSP | C4: 0 | D4: 0 | E4: 0 | F4: 0 | G4: 0 | H4: 0 | I4: 0 | J4: 0 | K4: 0 | L4: 4 | M4: 0
B5: ANRP | C5: 0 | D5: 0 | E5: 5 | F5: 0 | G5: 1 | H5: 0 | I5: 2 | J5: 0 | K5: 2 | L5: 3 | M5: 3
B6: ANSSEAT | C6: 34 | D6: 1 | E6: 1 | F6: 11 | G6: 0 | H6: 0 | I6: 13 | J6: 0 | K6: 1 | L6: 3 | M6: 0
B7: BCMP | C7: 0 | D7: 0 | E7: 0 | F7: 0 | G7: 0 | H7: 0 | I7: 0 | J7: 0 | K7: 1 | L7: 5 | M7: 1
B8: Cabinet | C8: 0 | D8: 0 | E8: 0 | F8: 0 | G8: 0 | H8: 0 | I8: 0 | J8: 0 | K8: 0 | L8: 4 | M8: 1
B9: CNTS | C9: 4 | D9: 0 | E9: 0 | F9: 0 | G9: 0 | H9: 0 | I9: 0 | J9: 0 | K9: 0 | L9: 7 | M9: 1
B10: DAD | C10: 0 | D10: 0 | E10: 0 | F10: 0 | G10: 0 | H10: 0 | I10: 0 | J10: 0 | K10: 0 | L10: 0 | M10: 0
B11: DDII | C11: 0 | D11: 0 | E11: 0 | F11: 0 | G11: 0 | H11: 0 | I11: 0 | J11: 0 | K11: 0 | L11: 1 | M11: 1
B12: DGAP | C12: 3 | D12: 0 | E12: 1 | F12: 0 | G12: 0 | H12: 0 | I12: 1 | J12: 0 | K12: 1 | L12: 4 | M12: 4
B13: DGESS | C13: 0 | D13: 0 | E13: 0 | F13: 0 | G13: 0 | H13: 0 | I13: 0 | J13: 0 | K13: 2 | L13: 4 | M13: 21
B14: DGOS | C14: 0 | D14: 0 | E14: 4 | F14: 0 | G14: 0 | H14: 0 | I14: 0 | J14: 0 | K14: 0 | L14: 9 | M14: 20
B15: DGSHP | C15: 0 | D15: 1 | E15: 8 | F15: 4 | G15: 0 | H15: 1 | I15: 7 | J15: 0 | K15: 7 | L15: 19 | M15: 9
... B23: Secrétariat Général | C23: 0 | D23: 0 | E23: 0 | F23: 0 | G23: 0 | H23: 0 | I23: 0 | J23: 0 | K23: 0 | L23: 1 | M23: 1
A24: Bankui | C24: =SUM(C25:C33) -> 44 | D24: =SUM(D25:D33) -> 9 | E24: =SUM(E25:E33) -> 6 | F24: =SUM(F25:F33) -> 13 | G24: =SUM(G25:G33) -> 48 | H24: =SUM(H25:H33) -> 35 | I24: =SUM(I25:I33) -> 5 | J24: =SUM(J25:J33) -> 26 | ... M24: =SUM(M25:M33) -> 9
B25: Administration DRS | C25: 0 | D25: 0 | E25: 1 | F25: 2 | G25: 0 | H25: 0 | I25: 0 | J25: 0 | K25: 1 | L25: 2 | M25: 1
B26: CHR Dedougou | C26: 23 | D26: 7 | E26: 1 | F26: 5 | G26: 0 | H26: 0 | I26: 1 | J26: 0 | K26: 2 | L26: 6 | M26: 5
B27: CNTS | C27: 4 | D27: 0 | E27: 0 | F27: 0 | G27: 0 | H27: 0 | I27: 0 | J27: 0 | K27: 1 | L27: 0 | M27: 0
B28: DS Boromo | C28: 0 | D28: 2 | E28: 1 | F28: 2 | G28: 18 | H28: 10 | I28: 2 | J28: 7 | K28: 0 | L28: 2 | M28: 1
B29: DS Dedougou | C29: 7 | D29: 0 | E29: 2 | F29: 2 | G29: 25 | H29: 25 | I29: 1 | J29: 18 | K29: 1 | L29: 3 | M29: 1
B30: DS Solenzo | C30: 3 | D30: 0 | E30: 1 | F30: 2 | G30: 5 | H30: 0 | I30: 1 | J30: 1 | K30: 0 | L30: 3 | M30: 1
B31: ENSP | C31: 0 | D31: 0 | E31: 0 | F31: 0 | G31: 0 | H31: 0 | I31: 0 | J31: 0 | K31: 0 | L31: 0 | M31: 0
B32: INSP | C32: 7 | D32: 0 | E32: 0 | F32: 0 | G32: 0 | H32: 0 | I32: 0 | J32: 0 | K32: 0 | L32: 1 | M32: 0
B33: OST | C33: 0 | D33: 0 | E33: 0 | F33: 0 | G33: 0 | H33: 0 | I33: 0 | J33: 0 | K33: 0 | L33: 0 | M33: 0
A34: Djoro | C34: =SUM(C35:C44) -> 53 | D34: =SUM(D35:D44) -> 10 | E34: =SUM(E35:E44) -> 6 | F34: =SUM(F35:F44) -> 12 | G34: =SUM(G35:G44) -> 54 | H34: =SUM(H35:H44) -> 34 | I34: =SUM(I35:I44) -> 28 | J34: =SUM(J35:J44) -> 14 | ... M34: =SUM(M35:M44) -> 10
B35: Administration DRS | C35: 0 | D35: 0 | E35: 0 | F35: 1 | G35: 0 | H35: 0 | I35: 0 | J35: 0 | K35: 1 | L35: 2 | M35: 1
B36: CHR de GAOUA | C36: 20 | D36: 7 | E36: 1 | F36: 3 | G36: 0 | H36: 0 | I36: 15 | J36: 2 | K36: 1 | L36: 5 | M36: 4
B37: DS BATIE | C37: 7 | D37: 2 | E37: 0 | F37: 2 | G37: 9 | H37: 8 | I37: 3 | J37: 1 | K37: 0 | L37: 3 | M37: 1
B38: DS DANO | C38: 10 | D38: 0 | E38: 2 | F38: 1 | G38: 8 | H38: 4 | I38: 3 | J38: 4 | K38: 0 | L38: 1 | M38: 2
B39: DS Diébougou | C39: 6 | D39: 1 | E39: 1 | F39: 2 | G39: 16 | H39: 8 | I39: 2 | J39: 1 | K39: 0 | L39: 4 | M39: 1
B40: DS Gaoua | C40: 5 | D40: 0 | E40: 1 | F40: 2 | G40: 17 | H40: 11 | I40: 2 | J40: 5 | K40: 1 | L40: 3 | M40: 0
B41: DS KAMPTI | C41: 2 | D41: 0 | E41: 1 | F41: 1 | G41: 4 | H41: 2 | I41: 2 | J41: 1 | K41: 1 | L41: 2 | M41: 1
B42: DPD/PS Gaoua | C42: 3 | D42: 0 | E42: 0 | F42: 0 | G42: 0 | H42: 1 | I42: 1 | J42: 0 | K42: 0 | L42: 0 | M42: 0
B43: ENSP | C43: 0 | D43: 0 | E43: 0 | F43: 0 | G43: 0 | H43: 0 | I43: 0 | J43: 0 | K43: 0 | L43: 0 | M43: 0
B44: OST | C44: 0 | D44: 0 | E44: 0 | F44: 0 | G44: 0 | H44: 0 | I44: 0 | J44: 0 | K44: 0 | L44: 0 | M44: 0
A45: Goulmou | C45: =SUM(C46:C52) -> 43 | D45: =SUM(D46:D52) -> 9 | E45: =SUM(E46:E52) -> 3 | F45: =SUM(F46:F52) -> 4 | G45: =SUM(G46:G52) -> 33 | H45: =SUM(H46:H52) -> 22 | I45: =SUM(I46:I52) -> 22 | J45: =SUM(J46:J52) -> 26 | ... M45: =SUM(M46:M52) -> 6
B46: Administration DRS | C46: 0 | D46: 0 | E46: 0 | F46: 1 | G46: 0 | H46: 0 | I46: 1 | J46: 0 | K46: 0 | L46: 3 | M46: 1
B47: CHR de Fada | C47: 27 | D47: 9 | E47: 2 | F47: 1 | G47: 0 | H47: 0 | I47: 13 | J47: 0 | K47: 1 | L47: 6 | M47: 4
B48: DS Fada | C48: 10 | D48: 0 | E48: 1 | F48: 1 | G48: 24 | H48: 22 | I48: 4 | J48: 26 | K48: 0 | L48: 3 | M48: 1
B49: DS Pama | C49: 1 | D49: 0 | E49: 0 | F49: 1 | G49: 9 | I49: 1 | J49: 0 | K49: 0 | L49: 3 | M49: 0
B50: CRTS Fada | C50: 5 | D50: 0 | E50: 0 | F50: 0 | G50: 0 | H50: 0 | I50: 3 | J50: 0 | K50: 0 | L50: 1 | M50: 0
B51: ENSP | C51: 0 | D51: 0 | E51: 0 | F51: 0 | G51: 0 | H51: 0 | I51: 0 | J51: 0 | K51: 0 | L51: 0 | M51: 0
B52: OST | C52: 0 | D52: 0 | E52: 0 | F52: 0 | G52: 0 | H52: 0 | I52: 0 | J52: 0 | K52: 0 | L52: 0 | M52: 0
A53: Guiriko | C53: =SUM(C55:C69) -> 138 | D53: =SUM(D55:D69) -> 23 | E53: =SUM(E55:E69) -> 16 | F53: =SUM(F55:F69) -> 17 | G53: =SUM(G55:G69) -> 117 | H53: =SUM(H55:H69) -> 190 | I53: =SUM(I55:I69) -> 107 | J53: =SUM(J55:J69) -> 160 | ... M53: =SUM(M55:M69) -> 23
B54: Administration DRS | C54: 2 | D54: 0 | E54: 0 | F54: 1 | G54: 0 | H54: 0 | I54: 2 | J54: 0 | K54: 0 | L54: 5 | M54: 1
B55: CHUSS | C55: 31 | D55: 13 | E55: 4 | F55: 4 | G55: 0 | H55: 0 | I55: 68 | J55: 1 | K55: 2 | L55: 6 | M55: 10
B56: CHU PALA | C56: 1 | D56: 0 | E56: 0 | F56: 0 | G56: 0 | I56: 0 | J56: 0 | K56: 0 | L56: 2 | M56: 6
B57: DS Dafra | C57: 11 | D57: 0 | E57: 2 | F57: 2 | G57: 28 | H57: 56 | I57: 14 | J57: 71 | K57: 0 | L57: 4 | M57: 1
B58: DS Dande | C58: 7 | D58: 0 | E58: 1 | F58: 1 | G58: 7 | H58: 12 | I58: 4 | J58: 4 | K58: 2 | L58: 2 | M58: 1
B59: DS Do | C59: 15 | D59: 3 | E59: 3 | F59: 2 | G59: 27 | H59: 75 | I59: 10 | J59: 76 | K59: 3 | L59: 3 | M59: 1
B60: DS Hounde | C60: 9 | D60: 5 | E60: 1 | F60: 1 | G60: 18 | H60: 17 | I60: 3 | J60: 1 | K60: 1 | L60: 2 | M60: 1
B61: DS Karangasso Vigue | C61: 0 | D61: 0 | E61: 1 | F61: 1 | G61: 7 | H61: 8 | I61: 0 | J61: 1 | K61: 0 | L61: 3 | M61: 1
B62: DS Léna | C62: 0 | D62: 0 | E62: 1 | F62: 1 | G62: 4 | H62: 3 | I62: 0 | J62: 2 | K62: 0 | L62: 3 | M62: 1
B63: DS N'Dorola | C63: 2 | D63: 0 | E63: 1 | F63: 1 | G63: 7 | H63: 5 | I63: 0 | J63: 1 | K63: 0 | L63: 0 | M63: 0
B64: DS Orodara | C64: 8 | D64: 0 | E64: 2 | F64: 2 | G64: 19 | H64: 13 | I64: 2 | J64: 3 | K64: 0 | L64: 2 | M64: 1
B65: ANSSEAT | C65: 5 | D65: 0 | E65: 0 | F65: 0 | G65: 0 | H65: 0 | I65: 2 | J65: 0 | K65: 0 | L65: 0 | M65: 0
B66: CRTS Bobo Dioulasso | C66: 14 | D66: 0 | E66: 0 | F66: 0 | G66: 0 | H66: 0 | I66: 1 | J66: 0 | K66: 0 | L66: 1 | M66: 0
B67: ENSP | C67: 0 | D67: 0 | E67: 0 | F67: 0 | G67: 0 | H67: 0 | I67: 0 | J67: 0 | K67: 0 | L67: 0 | M67: 0
B68: INSP | C68: 30 | D68: 0 | E68: 0 | F68: 2 | H68: 0 | I68: 2 | J68: 0 | K68: 0 | L68: 0 | M68: 0
B69: OST | C69: 5 | D69: 2 | E69: 0 | F69: 0 | G69: 0 | H69: 1 | I69: 1 | J69: 0 | K69: 0 | L69: 0 | M69: 0
A70: Kadiogo | C70: =SUM(C71:C85) -> 217 | D70: =SUM(D71:D85) -> 73 | E70: =SUM(E71:E85) -> 48 | F70: =SUM(F71:F85) -> 21 | G70: =SUM(G71:G85) -> 88 | H70: =SUM(H71:H85) -> 293 | I70: =SUM(I71:I85) -> 401 | J70: =SUM(J71:J85) -> 306 | ... M70: =SUM(M71:M85) -> 36
B71: Administration DRS | C71: 1 | D71: 0 | E71: 1 | F71: 3 | G71: 0 | H71: 0 | I71: 1 | J71: 0 | K71: 3 | L71: 2 | M71: 5
B72: CHU Bogodogo | C72: 38 | D72: 23 | E72: 10 | F72: 1 | G72: 0 | H72: 0 | I72: 74 | J72: 0 | K72: 3 | L72: 9 | M72: 8
B73: CHU Pédiatrique CDG | C73: 25 | D73: 9 | E73: 6 | F73: 1 | G73: 0 | H73: 0 | I73: 51 | J73: 0 | K73: 1 | L73: 7 | M73: 7
B74: CHU Tengandogo | C74: 0 | D74: 10 | E74: 10 | F74: 3 | G74: 0 | H74: 0 | I74: 84 | J74: 0 | K74: 0 | L74: 8 | M74: 4
B75: CHU Yalgado | C75: 52 | D75: 17 | E75: 9 | F75: 3 | G75: 0 | H75: 0 | I75: 164 | J75: 0 | K75: 4 | L75: 8 | M75: 8
B76: DS Baskuy | C76: 16 | D76: 0 | E76: 2 | F76: 2 | G76: 5 | H76: 40 | I76: 5 | J76: 62 | K76: 3 | L76: 6 | M76: 0
B77: DS Bogodogo | C77: 7 | D77: 0 | E77: 2 | F77: 2 | H77: 72 | I77: 6 | K77: 2 | L77: 5 | M77: 2
B78: DS Boulmiougou | C78: 22 | D78: 1 | E78: 4 | F78: 3 | G78: 39 | H78: 85 | I78: 11 | J78: 130 | K78: 6 | L78: 6 | M78: 1
B79: DS Nongr-Massom | C79: 18 | D79: 3 | E79: 2 | F79: 2 | G79: 14 | H79: 46 | I79: 1 | J79: 36 | K79: 0 | L79: 6 | M79: 0
B80: DS Sig-Noghin | C80: 6 | D80: 2 | E80: 2 | F80: 1 | G80: 30 | H80: 47 | I80: 2 | J80: 78 | K80: 2 | L80: 4 | M80: 1
B81: ANSSEAT
B82: CRTS Ouagadougou | C82: 18 | D82: 0 | E82: 0 | F82: 0 | G82: 0 | H82: 0 | I82: 1 | J82: 0 | K82: 0 | L82: 0 | M82: 0
B83: ENSP | C83: 0 | D83: 0 | E83: 0 | F83: 0 | G83: 0 | H83: 0 | I83: 0 | J83: 0 | K83: 0 | L83: 0 | M83: 0
B84: INSP
B85: OST | C85: 14 | D85: 8 | E85: 0 | F85: 0 | G85: 0 | H85: 3 | I85: 1 | J85: 0 | K85: 0 | L85: 0 | M85: 0
A86: Koulsé | C86: =SUM(C87:C96) -> 62 | D86: =SUM(D87:D96) -> 7 | E86: =SUM(E87:E96) -> 6 | F86: =SUM(F87:F96) -> 13 | G86: =SUM(G87:G96) -> 57 | H86: =SUM(H87:H96) -> 44 | I86: =SUM(I87:I96) -> 21 | J86: =SUM(J87:J96) -> 13 | ... M86: =SUM(M87:M96) -> 11
B87: Administration DRS | C87: 0 | D87: 0 | E87: 0 | F87: 3 | G87: 0 | H87: 0 | I87: 0 | J87: 0 | K87: 1 | L87: 2 | M87: 2
B88: CHR de KAYA | C88: 18 | D88: 4 | E88: 1 | F88: 2 | G88: 0 | H88: 0 | I88: 18 | J88: 0 | K88: 0 | L88: 5 | M88: 3
B89: DS Barsalogho | C89: 4 | D89: 0 | E89: 0 | F89: 1 | G89: 5 | H89: 3 | I89: 0 | J89: 0 | K89: 0 | L89: 1 | M89: 1
B90: DS Boulsa | C90: 7 | D90: 0 | E90: 0 | F90: 2 | G90: 6 | H90: 3 | I90: 0 | J90: 1 | K90: 1 | L90: 3 | M90: 1
B91: DS Boussouma | C91: 7 | D91: 0 | E91: 1 | F91: 1 | G91: 8 | H91: 5 | I91: 0 | J91: 0 | K91: 0 | L91: 3 | M91: 1
B92: DS Kaya | C92: 6 | D92: 0 | E92: 1 | F92: 2 | G92: 21 | H92: 26 | I92: 3 | J92: 9 | K92: 0 | L92: 2 | M92: 1
B93: DS Kongoussi | C93: 12 | D93: 3 | E93: 2 | F93: 1 | G93: 12 | H93: 6 | I93: 0 | J93: 1 | K93: 1 | L93: 3 | M93: 1
B94: DS Tougouri | C94: 4 | D94: 0 | E94: 1 | F94: 1 | G94: 5 | H94: 1 | I94: 0 | J94: 2 | K94: 1 | L94: 1 | M94: 1
B95: DPD/PS Kaya | C95: 4 | D95: 0 | E95: 0 | F95: 0 | G95: 0 | H95: 0 | I95: 0 | J95: 0 | K95: 0 | L95: 0 | M95: 0
B96: ENSP | C96: 0 | D96: 0 | E96: 0 | F96: 0 | G96: 0 | H96: 0 | I96: 0 | J96: 0 | K96: 0 | L96: 0 | M96: 0
B97: OST | C97: 0 | D97: 0 | E97: 0 | F97: 0 | G97: 0 | H97: 0 | I97: 0 | J97: 0 | K97: 0 | L97: 0 | M97: 0
A98: Liptako | C98: =SUM(C99:C106) -> 41 | D98: =SUM(D99:D106) -> 6 | E98: =SUM(E99:E106) -> 1 | F98: =SUM(F99:F106) -> 9 | G98: =SUM(G99:G106) -> 51 | H98: =SUM(H99:H106) -> 13 | I98: =SUM(I99:I106) -> 8 | J98: =SUM(J99:J106) -> 1 | ... M98: =SUM(M99:M106) -> 6
B99: Administration DRS | C99: 0 | D99: 0 | E99: 0 | F99: 1 | G99: 0 | H99: 0 | I99: 1 | J99: 0 | K99: 0 | L99: 3 | M99: 1
B100: CHR de Dori | C100: 18 | D100: 4 | E100: 1 | F100: 1 | G100: 0 | H100: 0 | I100: 3 | J100: 0 | K100: 0 | L100: 5 | M100: 4
B101: DS Dori | C101: 16 | D101: 0 | E101: 0 | F101: 4 | G101: 32 | H101: 8 | I101: 3 | J101: 1 | K101: 0 | L101: 2 | M101: 1
B102: DS Gorom Gorom | C102: 5 | D102: 2 | E102: 0 | F102: 2 | G102: 12 | H102: 4 | I102: 1 | J102: 0 | K102: 0 | L102: 3 | M102: 0
B103: DS Sebba | C103: 2 | D103: 0 | E103: 0 | F103: 1 | G103: 7 | H103: 1 | I103: 0 | J103: 0 | K103: 2 | L103: 1 | M103: 0
B104: DPD/PS Dori | C104: 0 | D104: 0 | E104: 0 | F104: 0 | G104: 0 | H104: 0 | I104: 0 | J104: 0 | K104: 0 | L104: 1 | M104: 0
B105: ENSP | C105: 0 | D105: 0 | E105: 0 | F105: 0 | G105: 0 | H105: 0 | I105: 0 | J105: 0 | K105: 0 | L105: 0 | M105: 0
B106: OST | C106: 0 | D106: 0 | E106: 0 | F106: 0 | G106: 0 | H106: 0 | I106: 0 | J106: 0 | K106: 0 | L106: 0 | M106: 0
A107: Nakambé | C107: =SUM(C108:C120) -> 78 | D107: =SUM(D108:D120) -> 15 | E107: =SUM(E108:E120) -> 9 | F107: =SUM(F108:F120) -> 22 | G107: =SUM(G108:G120) -> 68 | H107: =SUM(H108:H120) -> 48 | I107: =SUM(I108:I120) -> 34 | J107: =SUM(J108:J120) -> 22 | ... M107: =SUM(M108:M120) -> 13
...

Sheet Personnel Région 3 DRH
A1: Tableau 3.03: Effectif de quelques emplois du Ministère de la santé au 31 décembre 2025 (suite)
A2: Structures | C2: Conseiller de santé | D2: Nutritionniste | E2: Tech d’hygiène hospitalière | F2: Biologistes médicaux | G2: Cadre PEP | H2: Agent de santé communautaire
A3: Niveau Central | C3: =SUM(C4:C23) -> 38 | D3: =SUM(D4:D23) -> 19 | E3: =SUM(E4:E23) -> 19 | F3: =SUM(F4:F23) -> 38 | G3: =SUM(G4:G23) -> 17 | H3: =SUM(H4:H23) -> 0
B4: AGSP | C4: 1 | D4: 0 | E4: 0 | F4: 0 | G4: 0 | H4: 0
B5: ANRP | C5: 1 | D5: 0 | E5: 2 | F5: 0 | G5: 1 | H5: 0
B6: ANSSEAT | C6: 0 | D6: 2 | E6: 12 | F6: 5 | G6: 4 | H6: 0
B7: BCMP | C7: 0 | D7: 0 | E7: 0 | F7: 0 | G7: 0 | H7: 0
B8: Cabinet | C8: 0 | D8: 0 | E8: 0 | F8: 1 | G8: 0 | H8: 0
B9: CNTS | C9: 0 | D9: 0 | E9: 0 | F9: 2 | G9: 2 | H9: 0
B10: DAD | C10: 0 | D10: 0 | E10: 0 | F10: 0 | G10: 0 | H10: 0
B11: DDII | C11: 0 | D11: 0 | E11: 0 | F11: 0 | G11: 0 | H11: 0
B12: DGAP | C12: 0 | D12: 0 | E12: 0 | F12: 5 | G12: 3 | H12: 0
B13: DGESS | C13: 2 | D13: 0 | E13: 0 | F13: 0 | G13: 0 | H13: 0
B14: DGOS | C14: 0 | D14: 0 | E14: 1 | F14: 2 | G14: 0 | H14: 0
B15: DGSHP | C15: 16 | D15: 17 | E15: 2 | F15: 4 | G15: 5 | H15: 0
... B23: Secrétariat Général | C23: 1 | D23: 0 | E23: 0 | F23: 0 | G23: 0 | H23: 0
A24: Bankui | C24: =SUM(C25:C33) -> 5 | D24: =SUM(D25:D33) -> 3 | E24: =SUM(E25:E33) -> 38 | F24: =SUM(F25:F33) -> 9 | G24: =SUM(G25:G33) -> 0 | H24: =SUM(H25:H33) -> 62
B25: Administration DRS | C25: 1 | D25: 1 | E25: 0 | F25: 0 | G25: 0 | H25: 0
B26: CHR Dedougou | C26: 3 | D26: 2 | E26: 24 | F26: 2 | G26: 0 | H26: 0
B27: CNTS | C27: 0 | D27: 0 | E27: 3 | F27: 0 | G27: 0 | H27: 2
B28: DS Boromo | C28: 0 | D28: 0 | E28: 6 | F28: 5 | G28: 0 | H28: 26
B29: DS Dedougou | C29: 0 | D29: 0 | E29: 0 | F29: 0 | G29: 0 | H29: 21
B30: DS Solenzo | C30: 0 | D30: 0 | E30: 5 | F30: 0 | G30: 0 | H30: 13
B31: ENSP | C31: 1 | D31: 0 | E31: 0 | F31: 0 | G31: 0 | H31: 0
B32: INSP | C32: 0 | D32: 0 | E32: 0 | F32: 2 | G32: 0 | H32: 0
B33: OST | C33: 0 | D33: 0 | E33: 0 | F33: 0 | G33: 0 | H33: 0
A34: Djoro | C34: =SUM(C35:C44) -> 4 | D34: =SUM(D35:D44) -> 3 | E34: =SUM(E35:E44) -> 48 | F34: =SUM(F35:F44) -> 2 | G34: =SUM(G35:G44) -> 1 | H34: =SUM(H35:H44) -> 120
B35: Administration DRS | C35: 1 | D35: 1 | E35: 1 | F35: 0 | G35: 0 | H35: 0
B36: CHR de GAOUA | C36: 2 | D36: 2 | E36: 27 | F36: 2 | G36: 1 | H36: 0
B37: DS BATIE | C37: 0 | D37: 0 | E37: 7 | F37: 0 | G37: 0 | H37: 15
B38: DS DANO | C38: 1 | D38: 0 | E38: 0 | F38: 0 | G38: 0 | H38: 23
B39: DS Diébougou | C39: 0 | D39: 0 | E39: 8 | F39: 0 | G39: 0 | H39: 30
B40: DS Gaoua | C40: 0 | D40: 0 | E40: 4 | F40: 0 | G40: 0 | H40: 36
B41: DS KAMPTI | C41: 0 | D41: 0 | E41: 0 | F41: 0 | G41: 0 | H41: 14
B42: DPD/PS Gaoua | C42: 0 | D42: 0 | E42: 1 | F42: 0 | G42: 0 | H42: 2
B43: ENSP | C43: 0 | D43: 0 | E43: 0 | F43: 0 | G43: 0 | H43: 0
B44: OST | C44: 0 | D44: 0 | E44: 0 | F44: 0 | G44: 0 | H44: 0
A45: Goulmou | C45: =SUM(C46:C52) -> 5 | D45: =SUM(D46:D52) -> 3 | E45: =SUM(E46:E52) -> 52 | F45: =SUM(F46:F52) -> 2 | G45: =SUM(G46:G52) -> 1 | H45: =SUM(H46:H52) -> 56
B46: Administration DRS | C46: 2 | D46: 2 | E46: 0 | F46: 0 | G46: 1 | H46: 0
B47: CHR de Fada | C47: 1 | D47: 1 | E47: 38 | F47: 2 | G47: 0 | H47: 0
B48: DS Fada | C48: 1 | D48: 0 | E48: 11 | F48: 0 | G48: 0 | H48: 45
B49: DS Pama | C49: 0 | D49: 0 | E49: 2 | F49: 0 | G49: 0 | H49: 9
B50: CRTS Fada | C50: 0 | D50: 0 | E50: 1 | F50: 0 | G50: 0 | H50: 2
B51: ENSP | C51: 1 | D51: 0 | E51: 0 | F51: 0 | G51: 0 | H51: 0
B52: OST | C52: 0 | D52: 0 | E52: 0 | F52: 0 | G52: 0 | H52: 0
A53: Guiriko | C53: =SUM(C55:C69) -> 8 | D53: =SUM(D55:D69) -> 1 | E53: =SUM(E55:E69) -> 100 | F53: =SUM(F55:F69) -> 27 | G53: =SUM(G55:G69) -> 6 | H53: =SUM(H55:H69) -> 106
B54: Administration DRS | C54: 5 | D54: 0 | E54: 1 | F54: 1 | G54: 2 | H54: 0
B55: CHUSS | C55: 5 | D55: 1 | E55: 51 | F55: 7 | G55: 4 | H55: 0
B56: CHU PALA | C56: 1 | D56: 0 | E56: 19 | F56: 1 | G56: 0 | H56: 0
B57: DS Dafra | C57: 0 | D57: 0 | E57: 8 | F57: 1 | G57: 1 | H57: 13
B58: DS Dande | C58: 0 | D58: 0 | E58: 0 | F58: 4 | G58: 0 | H58: 14
B59: DS Do | C59: 0 | D59: 0 | E59: 7 | F59: 1 | G59: 0 | H59: 18
B60: DS Hounde | C60: 0 | D60: 0 | E60: 0 | F60: 0 | G60: 0 | H60: 17
B61: DS Karangasso Vigue | C61: 0 | D61: 0 | E61: 1 | F61: 0 | G61: 1 | H61: 14
B62: DS Léna | C62: 0 | D62: 0 | E62: 0 | F62: 0 | G62: 0 | H62: 10
B63: DS N'Dorola | C63: 0 | D63: 0 | E63: 2 | F63: 0 | G63: 0 | H63: 14
B64: DS Orodara | C64: 0 | D64: 0 | E64: 7 | F64: 0 | G64: 0 | H64: 4
B65: ANSSEAT | C65: 0 | D65: 0 | E65: 0 | F65: 1 | G65: 0 | H65: 0
... B69: OST | C69: 0 | D69: 0 | E69: 0 | F69: 0 | G69: 0 | H69: 0
A70: Kadiogo | C70: =SUM(C71:C85) -> 15 | D70: =SUM(D71:D85) -> 5 | E70: =SUM(E71:E85) -> 162 | F70: =SUM(F71:F85) -> 11 | G70: =SUM(G71:G85) -> 4 | H70: =SUM(H71:H85) -> 81
B71: Administration DRS | C71: 3 | D71: 1 | E71: 0 | F71: 0 | G71: 1 | H71: 0
B72: CHU Bogodogo | C72: 1 | D72: 2 | E72: 36 | F72: 4 | G72: 0 | H72: 0
B73: CHU Pédiatrique CDG | C73: 2 | D73: 0 | E73: 23 | F73: 2 | G73: 0 | H73: 0
B74: CHU Tengandogo | C74: 1 | D74: 1 | E74: 34 | F74: 0 | G74: 0 | H74: 0
B75: CHU Yalgado | C75: 6 | D75: 1 | E75: 55 | F75: 1 | G75: 0 | H75: 0
B76: DS Baskuy | C76: 0 | D76: 0 | E76: 0 | F76: 0 | G76: 0 | H76: 0
B77: DS Bogodogo | C77: 1 | D77: 0 | E77: 0 | F77: 0 | G77: 0 | H77: 32
B78: DS Boulmiougou | C78: 0 | D78: 0 | E78: 4 | F78: 1 | G78: 0 | H78: 19
B79: DS Nongr-Massom | C79: 0 | D79: 0 | E79: 6 | F79: 1 | G79: 0 | H79: 10
B80: DS Sig-Noghin | C80: 0 | D80: 0 | E80: 0 | F80: 0 | G80: 1 | H80: 19
B81: ANSSEAT
B82: CRTS Ouagadougou | C82: 0 | D82: 0 | E82: 4 | F82: 0 | G82: 1 | H82: 1
B83: ENSP
B84: INSP
B85: OST | C85: 1 | D85: 0 | E85: 0 | F85: 2 | G85: 1 | H85: 0
A86: Koulsé | C86: =SUM(C87:C97) -> 7 | D86: =SUM(D87:D97) -> 4 | E86: =SUM(E87:E97) -> 47 | F86: =SUM(F87:F97) -> 1 | G86: =SUM(G87:G97) -> 0 | H86: =SUM(H87:H97) -> 107
B87: Administration DRS | C87: 2 | D87: 2 | E87: 0 | F87: 0 | G87: 0 | H87: 0
B88: CHR de KAYA | C88: 3 | D88: 2 | E88: 24 | F88: 1 | G88: 0 | H88: 0
B89: DS Barsalogho | C89: 0 | D89: 0 | E89: 4 | F89: 0 | G89: 0 | H89: 9
B90: DS Boulsa | C90: 0 | D90: 0 | E90: 5 | F90: 0 | G90: 0 | H90: 23
B91: DS Boussouma | C91: 0 | D91: 0 | E91: 1 | F91: 0 | G91: 0 | H91: 17
B92: DS Kaya | C92: 1 | D92: 0 | E92: 2 | F92: 0 | G92: 0 | H92: 26
B93: DS Kongoussi | C93: 0 | D93: 0 | E93: 8 | F93: 0 | G93: 0 | H93: 19
B94: DS Tougouri | C94: 0 | D94: 0 | E94: 0 | F94: 0 | G94: 0 | H94: 11
B95: DPD/PS Kaya | C95: 0 | D95: 0 | E95: 3 | F95: 0 | G95: 0 | H95: 2
B96: ENSP | C96: 1 | D96: 0 | E96: 0 | F96: 0 | G96: 0 | H96: 0
B97: OST | C97: 0 | D97: 0 | E97: 0 | F97: 0 | G97: 0 | H97: 0
A98: Liptako | C98: =SUM(C99:C106) -> 1 | D98: =SUM(D99:D106) -> 1 | E98: =SUM(E99:E106) -> 40 | F98: =SUM(F99:F106) -> 2 | G98: =SUM(G99:G106) -> 1 | H98: =SUM(H99:H106) -> 94
B99: Administration DRS | C99: 1 | D99: 0 | E99: 0 | F99: 0 | G99: 0 | H99: 0
B100: CHR de Dori | C100: 0 | D100: 0 | E100: 29 | F100: 2 | G100: 1 | H100: 0
B101: DS Dori | C101: 0 | D101: 1 | E101: 5 | F101: 0 | G101: 0 | H101: 42
B102: DS Gorom Gorom | C102: 0 | D102: 0 | E102: 4 | F102: 0 | G102: 0 | H102: 31
B103: DS Sebba | C103: 0 | D103: 0 | E103: 2 | F103: 0 | G103: 0 | H103: 17
B104: DPD/PS Dori | C104: 0 | D104: 0 | E104: 0 | F104: 0 | G104: 0 | H104: 4
B105: ENSP | C105: 0 | D105: 0 | E105: 0 | F105: 0 | G105: 0 | H105: 0
B106: OST | C106: 0 | D106: 0 | E106: 0 | F106: 0 | G106: 0 | H106: 0
A107: Nakambé | C107: =SUM(C108:C120) -> 5 | D107: =SUM(D108:D120) -> 5 | E107: =SUM(E108:E120) -> 61 | F107: =SUM(F108:F120) -> 5 | G107: =SUM(G108:G120) -> 2 | H107: =SUM(H108:H120) -> 98
B108: Administration DRS | C108: 1 | D108: 1 | E108: 0 | F108: 0 | G108: 0 | H108: 0
